Workbook

Sheet Read Me
A1: Read Me — what is derived and what needs a human
A3: TABS
A4: UK Persona Matrix | B4: The summary Ian asked for. All live formulas.
A5: UK Target Institutions | B5: The denominator. Column D is the only editable column — set Yes/No on every row.
A6: UK Institution Coverage | B6: Institution-by-institution backing data behind the matrix.
A7: Persona Gaps & Priorities | B7: Which target institutions are missing which persona, ranked by how much we already hold there.
A8: Monthly Persona Email Report | B8: Template. Three month blocks. Target pre-set at 2 per persona per month.
A9: Marketing Performance Report | B9: Rolling template: headline metrics, by content type, best vs worst.
A10: Persona - To Review | B10: Contacts whose persona needs a human call.
A11: Zip Import Audit | B11: Where every contact from single_uni.zip landed.
A13: DERIVED, NOT SOURCE DATA
A14: Persona | B14: Filled from job title using rules built from the 6,057 contacts already classified in this workbook. Validated at 98.4% agreement against those. Contacts already carrying a persona were not touched.
A15: Research Tier | B15: Senior / Operational / Academic, from job title. Academic covers professors, fellows and researchers — relevant contacts, but not the buying persona.
A16: Country | B16: Where Region was blank, taken from the email domain: .uk to UK, .edu to USA, .ae to UAE.
A17: Institution (canonical) | B17: Name variants merged, e.g. "The University of Edinburgh" and "University of Edinburgh".
A18: Type (derived) | B18: Organisation type guessed from the name. Wrong in places — correct it in column D of UK Target Institutions.
A19: Snov Status | B19: Contacts imported from single_uni.zip that had no status were set to "valid" on your instruction that the zip contacts are all valid. They are identifiable by Source(s) beginning "single_uni:". No pre-existing status was overwritten.
A20: Alternate Email | B20: Where the same person appeared twice with two addresses, the rows were merged and the second address kept here. No email was discarded.
A22: STILL NEEDS A HUMAN
A23: 1. The target list | B23: Set column D on UK Target Institutions for every row, and add any institution we hold no contacts for. Until then the coverage figure counts only what we already have.
A24: 2. Persona - To Review | B24: Research/Finance hybrids and titles with no functional signal (COO, CEO, Registrar).
A25: 3. Email activity | B25: The blank blocks on the matrix and the two report tabs need the platform export.

Sheet UK Persona Matrix
A1: UK Persona and Audience Matrix
A2: Every figure is a live formula. Edit the target list or fix a persona on a contact sheet and this updates.
A4: INSTITUTION COVERAGE
A5: Relevant UK institutions (target list) | B5: =COUNTIF('UK Target Institutions'!$D$2:$D$727,"Yes") -> 308 | G5: Driven by column D of UK Target Institutions.
A6: Of those, we hold contact data for | B6: =COUNTIFS('UK Target Institutions'!$D$2:$D$727,"Yes",'UK Target Institutions'!$E$2:$E$727,">0") -> 308
A7: Institutions with no contacts at all | B7: =B5-B6 -> 0
A8: Coverage | B8: =IFERROR(B6/B5,"") -> 1
A9: Still to be classified Yes/No | B9: =COUNTIF('UK Target Institutions'!$D$2:$D$727,"Review") -> 0 | G9: Set these in column D of UK Target Institutions.
A11: CONTACTS BY PERSONA — target institutions only
A12: Persona | B12: Contacts | C12: Institutions | D12: Valid email | E12: % of target
A13: Research — total | B13: =SUMIFS('UK Institution Coverage'!$F$2:$F$727,'UK Institution Coverage'!$D$2:$D$727,"Yes") -> 4197 | C13: =COUNTIFS('UK Institution Coverage'!$F$2:$F$727,">0",'UK Institution Coverage'!$D$2:$D$727,"Yes") -> 273 | E13: =IFERROR(C13/$B$5,"") -> 0.88636364
A14: · Senior / executive | B14: =SUMIFS('UK Institution Coverage'!$G$2:$G$727,'UK Institution Coverage'!$D$2:$D$727,"Yes") -> 2016 | C14: =COUNTIFS('UK Institution Coverage'!$G$2:$G$727,">0",'UK Institution Coverage'!$D$2:$D$727,"Yes") -> 236 | E14: =IFERROR(C14/$B$5,"") -> 0.76623377
A15: · Operational | B15: =SUMIFS('UK Institution Coverage'!$H$2:$H$727,'UK Institution Coverage'!$D$2:$D$727,"Yes") -> 1949 | C15: =COUNTIFS('UK Institution Coverage'!$H$2:$H$727,">0",'UK Institution Coverage'!$D$2:$D$727,"Yes") -> 183 | E15: =IFERROR(C15/$B$5,"") -> 0.59415584
A16: · Academic staff | B16: =SUMIFS('UK Institution Coverage'!$I$2:$I$727,'UK Institution Coverage'!$D$2:$D$727,"Yes") -> 198 | C16: =COUNTIFS('UK Institution Coverage'!$I$2:$I$727,">0",'UK Institution Coverage'!$D$2:$D$727,"Yes") -> 84 | E16: =IFERROR(C16/$B$5,"") -> 0.27272727
A17: Finance | B17: =SUMIFS('UK Institution Coverage'!$J$2:$J$727,'UK Institution Coverage'!$D$2:$D$727,"Yes") -> 898 | C17: =COUNTIFS('UK Institution Coverage'!$J$2:$J$727,">0",'UK Institution Coverage'!$D$2:$D$727,"Yes") -> 188 | E17: =IFERROR(C17/$B$5,"") -> 0.61038961
A18: IT/Systems | B18: =SUMIFS('UK Institution Coverage'!$K$2:$K$727,'UK Institution Coverage'!$D$2:$D$727,"Yes") -> 430 | C18: =COUNTIFS('UK Institution Coverage'!$K$2:$K$727,">0",'UK Institution Coverage'!$D$2:$D$727,"Yes") -> 159 | E18: =IFERROR(C18/$B$5,"") -> 0.51623377
A19: Still unclassified | B19: =SUMIFS('UK Institution Coverage'!$L$2:$L$727,'UK Institution Coverage'!$D$2:$D$727,"Yes") -> 200 | C19: =COUNTIFS('UK Institution Coverage'!$L$2:$L$727,">0",'UK Institution Coverage'!$D$2:$D$727,"Yes") -> 66 | E19: =IFERROR(C19/$B$5,"") -> 0.21428571
A20: All UK contacts at target institutions | B20: =SUMIFS('UK Institution Coverage'!$E$2:$E$727,'UK Institution Coverage'!$D$2:$D$727,"Yes") -> 5832
A21: Valid email addresses among them | B21: =SUMIFS('UK Institution Coverage'!$N$2:$N$727,'UK Institution Coverage'!$D$2:$D$727,"Yes") -> 3539
A23: PERSONA GAPS
A24: Holding all three personas | B24: =COUNTIFS('UK Institution Coverage'!$M$2:$M$727,3,'UK Institution Coverage'!$D$2:$D$727,"Yes") -> 138
A25: Holding two | B25: =COUNTIFS('UK Institution Coverage'!$M$2:$M$727,2,'UK Institution Coverage'!$D$2:$D$727,"Yes") -> 48
A26: Holding one | B26: =COUNTIFS('UK Institution Coverage'!$M$2:$M$727,1,'UK Institution Coverage'!$D$2:$D$727,"Yes") -> 110
A27: Average personas per institution | B27: =IFERROR(ROUND(SUMIFS('UK Institution Coverage'!$M$2:$M$727,'UK Institution Coverage'!$D$2:$D$727,"Yes")/B6,2),"") -> 2.01 | G27: Out of 3.
A28: No Research contact | B28: =COUNTIFS('UK Institution Coverage'!$F$2:$F$727,0,'UK Institution Coverage'!$D$2:$D$727,"Yes") -> 35
A29: No Finance contact | B29: =COUNTIFS('UK Institution Coverage'!$J$2:$J$727,0,'UK Institution Coverage'!$D$2:$D$727,"Yes") -> 120
A30: No IT/Systems contact | B30: =COUNTIFS('UK Institution Coverage'!$K$2:$K$727,0,'UK Institution Coverage'!$D$2:$D$727,"Yes") -> 149
A32: ARE THE EMAILS CURRENT AND VALID? (all UK contacts)
A33: Verified valid | B33: =COUNTIFS('Relevant - In CRM valid'!$G$2:$G$4699,"UK",'Relevant - In CRM valid'!$Q$2:$Q$4699,"valid")+COUNTIFS('Relevant - In CRM unknown'!$G$2:$G$253,"UK",'Relevant - In CRM unknown'!$Q$2:$Q$253,"valid")+COUNTIFS('Relevant - IN NOW CRM valid'!$G$2:$G$2328,"UK",'Relevant - IN NOW CRM valid'!$Q$2:$Q$2328,"valid")+COUNTIFS('Relevant - IN NOW CRM unknown'!$G$2:$G$1227,"UK",'Relevant - IN NOW CRM unknown'!$Q$2:$Q$1227,"valid")+COUNTIFS('Relevant - Not CRM not valid'!$G$2:$G$416,"UK",'Relevant - Not CRM not valid'!$Q$2:$Q$416,"valid")+COUNTIFS('Relevant - In CRM not valid'!$G$2:$G$46,"UK",'Relevant - In CRM not valid'!$Q$2:$Q$46,"valid") -> 4034
A34: Unknown | B34: =COUNTIFS('Relevant - In CRM valid'!$G$2:$G$4699,"UK",'Relevant - In CRM valid'!$Q$2:$Q$4699,"unknown")+COUNTIFS('Relevant - In CRM unknown'!$G$2:$G$253,"UK",'Relevant - In CRM unknown'!$Q$2:$Q$253,"unknown")+COUNTIFS('Relevant - IN NOW CRM valid'!$G$2:$G$2328,"UK",'Relevant - IN NOW CRM valid'!$Q$2:$Q$2328,"unknown")+COUNTIFS('Relevant - IN NOW CRM unknown'!$G$2:$G$1227,"UK",'Relevant - IN NOW CRM unknown'!$Q$2:$Q$1227,"unknown")+COUNTIFS('Relevant - Not CRM not valid'!$G$2:$G$416,"UK",'Relevant - Not CRM not valid'!$Q$2:$Q$416,"unknown")+COUNTIFS('Relevant - In CRM not valid'!$G$2:$G$46,"UK",'Relevant - In CRM not valid'!$Q$2:$Q$46,"unknown") -> 1889
A35: Not valid | B35: =COUNTIFS('Relevant - In CRM valid'!$G$2:$G$4699,"UK",'Relevant - In CRM valid'!$Q$2:$Q$4699,"not valid")+COUNTIFS('Relevant - In CRM unknown'!$G$2:$G$253,"UK",'Relevant - In CRM unknown'!$Q$2:$Q$253,"not valid")+COUNTIFS('Relevant - IN NOW CRM valid'!$G$2:$G$2328,"UK",'Relevant - IN NOW CRM valid'!$Q$2:$Q$2328,"not valid")+COUNTIFS('Relevant - IN NOW CRM unknown'!$G$2:$G$1227,"UK",'Relevant - IN NOW CRM unknown'!$Q$2:$Q$1227,"not valid")+COUNTIFS('Relevant - Not CRM not valid'!$G$2:$G$416,"UK",'Relevant - Not CRM not valid'!$Q$2:$Q$416,"not valid")+COUNTIFS('Relevant - In CRM not valid'!$G$2:$G$46,"UK",'Relevant - In CRM not valid'!$Q$2:$Q$46,"not valid") -> 431
A36: No status recorded | B36: =COUNTIFS('Relevant - In CRM valid'!$G$2:$G$4699,"UK",'Relevant - In CRM valid'!$Q$2:$Q$4699,"")+COUNTIFS('Relevant - In CRM unknown'!$G$2:$G$253,"UK",'Relevant - In CRM unknown'!$Q$2:$Q$253,"")+COUNTIFS('Relevant - IN NOW CRM valid'!$G$2:$G$2328,"UK",'Relevant - IN NOW CRM valid'!$Q$2:$Q$2328,"")+COUNTIFS('Relevant - IN NOW CRM unknown'!$G$2:$G$1227,"UK",'Relevant - IN NOW CRM unknown'!$Q$2:$Q$1227,"")+COUNTIFS('Relevant - Not CRM not valid'!$G$2:$G$416,"UK",'Relevant - Not CRM not valid'!$Q$2:$Q$416,"")+COUNTIFS('Relevant - In CRM not valid'!$G$2:$G$46,"UK",'Relevant - In CRM not valid'!$Q$2:$Q$46,"") -> 31
A37: No email address at all | B37: =COUNTIFS('Relevant - In CRM valid'!$G$2:$G$4699,"UK",'Relevant - In CRM valid'!$H$2:$H$4699,"")+COUNTIFS('Relevant - In CRM unknown'!$G$2:$G$253,"UK",'Relevant - In CRM unknown'!$H$2:$H$253,"")+COUNTIFS('Relevant - IN NOW CRM valid'!$G$2:$G$2328,"UK",'Relevant - IN NOW CRM valid'!$H$2:$H$2328,"")+COUNTIFS('Relevant - IN NOW CRM unknown'!$G$2:$G$1227,"UK",'Relevant - IN NOW CRM unknown'!$H$2:$H$1227,"")+COUNTIFS('Relevant - Not CRM not valid'!$G$2:$G$416,"UK",'Relevant - Not CRM not valid'!$H$2:$H$416,"")+COUNTIFS('Relevant - In CRM not valid'!$G$2:$G$46,"UK",'Relevant - In CRM not valid'!$H$2:$H$46,"") -> 32
A39: EMAIL ACTIVITY — fill from the platform export
A40: Persona | B40: Sent last month | C40: Content received | D40: Planned next month | E40: Verdict
A41: Research — senior | E41: =IF(B41="","",IF(B41>3,"OVER-CONTACTED",IF(B41<2,"under-contacted","on target")))
A42: Research — operational | E42: =IF(B42="","",IF(B42>3,"OVER-CONTACTED",IF(B42<2,"under-contacted","on target")))
A43: Finance | E43: =IF(B43="","",IF(B43>3,"OVER-CONTACTED",IF(B43<2,"under-contacted","on target")))
A44: IT/Systems | E44: =IF(B44="","",IF(B44>3,"OVER-CONTACTED",IF(B44<2,"under-contacted","on target")))
A45: Target: 2 emails per persona per month, 3 maximum.

Sheet UK Target Institutions
A1: Institution (canonical) | B1: Name as it appears | C1: Type (derived) | D1: In target list? | E1: Contacts held | F1: Personas held | G1: Coverage status | H1: Decision basis
A2: manchester university | B2: University of Manchester | C2: University | D2: Yes | E2: =IFERROR(INDEX('UK Institution Coverage'!$E$2:$E$727,MATCH($A2,'UK Institution Coverage'!$A$2:$A$727,0)),0) -> 205 | F2: =IFERROR(INDEX('UK Institution Coverage'!$M$2:$M$727,MATCH($A2,'UK Institution Coverage'!$A$2:$A$727,0)),0) -> 3 | G2: =IF($D2<>"Yes","not in target",IF($E2=0,"NO CONTACTS",IF($F2=3,"all 3 personas","partial - "&$F2&" of 3"))) -> all 3 personas | H2: confirmed
A3: king s college london | B3: King's College London | C3: University college | D3: Yes | E3: =IFERROR(INDEX('UK Institution Coverage'!$E$2:$E$727,MATCH($A3,'UK Institution Coverage'!$A$2:$A$727,0)),0) -> 177 | F3: =IFERROR(INDEX('UK Institution Coverage'!$M$2:$M$727,MATCH($A3,'UK Institution Coverage'!$A$2:$A$727,0)),0) -> 3 | G3: =IF($D3<>"Yes","not in target",IF($E3=0,"NO CONTACTS",IF($F3=3,"all 3 personas","partial - "&$F3&" of 3"))) -> all 3 personas | H3: confirmed
A4: coventry university | B4: Coventry University | C4: University | D4: Yes | E4: =IFERROR(INDEX('UK Institution Coverage'!$E$2:$E$727,MATCH($A4,'UK Institution Coverage'!$A$2:$A$727,0)),0) -> 168 | F4: =IFERROR(INDEX('UK Institution Coverage'!$M$2:$M$727,MATCH($A4,'UK Institution Coverage'!$A$2:$A$727,0)),0) -> 3 | G4: =IF($D4<>"Yes","not in target",IF($E4=0,"NO CONTACTS",IF($F4=3,"all 3 personas","partial - "&$F4&" of 3"))) -> all 3 personas | H4: confirmed
A5: sussex university | B5: University of Sussex | C5: University | D5: Yes | E5: =IFERROR(INDEX('UK Institution Coverage'!$E$2:$E$727,MATCH($A5,'UK Institution Coverage'!$A$2:$A$727,0)),0) -> 158 | F5: =IFERROR(INDEX('UK Institution Coverage'!$M$2:$M$727,MATCH($A5,'UK Institution Coverage'!$A$2:$A$727,0)),0) -> 3 | G5: =IF($D5<>"Yes","not in target",IF($E5=0,"NO CONTACTS",IF($F5=3,"all 3 personas","partial - "&$F5&" of 3"))) -> all 3 personas | H5: confirmed
A6: edinburgh university | B6: University of Edinburgh | C6: University | D6: Yes | E6: =IFERROR(INDEX('UK Institution Coverage'!$E$2:$E$727,MATCH($A6,'UK Institution Coverage'!$A$2:$A$727,0)),0) -> 131 | F6: =IFERROR(INDEX('UK Institution Coverage'!$M$2:$M$727,MATCH($A6,'UK Institution Coverage'!$A$2:$A$727,0)),0) -> 3 | G6: =IF($D6<>"Yes","not in target",IF($E6=0,"NO CONTACTS",IF($F6=3,"all 3 personas","partial - "&$F6&" of 3"))) -> all 3 personas | H6: confirmed
A7: liverpool university | B7: University of Liverpool | C7: University | D7: Yes | E7: =IFERROR(INDEX('UK Institution Coverage'!$E$2:$E$727,MATCH($A7,'UK Institution Coverage'!$A$2:$A$727,0)),0) -> 124 | F7: =IFERROR(INDEX('UK Institution Coverage'!$M$2:$M$727,MATCH($A7,'UK Institution Coverage'!$A$2:$A$727,0)),0) -> 3 | G7: =IF($D7<>"Yes","not in target",IF($E7=0,"NO CONTACTS",IF($F7=3,"all 3 personas","partial - "&$F7&" of 3"))) -> all 3 personas | H7: confirmed
A8: sheffield university | B8: The University of Sheffield | C8: University | D8: Yes | E8: =IFERROR(INDEX('UK Institution Coverage'!$E$2:$E$727,MATCH($A8,'UK Institution Coverage'!$A$2:$A$727,0)),0) -> 115 | F8: =IFERROR(INDEX('UK Institution Coverage'!$M$2:$M$727,MATCH($A8,'UK Institution Coverage'!$A$2:$A$727,0)),0) -> 3 | G8: =IF($D8<>"Yes","not in target",IF($E8=0,"NO CONTACTS",IF($F8=3,"all 3 personas","partial - "&$F8&" of 3"))) -> all 3 personas | H8: confirmed
A9: manchester metropolitan university | B9: The Manchester Metropolitan University | C9: University | D9: Yes | E9: =IFERROR(INDEX('UK Institution Coverage'!$E$2:$E$727,MATCH($A9,'UK Institution Coverage'!$A$2:$A$727,0)),0) -> 109 | F9: =IFERROR(INDEX('UK Institution Coverage'!$M$2:$M$727,MATCH($A9,'UK Institution Coverage'!$A$2:$A$727,0)),0) -> 3 | G9: =IF($D9<>"Yes","not in target",IF($E9=0,"NO CONTACTS",IF($F9=3,"all 3 personas","partial - "&$F9&" of 3"))) -> all 3 personas | H9: confirmed
A10: york university | B10: University of York | C10: University | D10: Yes | E10: =IFERROR(INDEX('UK Institution Coverage'!$E$2:$E$727,MATCH($A10,'UK Institution Coverage'!$A$2:$A$727,0)),0) -> 92 | F10: =IFERROR(INDEX('UK Institution Coverage'!$M$2:$M$727,MATCH($A10,'UK Institution Coverage'!$A$2:$A$727,0)),0) -> 3 | G10: =IF($D10<>"Yes","not in target",IF($E10=0,"NO CONTACTS",IF($F10=3,"all 3 personas","partial - "&$F10&" of 3"))) -> all 3 personas | H10: confirmed
A11: cardiff university | B11: Cardiff University | C11: University | D11: Yes | E11: =IFERROR(INDEX('UK Institution Coverage'!$E$2:$E$727,MATCH($A11,'UK Institution Coverage'!$A$2:$A$727,0)),0) -> 86 | F11: =IFERROR(INDEX('UK Institution Coverage'!$M$2:$M$727,MATCH($A11,'UK Institution Coverage'!$A$2:$A$727,0)),0) -> 3 | G11: =IF($D11<>"Yes","not in target",IF($E11=0,"NO CONTACTS",IF($F11=3,"all 3 personas","partial - "&$F11&" of 3"))) -> all 3 personas | H11: confirmed
A12: exeter university | B12: University Of Exeter | C12: University | D12: Yes | E12: =IFERROR(INDEX('UK Institution Coverage'!$E$2:$E$727,MATCH($A12,'UK Institution Coverage'!$A$2:$A$727,0)),0) -> 95 | F12: =IFERROR(INDEX('UK Institution Coverage'!$M$2:$M$727,MATCH($A12,'UK Institution Coverage'!$A$2:$A$727,0)),0) -> 3 | G12: =IF($D12<>"Yes","not in target",IF($E12=0,"NO CONTACTS",IF($F12=3,"all 3 personas","partial - "&$F12&" of 3"))) -> all 3 personas | H12: confirmed
A13: newcastle university | B13: Newcastle University | C13: University | D13: Yes | E13: =IFERROR(INDEX('UK Institution Coverage'!$E$2:$E$727,MATCH($A13,'UK Institution Coverage'!$A$2:$A$727,0)),0) -> 87 | F13: =IFERROR(INDEX('UK Institution Coverage'!$M$2:$M$727,MATCH($A13,'UK Institution Coverage'!$A$2:$A$727,0)),0) -> 2 | G13: =IF($D13<>"Yes","not in target",IF($E13=0,"NO CONTACTS",IF($F13=3,"all 3 personas","partial - "&$F13&" of 3"))) -> partial - 2 of 3 | H13: confirmed
... A727: yorkshire universities | B727: Yorkshire Universities | C727: University | D727: Yes | E727: =IFERROR(INDEX('UK Institution Coverage'!$E$2:$E$727,MATCH($A727,'UK Institution Coverage'!$A$2:$A$727,0)),0) -> 1 | F727: =IFERROR(INDEX('UK Institution Coverage'!$M$2:$M$727,MATCH($A727,'UK Institution Coverage'!$A$2:$A$727,0)),0) -> 0 | G727: =IF($D727<>"Yes","not in target",IF($E727=0,"NO CONTACTS",IF($F727=3,"all 3 personas","partial - "&$F727&" of 3"))) -> partial - 0 of 3 | H727: confirmed
A729: Column D is the only column to edit. Set Yes / No for every row, including the "Review" ones. Add any institution we hold no contacts for as a new row at the bottom with D = Yes — the matrix will count it as a gap.

Sheet UK Institution Coverage
A1: Institution (canonical) | B1: Name as it appears | C1: Type | D1: In target list | E1: Contacts | F1: Research | G1: · Senior | H1: · Operational | I1: · Academic | J1: Finance | K1: IT/Systems | L1: Unclassified | M1: Personas held | N1: Valid emails | O1: Missing personas
A2: manchester university | B2: University of Manchester | C2: University | D2: =IFERROR(INDEX('UK Target Institutions'!$D$2:$D$727,MATCH($A2,'UK Target Institutions'!$A$2:$A$727,0)),"") -> Yes | E2: =COUNTIFS('Relevant - In CRM valid'!$T$2:$T$4699,$A2,'Relevant - In CRM valid'!$G$2:$G$4699,"UK")+COUNTIFS('Relevant - In CRM unknown'!$T$2:$T$253,$A2,'Relevant - In CRM unknown'!$G$2:$G$253,"UK")+COUNTIFS('Relevant - IN NOW CRM valid'!$T$2:$T$2328,$A2,'Relevant - IN NOW CRM valid'!$G$2:$G$2328,"UK")+COUNTIFS('Relevant - IN NOW CRM unknown'!$T$2:$T$1227,$A2,'Relevant - IN NOW CRM unknown'!$G$2:$G$1227,"UK")+COUNTIFS('Relevant - Not CRM not valid'!$T$2:$T$416,$A2,'Relevant - Not CRM not valid'!$G$2:$G$416,"UK")+COUNTIFS('Relevant - In CRM not valid'!$T$2:$T$46,$A2,'Relevant - In CRM not valid'!$G$2:$G$46,"UK") -> 205 | F2: =COUNTIFS('Relevant - In CRM valid'!$T$2:$T$4699,$A2,'Relevant - In CRM valid'!$G$2:$G$4699,"UK",'Relevant - In CRM valid'!$M$2:$M$4699,"Research")+COUNTIFS('Relevant - In CRM unknown'!$T$2:$T$253,$A2,'Relevant - In CRM unknown'!$G$2:$G$253,"UK",'Relevant - In CRM unknown'!$M$2:$M$253,"Research")+COUNTIFS('Relevant - IN NOW CRM valid'!$T$2:$T$2328,$A2,'Relevant - IN NOW CRM valid'!$G$2:$G$2328,"UK",'Relevant - IN NOW CRM valid'!$M$2:$M$2328,"Research")+COUNTIFS('Relevant - IN NOW CRM unknown'!$T$2:$T$1227,$A2,'Relevant - IN NOW CRM unknown'!$G$2:$G$1227,"UK",'Relevant - IN NOW CRM unknown'!$M$2:$M$1227,"Research")+COUNTIFS('Relevant - Not CRM not valid'!$T$2:$T$416,$A2,'Relevant - Not CRM not valid'!$G$2:$G$416,"UK",'Relevant - Not CRM not valid'!$M$2:$M$416,"Research")+COUNTIFS('Relevant - In CRM not valid'!$T$2:$T$46,$A2,'Relevant - In CRM not valid'!$G$2:$G$46,"UK",'Relevant - In CRM not valid'!$M$2:$M$46,"Research") -> 156 | G2: =COUNTIFS('Relevant - In CRM valid'!$T$2:$T$4699,$A2,'Relevant - In CRM valid'!$G$2:$G$4699,"UK",'Relevant - In CRM valid'!$M$2:$M$4699,"Research",'Relevant - In CRM valid'!$R$2:$R$4699,"Senior")+COUNTIFS('Relevant - In CRM unknown'!$T$2:$T$253,$A2,'Relevant - In CRM unknown'!$G$2:$G$253,"UK",'Relevant - In CRM unknown'!$M$2:$M$253,"Research",'Relevant - In CRM unknown'!$R$2:$R$253,"Senior")+COUNTIFS('Relevant - IN NOW CRM valid'!$T$2:$T$2328,$A2,'Relevant - IN NOW CRM valid'!$G$2:$G$2328,"UK",'Relevant - IN NOW CRM valid'!$M$2:$M$2328,"Research",'Relevant - IN NOW CRM valid'!$R$2:$R$2328,"Senior")+COUNTIFS('Relevant - IN NOW CRM unknown'!$T$2:$T$1227,$A2,'Relevant - IN NOW CRM unknown'!$G$2:$G$1227,"UK",'Relevant - IN NOW CRM unknown'!$M$2:$M$1227,"Research",'Relevant - IN NOW CRM unknown'!$R$2:$R$1227,"Senior")+COUNTIFS('Relevant - Not CRM not valid'!$T$2:$T$416,$A2,'Relevant - Not CRM not valid'!$G$2:$G$416,"UK",'Relevant - Not CRM not valid'!$M$2:$M$416,"Research",'Relevant - Not CRM not valid'!$R$2:$R$416,"Senior")+COUNTIFS('Relevant - In CRM not valid'!$T$2:$T$46,$A2,'Relevant - In CRM not valid'!$G$2:$G$46,"UK",'Relevant - In CRM not valid'!$M$2:$M$46,"Research",'Relevant - In CRM not valid'!$R$2:$R$46,"Senior") -> 30 | H2: =COUNTIFS('Relevant - In CRM valid'!$T$2:$T$4699,$A2,'Relevant - In CRM valid'!$G$2:$G$4699,"UK",'Relevant - In CRM valid'!$M$2:$M$4699,"Research",'Relevant - In CRM valid'!$R$2:$R$4699,"Operational")+COUNTIFS('Relevant - In CRM unknown'!$T$2:$T$253,$A2,'Relevant - In CRM unknown'!$G$2:$G$253,"UK",'Relevant - In CRM unknown'!$M$2:$M$253,"Research",'Relevant - In CRM unknown'!$R$2:$R$253,"Operational")+COUNTIFS('Relevant - IN NOW CRM valid'!$T$2:$T$2328,$A2,'Relevant - IN NOW CRM valid'!$G$2:$G$2328,"UK",'Relevant - IN NOW CRM valid'!$M$2:$M$2328,"Research",'Relevant - IN NOW CRM valid'!$R$2:$R$2328,"Operational")+COUNTIFS('Relevant - IN NOW CRM unknown'!$T$2:$T$1227,$A2,'Relevant - IN NOW CRM unknown'!$G$2:$G$1227,"UK",'Relevant - IN NOW CRM unknown'!$M$2:$M$1227,"Research",'Relevant - IN NOW CRM unknown'!$R$2:$R$1227,"Operational")+COUNTIFS('Relevant - Not CRM not valid'!$T$2:$T$416,$A2,'Relevant - Not CRM not valid'!$G$2:$G$416,"UK",'Relevant - Not CRM not valid'!$M$2:$M$416,"Research",'Relevant - Not CRM not valid'!$R$2:$R$416,"Operational")+COUNTIFS('Relevant - In CRM not valid'!$T$2:$T$46,$A2,'Relevant - In CRM not valid'!$G$2:$G$46,"UK",'Relevant - In CRM not valid'!$M$2:$M$46,"Research",'Relevant - In CRM not valid'!$R$2:$R$46,"Operational") -> 118 | I2: =COUNTIFS('Relevant - In CRM valid'!$T$2:$T$4699,$A2,'Relevant - In CRM valid'!$G$2:$G$4699,"UK",'Relevant - In CRM valid'!$M$2:$M$4699,"Research",'Relevant - In CRM valid'!$R$2:$R$4699,"Academic")+COUNTIFS('Relevant - In CRM unknown'!$T$2:$T$253,$A2,'Relevant - In CRM unknown'!$G$2:$G$253,"UK",'Relevant - In CRM unknown'!$M$2:$M$253,"Research",'Relevant - In CRM unknown'!$R$2:$R$253,"Academic")+COUNTIFS('Relevant - IN NOW CRM valid'!$T$2:$T$2328,$A2,'Relevant - IN NOW CRM valid'!$G$2:$G$2328,"UK",'Relevant - IN NOW CRM valid'!$M$2:$M$2328,"Research",'Relevant - IN NOW CRM valid'!$R$2:$R$2328,"Academic")+COUNTIFS('Relevant - IN NOW CRM unknown'!$T$2:$T$1227,$A2,'Relevant - IN NOW CRM unknown'!$G$2:$G$1227,"UK",'Relevant - IN NOW CRM unknown'!$M$2:$M$1227,"Research",'Relevant - IN NOW CRM unknown'!$R$2:$R$1227,"Academic")+COUNTIFS('Relevant - Not CRM not valid'!$T$2:$T$416,$A2,'Relevant - Not CRM not valid'!$G$2:$G$416,"UK",'Relevant - Not CRM not valid'!$M$2:$M$416,"Research",'Relevant - Not CRM not valid'!$R$2:$R$416,"Academic")+COUNTIFS('Relevant - In CRM not valid'!$T$2:$T$46,$A2,'Relevant - In CRM not valid'!$G$2:$G$46,"UK",'Relevant - In CRM not valid'!$M$2:$M$46,"Research",'Relevant - In CRM not valid'!$R$2:$R$46,"Academic") -> 4 | J2: =COUNTIFS('Relevant - In CRM valid'!$T$2:$T$4699,$A2,'Relevant - In CRM valid'!$G$2:$G$4699,"UK",'Relevant - In CRM valid'!$M$2:$M$4699,"Finance")+COUNTIFS('Relevant - In CRM unknown'!$T$2:$T$253,$A2,'Relevant - In CRM unknown'!$G$2:$G$253,"UK",'Relevant - In CRM unknown'!$M$2:$M$253,"Finance")+COUNTIFS('Relevant - IN NOW CRM valid'!$T$2:$T$2328,$A2,'Relevant - IN NOW CRM valid'!$G$2:$G$2328,"UK",'Relevant - IN NOW CRM valid'!$M$2:$M$2328,"Finance")+COUNTIFS('Relevant - IN NOW CRM unknown'!$T$2:$T$1227,$A2,'Relevant - IN NOW CRM unknown'!$G$2:$G$1227,"UK",'Relevant - IN NOW CRM unknown'!$M$2:$M$1227,"Finance")+COUNTIFS('Relevant - Not CRM not valid'!$T$2:$T$416,$A2,'Relevant - Not CRM not valid'!$G$2:$G$416,"UK",'Relevant - Not CRM not valid'!$M$2:$M$416,"Finance")+COUNTIFS('Relevant - In CRM not valid'!$T$2:$T$46,$A2,'Relevant - In CRM not valid'!$G$2:$G$46,"UK",'Relevant - In CRM not valid'!$M$2:$M$46,"Finance") -> 39 | K2: =COUNTIFS('Relevant - In CRM valid'!$T$2:$T$4699,$A2,'Relevant - In CRM valid'!$G$2:$G$4699,"UK",'Relevant - In CRM valid'!$M$2:$M$4699,"IT/Systems")+COUNTIFS('Relevant - In CRM unknown'!$T$2:$T$253,$A2,'Relevant - In CRM unknown'!$G$2:$G$253,"UK",'Relevant - In CRM unknown'!$M$2:$M$253,"IT/Systems")+COUNTIFS('Relevant - IN NOW CRM valid'!$T$2:$T$2328,$A2,'Relevant - IN NOW CRM valid'!$G$2:$G$2328,"UK",'Relevant - IN NOW CRM valid'!$M$2:$M$2328,"IT/Systems")+COUNTIFS('Relevant - IN NOW CRM unknown'!$T$2:$T$1227,$A2,'Relevant - IN NOW CRM unknown'!$G$2:$G$1227,"UK",'Relevant - IN NOW CRM unknown'!$M$2:$M$1227,"IT/Systems")+COUNTIFS('Relevant - Not CRM not valid'!$T$2:$T$416,$A2,'Relevant - Not CRM not valid'!$G$2:$G$416,"UK",'Relevant - Not CRM not valid'!$M$2:$M$416,"IT/Systems")+COUNTIFS('Relevant - In CRM not valid'!$T$2:$T$46,$A2,'Relevant - In CRM not valid'!$G$2:$G$46,"UK",'Relevant - In CRM not valid'!$M$2:$M$46,"IT/Systems") -> 8 | L2: =COUNTIFS('Relevant - In CRM valid'!$T$2:$T$4699,$A2,'Relevant - In CRM valid'!$G$2:$G$4699,"UK",'Relevant - In CRM valid'!$M$2:$M$4699,"")+COUNTIFS('Relevant - In CRM unknown'!$T$2:$T$253,$A2,'Relevant - In CRM unknown'!$G$2:$G$253,"UK",'Relevant - In CRM unknown'!$M$2:$M$253,"")+COUNTIFS('Relevant - IN NOW CRM valid'!$T$2:$T$2328,$A2,'Relevant - IN NOW CRM valid'!$G$2:$G$2328,"UK",'Relevant - IN NOW CRM valid'!$M$2:$M$2328,"")+COUNTIFS('Relevant - IN NOW CRM unknown'!$T$2:$T$1227,$A2,'Relevant - IN NOW CRM unknown'!$G$2:$G$1227,"UK",'Relevant - IN NOW CRM unknown'!$M$2:$M$1227,"")+COUNTIFS('Relevant - Not CRM not valid'!$T$2:$T$416,$A2,'Relevant - Not CRM not valid'!$G$2:$G$416,"UK",'Relevant - Not CRM not valid'!$M$2:$M$416,"")+COUNTIFS('Relevant - In CRM not valid'!$T$2:$T$46,$A2,'Relevant - In CRM not valid'!$G$2:$G$46,"UK",'Relevant - In CRM not valid'!$M$2:$M$46,"") -> 2 | M2: =(F2>0)+(J2>0)+(K2>0) -> 3 | N2: =COUNTIFS('Relevant - In CRM valid'!$T$2:$T$4699,$A2,'Relevant - In CRM valid'!$G$2:$G$4699,"UK",'Relevant - In CRM valid'!$Q$2:$Q$4699,"valid")+COUNTIFS('Relevant - In CRM unknown'!$T$2:$T$253,$A2,'Relevant - In CRM unknown'!$G$2:$G$253,"UK",'Relevant - In CRM unknown'!$Q$2:$Q$253,"valid")+COUNTIFS('Relevant - IN NOW CRM valid'!$T$2:$T$2328,$A2,'Relevant - IN NOW CRM valid'!$G$2:$G$2328,"UK",'Relevant - IN NOW CRM valid'!$Q$2:$Q$2328,"valid")+COUNTIFS('Relevant - IN NOW CRM unknown'!$T$2:$T$1227,$A2,'Relevant - IN NOW CRM unknown'!$G$2:$G$1227,"UK",'Relevant - IN NOW CRM unknown'!$Q$2:$Q$1227,"valid")+COUNTIFS('Relevant - Not CRM not valid'!$T$2:$T$416,$A2,'Relevant - Not CRM not valid'!$G$2:$G$416,"UK",'Relevant - Not CRM not valid'!$Q$2:$Q$416,"valid")+COUNTIFS('Relevant - In CRM not valid'!$T$2:$T$46,$A2,'Relevant - In CRM not valid'!$G$2:$G$46,"UK",'Relevant - In CRM not valid'!$Q$2:$Q$46,"valid") -> 121 | O2: =IF(F2=0,"Research ","")&IF(J2=0,"Finance ","")&IF(K2=0,"IT/Systems","")
A3: king s college london | B3: King's College London | C3: University college | D3: =IFERROR(INDEX('UK Target Institutions'!$D$2:$D$727,MATCH($A3,'UK Target Institutions'!$A$2:$A$727,0)),"") -> Yes | E3: =COUNTIFS('Relevant - In CRM valid'!$T$2:$T$4699,$A3,'Relevant - In CRM valid'!$G$2:$G$4699,"UK")+COUNTIFS('Relevant - In CRM unknown'!$T$2:$T$253,$A3,'Relevant - In CRM unknown'!$G$2:$G$253,"UK")+COUNTIFS('Relevant - IN NOW CRM valid'!$T$2:$T$2328,$A3,'Relevant - IN NOW CRM valid'!$G$2:$G$2328,"UK")+COUNTIFS('Relevant - IN NOW CRM unknown'!$T$2:$T$1227,$A3,'Relevant - IN NOW CRM unknown'!$G$2:$G$1227,"UK")+COUNTIFS('Relevant - Not CRM not valid'!$T$2:$T$416,$A3,'Relevant - Not CRM not valid'!$G$2:$G$416,"UK")+COUNTIFS('Relevant - In CRM not valid'!$T$2:$T$46,$A3,'Relevant - In CRM not valid'!$G$2:$G$46,"UK") -> 177 | F3: =COUNTIFS('Relevant - In CRM valid'!$T$2:$T$4699,$A3,'Relevant - In CRM valid'!$G$2:$G$4699,"UK",'Relevant - In CRM valid'!$M$2:$M$4699,"Research")+COUNTIFS('Relevant - In CRM unknown'!$T$2:$T$253,$A3,'Relevant - In CRM unknown'!$G$2:$G$253,"UK",'Relevant - In CRM unknown'!$M$2:$M$253,"Research")+COUNTIFS('Relevant - IN NOW CRM valid'!$T$2:$T$2328,$A3,'Relevant - IN NOW CRM valid'!$G$2:$G$2328,"UK",'Relevant - IN NOW CRM valid'!$M$2:$M$2328,"Research")+COUNTIFS('Relevant - IN NOW CRM unknown'!$T$2:$T$1227,$A3,'Relevant - IN NOW CRM unknown'!$G$2:$G$1227,"UK",'Relevant - IN NOW CRM unknown'!$M$2:$M$1227,"Research")+COUNTIFS('Relevant - Not CRM not valid'!$T$2:$T$416,$A3,'Relevant - Not CRM not valid'!$G$2:$G$416,"UK",'Relevant - Not CRM not valid'!$M$2:$M$416,"Research")+COUNTIFS('Relevant - In CRM not valid'!$T$2:$T$46,$A3,'Relevant - In CRM not valid'!$G$2:$G$46,"UK",'Relevant - In CRM not valid'!$M$2:$M$46,"Research") -> 173 | G3: =COUNTIFS('Relevant - In CRM valid'!$T$2:$T$4699,$A3,'Relevant - In CRM valid'!$G$2:$G$4699,"UK",'Relevant - In CRM valid'!$M$2:$M$4699,"Research",'Relevant - In CRM valid'!$R$2:$R$4699,"Senior")+COUNTIFS('Relevant - In CRM unknown'!$T$2:$T$253,$A3,'Relevant - In CRM unknown'!$G$2:$G$253,"UK",'Relevant - In CRM unknown'!$M$2:$M$253,"Research",'Relevant - In CRM unknown'!$R$2:$R$253,"Senior")+COUNTIFS('Relevant - IN NOW CRM valid'!$T$2:$T$2328,$A3,'Relevant - IN NOW CRM valid'!$G$2:$G$2328,"UK",'Relevant - IN NOW CRM valid'!$M$2:$M$2328,"Research",'Relevant - IN NOW CRM valid'!$R$2:$R$2328,"Senior")+COUNTIFS('Relevant - IN NOW CRM unknown'!$T$2:$T$1227,$A3,'Relevant - IN NOW CRM unknown'!$G$2:$G$1227,"UK",'Relevant - IN NOW CRM unknown'!$M$2:$M$1227,"Research",'Relevant - IN NOW CRM unknown'!$R$2:$R$1227,"Senior")+COUNTIFS('Relevant - Not CRM not valid'!$T$2:$T$416,$A3,'Relevant - Not CRM not valid'!$G$2:$G$416,"UK",'Relevant - Not CRM not valid'!$M$2:$M$416,"Research",'Relevant - Not CRM not valid'!$R$2:$R$416,"Senior")+COUNTIFS('Relevant - In CRM not valid'!$T$2:$T$46,$A3,'Relevant - In CRM not valid'!$G$2:$G$46,"UK",'Relevant - In CRM not valid'!$M$2:$M$46,"Research",'Relevant - In CRM not valid'!$R$2:$R$46,"Senior") -> 46 | H3: =COUNTIFS('Relevant - In CRM valid'!$T$2:$T$4699,$A3,'Relevant - In CRM valid'!$G$2:$G$4699,"UK",'Relevant - In CRM valid'!$M$2:$M$4699,"Research",'Relevant - In CRM valid'!$R$2:$R$4699,"Operational")+COUNTIFS('Relevant - In CRM unknown'!$T$2:$T$253,$A3,'Relevant - In CRM unknown'!$G$2:$G$253,"UK",'Relevant - In CRM unknown'!$M$2:$M$253,"Research",'Relevant - In CRM unknown'!$R$2:$R$253,"Operational")+COUNTIFS('Relevant - IN NOW CRM valid'!$T$2:$T$2328,$A3,'Relevant - IN NOW CRM valid'!$G$2:$G$2328,"UK",'Relevant - IN NOW CRM valid'!$M$2:$M$2328,"Research",'Relevant - IN NOW CRM valid'!$R$2:$R$2328,"Operational")+COUNTIFS('Relevant - IN NOW CRM unknown'!$T$2:$T$1227,$A3,'Relevant - IN NOW CRM unknown'!$G$2:$G$1227,"UK",'Relevant - IN NOW CRM unknown'!$M$2:$M$1227,"Research",'Relevant - IN NOW CRM unknown'!$R$2:$R$1227,"Operational")+COUNTIFS('Relevant - Not CRM not valid'!$T$2:$T$416,$A3,'Relevant - Not CRM not valid'!$G$2:$G$416,"UK",'Relevant - Not CRM not valid'!$M$2:$M$416,"Research",'Relevant - Not CRM not valid'!$R$2:$R$416,"Operational")+COUNTIFS('Relevant - In CRM not valid'!$T$2:$T$46,$A3,'Relevant - In CRM not valid'!$G$2:$G$46,"UK",'Relevant - In CRM not valid'!$M$2:$M$46,"Research",'Relevant - In CRM not valid'!$R$2:$R$46,"Operational") -> 117 | I3: =COUNTIFS('Relevant - In CRM valid'!$T$2:$T$4699,$A3,'Relevant - In CRM valid'!$G$2:$G$4699,"UK",'Relevant - In CRM valid'!$M$2:$M$4699,"Research",'Relevant - In CRM valid'!$R$2:$R$4699,"Academic")+COUNTIFS('Relevant - In CRM unknown'!$T$2:$T$253,$A3,'Relevant - In CRM unknown'!$G$2:$G$253,"UK",'Relevant - In CRM unknown'!$M$2:$M$253,"Research",'Relevant - In CRM unknown'!$R$2:$R$253,"Academic")+COUNTIFS('Relevant - IN NOW CRM valid'!$T$2:$T$2328,$A3,'Relevant - IN NOW CRM valid'!$G$2:$G$2328,"UK",'Relevant - IN NOW CRM valid'!$M$2:$M$2328,"Research",'Relevant - IN NOW CRM valid'!$R$2:$R$2328,"Academic")+COUNTIFS('Relevant - IN NOW CRM unknown'!$T$2:$T$1227,$A3,'Relevant - IN NOW CRM unknown'!$G$2:$G$1227,"UK",'Relevant - IN NOW CRM unknown'!$M$2:$M$1227,"Research",'Relevant - IN NOW CRM unknown'!$R$2:$R$1227,"Academic")+COUNTIFS('Relevant - Not CRM not valid'!$T$2:$T$416,$A3,'Relevant - Not CRM not valid'!$G$2:$G$416,"UK",'Relevant - Not CRM not valid'!$M$2:$M$416,"Research",'Relevant - Not CRM not valid'!$R$2:$R$416,"Academic")+COUNTIFS('Relevant - In CRM not valid'!$T$2:$T$46,$A3,'Relevant - In CRM not valid'!$G$2:$G$46,"UK",'Relevant - In CRM not valid'!$M$2:$M$46,"Research",'Relevant - In CRM not valid'!$R$2:$R$46,"Academic") -> 10 | J3: =COUNTIFS('Relevant - In CRM valid'!$T$2:$T$4699,$A3,'Relevant - In CRM valid'!$G$2:$G$4699,"UK",'Relevant - In CRM valid'!$M$2:$M$4699,"Finance")+COUNTIFS('Relevant - In CRM unknown'!$T$2:$T$253,$A3,'Relevant - In CRM unknown'!$G$2:$G$253,"UK",'Relevant - In CRM unknown'!$M$2:$M$253,"Finance")+COUNTIFS('Relevant - IN NOW CRM valid'!$T$2:$T$2328,$A3,'Relevant - IN NOW CRM valid'!$G$2:$G$2328,"UK",'Relevant - IN NOW CRM valid'!$M$2:$M$2328,"Finance")+COUNTIFS('Relevant - IN NOW CRM unknown'!$T$2:$T$1227,$A3,'Relevant - IN NOW CRM unknown'!$G$2:$G$1227,"UK",'Relevant - IN NOW CRM unknown'!$M$2:$M$1227,"Finance")+COUNTIFS('Relevant - Not CRM not valid'!$T$2:$T$416,$A3,'Relevant - Not CRM not valid'!$G$2:$G$416,"UK",'Relevant - Not CRM not valid'!$M$2:$M$416,"Finance")+COUNTIFS('Relevant - In CRM not valid'!$T$2:$T$46,$A3,'Relevant - In CRM not valid'!$G$2:$G$46,"UK",'Relevant - In CRM not valid'!$M$2:$M$46,"Finance") -> 2 | K3: =COUNTIFS('Relevant - In CRM valid'!$T$2:$T$4699,$A3,'Relevant - In CRM valid'!$G$2:$G$4699,"UK",'Relevant - In CRM valid'!$M$2:$M$4699,"IT/Systems")+COUNTIFS('Relevant - In CRM unknown'!$T$2:$T$253,$A3,'Relevant - In CRM unknown'!$G$2:$G$253,"UK",'Relevant - In CRM unknown'!$M$2:$M$253,"IT/Systems")+COUNTIFS('Relevant - IN NOW CRM valid'!$T$2:$T$2328,$A3,'Relevant - IN NOW CRM valid'!$G$2:$G$2328,"UK",'Relevant - IN NOW CRM valid'!$M$2:$M$2328,"IT/Systems")+COUNTIFS('Relevant - IN NOW CRM unknown'!$T$2:$T$1227,$A3,'Relevant - IN NOW CRM unknown'!$G$2:$G$1227,"UK",'Relevant - IN NOW CRM unknown'!$M$2:$M$1227,"IT/Systems")+COUNTIFS('Relevant - Not CRM not valid'!$T$2:$T$416,$A3,'Relevant - Not CRM not valid'!$G$2:$G$416,"UK",'Relevant - Not CRM not valid'!$M$2:$M$416,"IT/Systems")+COUNTIFS('Relevant - In CRM not valid'!$T$2:$T$46,$A3,'Relevant - In CRM not valid'!$G$2:$G$46,"UK",'Relevant - In CRM not valid'!$M$2:$M$46,"IT/Systems") -> 1 | L3: =COUNTIFS('Relevant - In CRM valid'!$T$2:$T$4699,$A3,'Relevant - In CRM valid'!$G$2:$G$4699,"UK",'Relevant - In CRM valid'!$M$2:$M$4699,"")+COUNTIFS('Relevant - In CRM unknown'!$T$2:$T$253,$A3,'Relevant - In CRM unknown'!$G$2:$G$253,"UK",'Relevant - In CRM unknown'!$M$2:$M$253,"")+COUNTIFS('Relevant - IN NOW CRM valid'!$T$2:$T$2328,$A3,'Relevant - IN NOW CRM valid'!$G$2:$G$2328,"UK",'Relevant - IN NOW CRM valid'!$M$2:$M$2328,"")+COUNTIFS('Relevant - IN NOW CRM unknown'!$T$2:$T$1227,$A3,'Relevant - IN NOW CRM unknown'!$G$2:$G$1227,"UK",'Relevant - IN NOW CRM unknown'!$M$2:$M$1227,"")+COUNTIFS('Relevant - Not CRM not valid'!$T$2:$T$416,$A3,'Relevant - Not CRM not valid'!$G$2:$G$416,"UK",'Relevant - Not CRM not valid'!$M$2:$M$416,"")+COUNTIFS('Relevant - In CRM not valid'!$T$2:$T$46,$A3,'Relevant - In CRM not valid'!$G$2:$G$46,"UK",'Relevant - In CRM not valid'!$M$2:$M$46,"") -> 0 | M3: =(F3>0)+(J3>0)+(K3>0) -> 3 | N3: =COUNTIFS('Relevant - In CRM valid'!$T$2:$T$4699,$A3,'Relevant - In CRM valid'!$G$2:$G$4699,"UK",'Relevant - In CRM valid'!$Q$2:$Q$4699,"valid")+COUNTIFS('Relevant - In CRM unknown'!$T$2:$T$253,$A3,'Relevant - In CRM unknown'!$G$2:$G$253,"UK",'Relevant - In CRM unknown'!$Q$2:$Q$253,"valid")+COUNTIFS('Relevant - IN NOW CRM valid'!$T$2:$T$2328,$A3,'Relevant - IN NOW CRM valid'!$G$2:$G$2328,"UK",'Relevant - IN NOW CRM valid'!$Q$2:$Q$2328,"valid")+COUNTIFS('Relevant - IN NOW CRM unknown'!$T$2:$T$1227,$A3,'Relevant - IN NOW CRM unknown'!$G$2:$G$1227,"UK",'Relevant - IN NOW CRM unknown'!$Q$2:$Q$1227,"valid")+COUNTIFS('Relevant - Not CRM not valid'!$T$2:$T$416,$A3,'Relevant - Not CRM not valid'!$G$2:$G$416,"UK",'Relevant - Not CRM not valid'!$Q$2:$Q$416,"valid")+COUNTIFS('Relevant - In CRM not valid'!$T$2:$T$46,$A3,'Relevant - In CRM not valid'!$G$2:$G$46,"UK",'Relevant - In CRM not valid'!$Q$2:$Q$46,"valid") -> 155 | O3: =IF(F3=0,"Research ","")&IF(J3=0,"Finance ","")&IF(K3=0,"IT/Systems","")
A4: coventry university | B4: Coventry University | C4: University | D4: =IFERROR(INDEX('UK Target Institutions'!$D$2:$D$727,MATCH($A4,'UK Target Institutions'!$A$2:$A$727,0)),"") -> Yes | E4: =COUNTIFS('Relevant - In CRM valid'!$T$2:$T$4699,$A4,'Relevant - In CRM valid'!$G$2:$G$4699,"UK")+COUNTIFS('Relevant - In CRM unknown'!$T$2:$T$253,$A4,'Relevant - In CRM unknown'!$G$2:$G$253,"UK")+COUNTIFS('Relevant - IN NOW CRM valid'!$T$2:$T$2328,$A4,'Relevant - IN NOW CRM valid'!$G$2:$G$2328,"UK")+COUNTIFS('Relevant - IN NOW CRM unknown'!$T$2:$T$1227,$A4,'Relevant - IN NOW CRM unknown'!$G$2:$G$1227,"UK")+COUNTIFS('Relevant - Not CRM not valid'!$T$2:$T$416,$A4,'Relevant - Not CRM not valid'!$G$2:$G$416,"UK")+COUNTIFS('Relevant - In CRM not valid'!$T$2:$T$46,$A4,'Relevant - In CRM not valid'!$G$2:$G$46,"UK") -> 168 | F4: =COUNTIFS('Relevant - In CRM valid'!$T$2:$T$4699,$A4,'Relevant - In CRM valid'!$G$2:$G$4699,"UK",'Relevant - In CRM valid'!$M$2:$M$4699,"Research")+COUNTIFS('Relevant - In CRM unknown'!$T$2:$T$253,$A4,'Relevant - In CRM unknown'!$G$2:$G$253,"UK",'Relevant - In CRM unknown'!$M$2:$M$253,"Research")+COUNTIFS('Relevant - IN NOW CRM valid'!$T$2:$T$2328,$A4,'Relevant - IN NOW CRM valid'!$G$2:$G$2328,"UK",'Relevant - IN NOW CRM valid'!$M$2:$M$2328,"Research")+COUNTIFS('Relevant - IN NOW CRM unknown'!$T$2:$T$1227,$A4,'Relevant - IN NOW CRM unknown'!$G$2:$G$1227,"UK",'Relevant - IN NOW CRM unknown'!$M$2:$M$1227,"Research")+COUNTIFS('Relevant - Not CRM not valid'!$T$2:$T$416,$A4,'Relevant - Not CRM not valid'!$G$2:$G$416,"UK",'Relevant - Not CRM not valid'!$M$2:$M$416,"Research")+COUNTIFS('Relevant - In CRM not valid'!$T$2:$T$46,$A4,'Relevant - In CRM not valid'!$G$2:$G$46,"UK",'Relevant - In CRM not valid'!$M$2:$M$46,"Research") -> 147 | G4: =COUNTIFS('Relevant - In CRM valid'!$T$2:$T$4699,$A4,'Relevant - In CRM valid'!$G$2:$G$4699,"UK",'Relevant - In CRM valid'!$M$2:$M$4699,"Research",'Relevant - In CRM valid'!$R$2:$R$4699,"Senior")+COUNTIFS('Relevant - In CRM unknown'!$T$2:$T$253,$A4,'Relevant - In CRM unknown'!$G$2:$G$253,"UK",'Relevant - In CRM unknown'!$M$2:$M$253,"Research",'Relevant - In CRM unknown'!$R$2:$R$253,"Senior")+COUNTIFS('Relevant - IN NOW CRM valid'!$T$2:$T$2328,$A4,'Relevant - IN NOW CRM valid'!$G$2:$G$2328,"UK",'Relevant - IN NOW CRM valid'!$M$2:$M$2328,"Research",'Relevant - IN NOW CRM valid'!$R$2:$R$2328,"Senior")+COUNTIFS('Relevant - IN NOW CRM unknown'!$T$2:$T$1227,$A4,'Relevant - IN NOW CRM unknown'!$G$2:$G$1227,"UK",'Relevant - IN NOW CRM unknown'!$M$2:$M$1227,"Research",'Relevant - IN NOW CRM unknown'!$R$2:$R$1227,"Senior")+COUNTIFS('Relevant - Not CRM not valid'!$T$2:$T$416,$A4,'Relevant - Not CRM not valid'!$G$2:$G$416,"UK",'Relevant - Not CRM not valid'!$M$2:$M$416,"Research",'Relevant - Not CRM not valid'!$R$2:$R$416,"Senior")+COUNTIFS('Relevant - In CRM not valid'!$T$2:$T$46,$A4,'Relevant - In CRM not valid'!$G$2:$G$46,"UK",'Relevant - In CRM not valid'!$M$2:$M$46,"Research",'Relevant - In CRM not valid'!$R$2:$R$46,"Senior") -> 59 | H4: =COUNTIFS('Relevant - In CRM valid'!$T$2:$T$4699,$A4,'Relevant - In CRM valid'!$G$2:$G$4699,"UK",'Relevant - In CRM valid'!$M$2:$M$4699,"Research",'Relevant - In CRM valid'!$R$2:$R$4699,"Operational")+COUNTIFS('Relevant - In CRM unknown'!$T$2:$T$253,$A4,'Relevant - In CRM unknown'!$G$2:$G$253,"UK",'Relevant - In CRM unknown'!$M$2:$M$253,"Research",'Relevant - In CRM unknown'!$R$2:$R$253,"Operational")+COUNTIFS('Relevant - IN NOW CRM valid'!$T$2:$T$2328,$A4,'Relevant - IN NOW CRM valid'!$G$2:$G$2328,"UK",'Relevant - IN NOW CRM valid'!$M$2:$M$2328,"Research",'Relevant - IN NOW CRM valid'!$R$2:$R$2328,"Operational")+COUNTIFS('Relevant - IN NOW CRM unknown'!$T$2:$T$1227,$A4,'Relevant - IN NOW CRM unknown'!$G$2:$G$1227,"UK",'Relevant - IN NOW CRM unknown'!$M$2:$M$1227,"Research",'Relevant - IN NOW CRM unknown'!$R$2:$R$1227,"Operational")+COUNTIFS('Relevant - Not CRM not valid'!$T$2:$T$416,$A4,'Relevant - Not CRM not valid'!$G$2:$G$416,"UK",'Relevant - Not CRM not valid'!$M$2:$M$416,"Research",'Relevant - Not CRM not valid'!$R$2:$R$416,"Operational")+COUNTIFS('Relevant - In CRM not valid'!$T$2:$T$46,$A4,'Relevant - In CRM not valid'!$G$2:$G$46,"UK",'Relevant - In CRM not valid'!$M$2:$M$46,"Research",'Relevant - In CRM not valid'!$R$2:$R$46,"Operational") -> 47 | I4: =COUNTIFS('Relevant - In CRM valid'!$T$2:$T$4699,$A4,'Relevant - In CRM valid'!$G$2:$G$4699,"UK",'Relevant - In CRM valid'!$M$2:$M$4699,"Research",'Relevant - In CRM valid'!$R$2:$R$4699,"Academic")+COUNTIFS('Relevant - In CRM unknown'!$T$2:$T$253,$A4,'Relevant - In CRM unknown'!$G$2:$G$253,"UK",'Relevant - In CRM unknown'!$M$2:$M$253,"Research",'Relevant - In CRM unknown'!$R$2:$R$253,"Academic")+COUNTIFS('Relevant - IN NOW CRM valid'!$T$2:$T$2328,$A4,'Relevant - IN NOW CRM valid'!$G$2:$G$2328,"UK",'Relevant - IN NOW CRM valid'!$M$2:$M$2328,"Research",'Relevant - IN NOW CRM valid'!$R$2:$R$2328,"Academic")+COUNTIFS('Relevant - IN NOW CRM unknown'!$T$2:$T$1227,$A4,'Relevant - IN NOW CRM unknown'!$G$2:$G$1227,"UK",'Relevant - IN NOW CRM unknown'!$M$2:$M$1227,"Research",'Relevant - IN NOW CRM unknown'!$R$2:$R$1227,"Academic")+COUNTIFS('Relevant - Not CRM not valid'!$T$2:$T$416,$A4,'Relevant - Not CRM not valid'!$G$2:$G$416,"UK",'Relevant - Not CRM not valid'!$M$2:$M$416,"Research",'Relevant - Not CRM not valid'!$R$2:$R$416,"Academic")+COUNTIFS('Relevant - In CRM not valid'!$T$2:$T$46,$A4,'Relevant - In CRM not valid'!$G$2:$G$46,"UK",'Relevant - In CRM not valid'!$M$2:$M$46,"Research",'Relevant - In CRM not valid'!$R$2:$R$46,"Academic") -> 41 | J4: =COUNTIFS('Relevant - In CRM valid'!$T$2:$T$4699,$A4,'Relevant - In CRM valid'!$G$2:$G$4699,"UK",'Relevant - In CRM valid'!$M$2:$M$4699,"Finance")+COUNTIFS('Relevant - In CRM unknown'!$T$2:$T$253,$A4,'Relevant - In CRM unknown'!$G$2:$G$253,"UK",'Relevant - In CRM unknown'!$M$2:$M$253,"Finance")+COUNTIFS('Relevant - IN NOW CRM valid'!$T$2:$T$2328,$A4,'Relevant - IN NOW CRM valid'!$G$2:$G$2328,"UK",'Relevant - IN NOW CRM valid'!$M$2:$M$2328,"Finance")+COUNTIFS('Relevant - IN NOW CRM unknown'!$T$2:$T$1227,$A4,'Relevant - IN NOW CRM unknown'!$G$2:$G$1227,"UK",'Relevant - IN NOW CRM unknown'!$M$2:$M$1227,"Finance")+COUNTIFS('Relevant - Not CRM not valid'!$T$2:$T$416,$A4,'Relevant - Not CRM not valid'!$G$2:$G$416,"UK",'Relevant - Not CRM not valid'!$M$2:$M$416,"Finance")+COUNTIFS('Relevant - In CRM not valid'!$T$2:$T$46,$A4,'Relevant - In CRM not valid'!$G$2:$G$46,"UK",'Relevant - In CRM not valid'!$M$2:$M$46,"Finance") -> 10 | K4: =COUNTIFS('Relevant - In CRM valid'!$T$2:$T$4699,$A4,'Relevant - In CRM valid'!$G$2:$G$4699,"UK",'Relevant - In CRM valid'!$M$2:$M$4699,"IT/Systems")+COUNTIFS('Relevant - In CRM unknown'!$T$2:$T$253,$A4,'Relevant - In CRM unknown'!$G$2:$G$253,"UK",'Relevant - In CRM unknown'!$M$2:$M$253,"IT/Systems")+COUNTIFS('Relevant - IN NOW CRM valid'!$T$2:$T$2328,$A4,'Relevant - IN NOW CRM valid'!$G$2:$G$2328,"UK",'Relevant - IN NOW CRM valid'!$M$2:$M$2328,"IT/Systems")+COUNTIFS('Relevant - IN NOW CRM unknown'!$T$2:$T$1227,$A4,'Relevant - IN NOW CRM unknown'!$G$2:$G$1227,"UK",'Relevant - IN NOW CRM unknown'!$M$2:$M$1227,"IT/Systems")+COUNTIFS('Relevant - Not CRM not valid'!$T$2:$T$416,$A4,'Relevant - Not CRM not valid'!$G$2:$G$416,"UK",'Relevant - Not CRM not valid'!$M$2:$M$416,"IT/Systems")+COUNTIFS('Relevant - In CRM not valid'!$T$2:$T$46,$A4,'Relevant - In CRM not valid'!$G$2:$G$46,"UK",'Relevant - In CRM not valid'!$M$2:$M$46,"IT/Systems") -> 4 | L4: =COUNTIFS('Relevant - In CRM valid'!$T$2:$T$4699,$A4,'Relevant - In CRM valid'!$G$2:$G$4699,"UK",'Relevant - In CRM valid'!$M$2:$M$4699,"")+COUNTIFS('Relevant - In CRM unknown'!$T$2:$T$253,$A4,'Relevant - In CRM unknown'!$G$2:$G$253,"UK",'Relevant - In CRM unknown'!$M$2:$M$253,"")+COUNTIFS('Relevant - IN NOW CRM valid'!$T$2:$T$2328,$A4,'Relevant - IN NOW CRM valid'!$G$2:$G$2328,"UK",'Relevant - IN NOW CRM valid'!$M$2:$M$2328,"")+COUNTIFS('Relevant - IN NOW CRM unknown'!$T$2:$T$1227,$A4,'Relevant - IN NOW CRM unknown'!$G$2:$G$1227,"UK",'Relevant - IN NOW CRM unknown'!$M$2:$M$1227,"")+COUNTIFS('Relevant - Not CRM not valid'!$T$2:$T$416,$A4,'Relevant - Not CRM not valid'!$G$2:$G$416,"UK",'Relevant - Not CRM not valid'!$M$2:$M$416,"")+COUNTIFS('Relevant - In CRM not valid'!$T$2:$T$46,$A4,'Relevant - In CRM not valid'!$G$2:$G$46,"UK",'Relevant - In CRM not valid'!$M$2:$M$46,"") -> 6 | M4: =(F4>0)+(J4>0)+(K4>0) -> 3 | N4: =COUNTIFS('Relevant - In CRM valid'!$T$2:$T$4699,$A4,'Relevant - In CRM valid'!$G$2:$G$4699,"UK",'Relevant - In CRM valid'!$Q$2:$Q$4699,"valid")+COUNTIFS('Relevant - In CRM unknown'!$T$2:$T$253,$A4,'Relevant - In CRM unknown'!$G$2:$G$253,"UK",'Relevant - In CRM unknown'!$Q$2:$Q$253,"valid")+COUNTIFS('Relevant - IN NOW CRM valid'!$T$2:$T$2328,$A4,'Relevant - IN NOW CRM valid'!$G$2:$G$2328,"UK",'Relevant - IN NOW CRM valid'!$Q$2:$Q$2328,"valid")+COUNTIFS('Relevant - IN NOW CRM unknown'!$T$2:$T$1227,$A4,'Relevant - IN NOW CRM unknown'!$G$2:$G$1227,"UK",'Relevant - IN NOW CRM unknown'!$Q$2:$Q$1227,"valid")+COUNTIFS('Relevant - Not CRM not valid'!$T$2:$T$416,$A4,'Relevant - Not CRM not valid'!$G$2:$G$416,"UK",'Relevant - Not CRM not valid'!$Q$2:$Q$416,"valid")+COUNTIFS('Relevant - In CRM not valid'!$T$2:$T$46,$A4,'Relevant - In CRM not valid'!$G$2:$G$46,"UK",'Relevant - In CRM not valid'!$Q$2:$Q$46,"valid") -> 90 | O4: =IF(F4=0,"Research ","")&IF(J4=0,"Finance ","")&IF(K4=0,"IT/Systems","")
A5: sussex university | B5: University of Sussex | C5: University | D5: =IFERROR(INDEX('UK Target Institutions'!$D$2:$D$727,MATCH($A5,'UK Target Institutions'!$A$2:$A$727,0)),"") -> Yes | E5: =COUNTIFS('Relevant - In CRM valid'!$T$2:$T$4699,$A5,'Relevant - In CRM valid'!$G$2:$G$4699,"UK")+COUNTIFS('Relevant - In CRM unknown'!$T$2:$T$253,$A5,'Relevant - In CRM unknown'!$G$2:$G$253,"UK")+COUNTIFS('Relevant - IN NOW CRM valid'!$T$2:$T$2328,$A5,'Relevant - IN NOW CRM valid'!$G$2:$G$2328,"UK")+COUNTIFS('Relevant - IN NOW CRM unknown'!$T$2:$T$1227,$A5,'Relevant - IN NOW CRM unknown'!$G$2:$G$1227,"UK")+COUNTIFS('Relevant - Not CRM not valid'!$T$2:$T$416,$A5,'Relevant - Not CRM not valid'!$G$2:$G$416,"UK")+COUNTIFS('Relevant - In CRM not valid'!$T$2:$T$46,$A5,'Relevant - In CRM not valid'!$G$2:$G$46,"UK") -> 158 | F5: =COUNTIFS('Relevant - In CRM valid'!$T$2:$T$4699,$A5,'Relevant - In CRM valid'!$G$2:$G$4699,"UK",'Relevant - In CRM valid'!$M$2:$M$4699,"Research")+COUNTIFS('Relevant - In CRM unknown'!$T$2:$T$253,$A5,'Relevant - In CRM unknown'!$G$2:$G$253,"UK",'Relevant - In CRM unknown'!$M$2:$M$253,"Research")+COUNTIFS('Relevant - IN NOW CRM valid'!$T$2:$T$2328,$A5,'Relevant - IN NOW CRM valid'!$G$2:$G$2328,"UK",'Relevant - IN NOW CRM valid'!$M$2:$M$2328,"Research")+COUNTIFS('Relevant - IN NOW CRM unknown'!$T$2:$T$1227,$A5,'Relevant - IN NOW CRM unknown'!$G$2:$G$1227,"UK",'Relevant - IN NOW CRM unknown'!$M$2:$M$1227,"Research")+COUNTIFS('Relevant - Not CRM not valid'!$T$2:$T$416,$A5,'Relevant - Not CRM not valid'!$G$2:$G$416,"UK",'Relevant - Not CRM not valid'!$M$2:$M$416,"Research")+COUNTIFS('Relevant - In CRM not valid'!$T$2:$T$46,$A5,'Relevant - In CRM not valid'!$G$2:$G$46,"UK",'Relevant - In CRM not valid'!$M$2:$M$46,"Research") -> 117 | G5: =COUNTIFS('Relevant - In CRM valid'!$T$2:$T$4699,$A5,'Relevant - In CRM valid'!$G$2:$G$4699,"UK",'Relevant - In CRM valid'!$M$2:$M$4699,"Research",'Relevant - In CRM valid'!$R$2:$R$4699,"Senior")+COUNTIFS('Relevant - In CRM unknown'!$T$2:$T$253,$A5,'Relevant - In CRM unknown'!$G$2:$G$253,"UK",'Relevant - In CRM unknown'!$M$2:$M$253,"Research",'Relevant - In CRM unknown'!$R$2:$R$253,"Senior")+COUNTIFS('Relevant - IN NOW CRM valid'!$T$2:$T$2328,$A5,'Relevant - IN NOW CRM valid'!$G$2:$G$2328,"UK",'Relevant - IN NOW CRM valid'!$M$2:$M$2328,"Research",'Relevant - IN NOW CRM valid'!$R$2:$R$2328,"Senior")+COUNTIFS('Relevant - IN NOW CRM unknown'!$T$2:$T$1227,$A5,'Relevant - IN NOW CRM unknown'!$G$2:$G$1227,"UK",'Relevant - IN NOW CRM unknown'!$M$2:$M$1227,"Research",'Relevant - IN NOW CRM unknown'!$R$2:$R$1227,"Senior")+COUNTIFS('Relevant - Not CRM not valid'!$T$2:$T$416,$A5,'Relevant - Not CRM not valid'!$G$2:$G$416,"UK",'Relevant - Not CRM not valid'!$M$2:$M$416,"Research",'Relevant - Not CRM not valid'!$R$2:$R$416,"Senior")+COUNTIFS('Relevant - In CRM not valid'!$T$2:$T$46,$A5,'Relevant - In CRM not valid'!$G$2:$G$46,"UK",'Relevant - In CRM not valid'!$M$2:$M$46,"Research",'Relevant - In CRM not valid'!$R$2:$R$46,"Senior") -> 33 | H5: =COUNTIFS('Relevant - In CRM valid'!$T$2:$T$4699,$A5,'Relevant - In CRM valid'!$G$2:$G$4699,"UK",'Relevant - In CRM valid'!$M$2:$M$4699,"Research",'Relevant - In CRM valid'!$R$2:$R$4699,"Operational")+COUNTIFS('Relevant - In CRM unknown'!$T$2:$T$253,$A5,'Relevant - In CRM unknown'!$G$2:$G$253,"UK",'Relevant - In CRM unknown'!$M$2:$M$253,"Research",'Relevant - In CRM unknown'!$R$2:$R$253,"Operational")+COUNTIFS('Relevant - IN NOW CRM valid'!$T$2:$T$2328,$A5,'Relevant - IN NOW CRM valid'!$G$2:$G$2328,"UK",'Relevant - IN NOW CRM valid'!$M$2:$M$2328,"Research",'Relevant - IN NOW CRM valid'!$R$2:$R$2328,"Operational")+COUNTIFS('Relevant - IN NOW CRM unknown'!$T$2:$T$1227,$A5,'Relevant - IN NOW CRM unknown'!$G$2:$G$1227,"UK",'Relevant - IN NOW CRM unknown'!$M$2:$M$1227,"Research",'Relevant - IN NOW CRM unknown'!$R$2:$R$1227,"Operational")+COUNTIFS('Relevant - Not CRM not valid'!$T$2:$T$416,$A5,'Relevant - Not CRM not valid'!$G$2:$G$416,"UK",'Relevant - Not CRM not valid'!$M$2:$M$416,"Research",'Relevant - Not CRM not valid'!$R$2:$R$416,"Operational")+COUNTIFS('Relevant - In CRM not valid'!$T$2:$T$46,$A5,'Relevant - In CRM not valid'!$G$2:$G$46,"UK",'Relevant - In CRM not valid'!$M$2:$M$46,"Research",'Relevant - In CRM not valid'!$R$2:$R$46,"Operational") -> 76 | I5: =COUNTIFS('Relevant - In CRM valid'!$T$2:$T$4699,$A5,'Relevant - In CRM valid'!$G$2:$G$4699,"UK",'Relevant - In CRM valid'!$M$2:$M$4699,"Research",'Relevant - In CRM valid'!$R$2:$R$4699,"Academic")+COUNTIFS('Relevant - In CRM unknown'!$T$2:$T$253,$A5,'Relevant - In CRM unknown'!$G$2:$G$253,"UK",'Relevant - In CRM unknown'!$M$2:$M$253,"Research",'Relevant - In CRM unknown'!$R$2:$R$253,"Academic")+COUNTIFS('Relevant - IN NOW CRM valid'!$T$2:$T$2328,$A5,'Relevant - IN NOW CRM valid'!$G$2:$G$2328,"UK",'Relevant - IN NOW CRM valid'!$M$2:$M$2328,"Research",'Relevant - IN NOW CRM valid'!$R$2:$R$2328,"Academic")+COUNTIFS('Relevant - IN NOW CRM unknown'!$T$2:$T$1227,$A5,'Relevant - IN NOW CRM unknown'!$G$2:$G$1227,"UK",'Relevant - IN NOW CRM unknown'!$M$2:$M$1227,"Research",'Relevant - IN NOW CRM unknown'!$R$2:$R$1227,"Academic")+COUNTIFS('Relevant - Not CRM not valid'!$T$2:$T$416,$A5,'Relevant - Not CRM not valid'!$G$2:$G$416,"UK",'Relevant - Not CRM not valid'!$M$2:$M$416,"Research",'Relevant - Not CRM not valid'!$R$2:$R$416,"Academic")+COUNTIFS('Relevant - In CRM not valid'!$T$2:$T$46,$A5,'Relevant - In CRM not valid'!$G$2:$G$46,"UK",'Relevant - In CRM not valid'!$M$2:$M$46,"Research",'Relevant - In CRM not valid'!$R$2:$R$46,"Academic") -> 4 | J5: =COUNTIFS('Relevant - In CRM valid'!$T$2:$T$4699,$A5,'Relevant - In CRM valid'!$G$2:$G$4699,"UK",'Relevant - In CRM valid'!$M$2:$M$4699,"Finance")+COUNTIFS('Relevant - In CRM unknown'!$T$2:$T$253,$A5,'Relevant - In CRM unknown'!$G$2:$G$253,"UK",'Relevant - In CRM unknown'!$M$2:$M$253,"Finance")+COUNTIFS('Relevant - IN NOW CRM valid'!$T$2:$T$2328,$A5,'Relevant - IN NOW CRM valid'!$G$2:$G$2328,"UK",'Relevant - IN NOW CRM valid'!$M$2:$M$2328,"Finance")+COUNTIFS('Relevant - IN NOW CRM unknown'!$T$2:$T$1227,$A5,'Relevant - IN NOW CRM unknown'!$G$2:$G$1227,"UK",'Relevant - IN NOW CRM unknown'!$M$2:$M$1227,"Finance")+COUNTIFS('Relevant - Not CRM not valid'!$T$2:$T$416,$A5,'Relevant - Not CRM not valid'!$G$2:$G$416,"UK",'Relevant - Not CRM not valid'!$M$2:$M$416,"Finance")+COUNTIFS('Relevant - In CRM not valid'!$T$2:$T$46,$A5,'Relevant - In CRM not valid'!$G$2:$G$46,"UK",'Relevant - In CRM not valid'!$M$2:$M$46,"Finance") -> 22 | K5: =COUNTIFS('Relevant - In CRM valid'!$T$2:$T$4699,$A5,'Relevant - In CRM valid'!$G$2:$G$4699,"UK",'Relevant - In CRM valid'!$M$2:$M$4699,"IT/Systems")+COUNTIFS('Relevant - In CRM unknown'!$T$2:$T$253,$A5,'Relevant - In CRM unknown'!$G$2:$G$253,"UK",'Relevant - In CRM unknown'!$M$2:$M$253,"IT/Systems")+COUNTIFS('Relevant - IN NOW CRM valid'!$T$2:$T$2328,$A5,'Relevant - IN NOW CRM valid'!$G$2:$G$2328,"UK",'Relevant - IN NOW CRM valid'!$M$2:$M$2328,"IT/Systems")+COUNTIFS('Relevant - IN NOW CRM unknown'!$T$2:$T$1227,$A5,'Relevant - IN NOW CRM unknown'!$G$2:$G$1227,"UK",'Relevant - IN NOW CRM unknown'!$M$2:$M$1227,"IT/Systems")+COUNTIFS('Relevant - Not CRM not valid'!$T$2:$T$416,$A5,'Relevant - Not CRM not valid'!$G$2:$G$416,"UK",'Relevant - Not CRM not valid'!$M$2:$M$416,"IT/Systems")+COUNTIFS('Relevant - In CRM not valid'!$T$2:$T$46,$A5,'Relevant - In CRM not valid'!$G$2:$G$46,"UK",'Relevant - In CRM not valid'!$M$2:$M$46,"IT/Systems") -> 4 | L5: =COUNTIFS('Relevant - In CRM valid'!$T$2:$T$4699,$A5,'Relevant - In CRM valid'!$G$2:$G$4699,"UK",'Relevant - In CRM valid'!$M$2:$M$4699,"")+COUNTIFS('Relevant - In CRM unknown'!$T$2:$T$253,$A5,'Relevant - In CRM unknown'!$G$2:$G$253,"UK",'Relevant - In CRM unknown'!$M$2:$M$253,"")+COUNTIFS('Relevant - IN NOW CRM valid'!$T$2:$T$2328,$A5,'Relevant - IN NOW CRM valid'!$G$2:$G$2328,"UK",'Relevant - IN NOW CRM valid'!$M$2:$M$2328,"")+COUNTIFS('Relevant - IN NOW CRM unknown'!$T$2:$T$1227,$A5,'Relevant - IN NOW CRM unknown'!$G$2:$G$1227,"UK",'Relevant - IN NOW CRM unknown'!$M$2:$M$1227,"")+COUNTIFS('Relevant - Not CRM not valid'!$T$2:$T$416,$A5,'Relevant - Not CRM not valid'!$G$2:$G$416,"UK",'Relevant - Not CRM not valid'!$M$2:$M$416,"")+COUNTIFS('Relevant - In CRM not valid'!$T$2:$T$46,$A5,'Relevant - In CRM not valid'!$G$2:$G$46,"UK",'Relevant - In CRM not valid'!$M$2:$M$46,"") -> 13 | M5: =(F5>0)+(J5>0)+(K5>0) -> 3 | N5: =COUNTIFS('Relevant - In CRM valid'!$T$2:$T$4699,$A5,'Relevant - In CRM valid'!$G$2:$G$4699,"UK",'Relevant - In CRM valid'!$Q$2:$Q$4699,"valid")+COUNTIFS('Relevant - In CRM unknown'!$T$2:$T$253,$A5,'Relevant - In CRM unknown'!$G$2:$G$253,"UK",'Relevant - In CRM unknown'!$Q$2:$Q$253,"valid")+COUNTIFS('Relevant - IN NOW CRM valid'!$T$2:$T$2328,$A5,'Relevant - IN NOW CRM valid'!$G$2:$G$2328,"UK",'Relevant - IN NOW CRM valid'!$Q$2:$Q$2328,"valid")+COUNTIFS('Relevant - IN NOW CRM unknown'!$T$2:$T$1227,$A5,'Relevant - IN NOW CRM unknown'!$G$2:$G$1227,"UK",'Relevant - IN NOW CRM unknown'!$Q$2:$Q$1227,"valid")+COUNTIFS('Relevant - Not CRM not valid'!$T$2:$T$416,$A5,'Relevant - Not CRM not valid'!$G$2:$G$416,"UK",'Relevant - Not CRM not valid'!$Q$2:$Q$416,"valid")+COUNTIFS('Relevant - In CRM not valid'!$T$2:$T$46,$A5,'Relevant - In CRM not valid'!$G$2:$G$46,"UK",'Relevant - In CRM not valid'!$Q$2:$Q$46,"valid") -> 39 | O5: =IF(F5=0,"Research ","")&IF(J5=0,"Finance ","")&IF(K5=0,"IT/Systems","")
A6: edinburgh university | B6: University of Edinburgh | C6: University | D6: =IFERROR(INDEX('UK Target Institutions'!$D$2:$D$727,MATCH($A6,'UK Target Institutions'!$A$2:$A$727,0)),"") -> Yes | E6: =COUNTIFS('Relevant - In CRM valid'!$T$2:$T$4699,$A6,'Relevant - In CRM valid'!$G$2:$G$4699,"UK")+COUNTIFS('Relevant - In CRM unknown'!$T$2:$T$253,$A6,'Relevant - In CRM unknown'!$G$2:$G$253,"UK")+COUNTIFS('Relevant - IN NOW CRM valid'!$T$2:$T$2328,$A6,'Relevant - IN NOW CRM valid'!$G$2:$G$2328,"UK")+COUNTIFS('Relevant - IN NOW CRM unknown'!$T$2:$T$1227,$A6,'Relevant - IN NOW CRM unknown'!$G$2:$G$1227,"UK")+COUNTIFS('Relevant - Not CRM not valid'!$T$2:$T$416,$A6,'Relevant - Not CRM not valid'!$G$2:$G$416,"UK")+COUNTIFS('Relevant - In CRM not valid'!$T$2:$T$46,$A6,'Relevant - In CRM not valid'!$G$2:$G$46,"UK") -> 131 | F6: =COUNTIFS('Relevant - In CRM valid'!$T$2:$T$4699,$A6,'Relevant - In CRM valid'!$G$2:$G$4699,"UK",'Relevant - In CRM valid'!$M$2:$M$4699,"Research")+COUNTIFS('Relevant - In CRM unknown'!$T$2:$T$253,$A6,'Relevant - In CRM unknown'!$G$2:$G$253,"UK",'Relevant - In CRM unknown'!$M$2:$M$253,"Research")+COUNTIFS('Relevant - IN NOW CRM valid'!$T$2:$T$2328,$A6,'Relevant - IN NOW CRM valid'!$G$2:$G$2328,"UK",'Relevant - IN NOW CRM valid'!$M$2:$M$2328,"Research")+COUNTIFS('Relevant - IN NOW CRM unknown'!$T$2:$T$1227,$A6,'Relevant - IN NOW CRM unknown'!$G$2:$G$1227,"UK",'Relevant - IN NOW CRM unknown'!$M$2:$M$1227,"Research")+COUNTIFS('Relevant - Not CRM not valid'!$T$2:$T$416,$A6,'Relevant - Not CRM not valid'!$G$2:$G$416,"UK",'Relevant - Not CRM not valid'!$M$2:$M$416,"Research")+COUNTIFS('Relevant - In CRM not valid'!$T$2:$T$46,$A6,'Relevant - In CRM not valid'!$G$2:$G$46,"UK",'Relevant - In CRM not valid'!$M$2:$M$46,"Research") -> 86 | G6: =COUNTIFS('Relevant - In CRM valid'!$T$2:$T$4699,$A6,'Relevant - In CRM valid'!$G$2:$G$4699,"UK",'Relevant - In CRM valid'!$M$2:$M$4699,"Research",'Relevant - In CRM valid'!$R$2:$R$4699,"Senior")+COUNTIFS('Relevant - In CRM unknown'!$T$2:$T$253,$A6,'Relevant - In CRM unknown'!$G$2:$G$253,"UK",'Relevant - In CRM unknown'!$M$2:$M$253,"Research",'Relevant - In CRM unknown'!$R$2:$R$253,"Senior")+COUNTIFS('Relevant - IN NOW CRM valid'!$T$2:$T$2328,$A6,'Relevant - IN NOW CRM valid'!$G$2:$G$2328,"UK",'Relevant - IN NOW CRM valid'!$M$2:$M$2328,"Research",'Relevant - IN NOW CRM valid'!$R$2:$R$2328,"Senior")+COUNTIFS('Relevant - IN NOW CRM unknown'!$T$2:$T$1227,$A6,'Relevant - IN NOW CRM unknown'!$G$2:$G$1227,"UK",'Relevant - IN NOW CRM unknown'!$M$2:$M$1227,"Research",'Relevant - IN NOW CRM unknown'!$R$2:$R$1227,"Senior")+COUNTIFS('Relevant - Not CRM not valid'!$T$2:$T$416,$A6,'Relevant - Not CRM not valid'!$G$2:$G$416,"UK",'Relevant - Not CRM not valid'!$M$2:$M$416,"Research",'Relevant - Not CRM not valid'!$R$2:$R$416,"Senior")+COUNTIFS('Relevant - In CRM not valid'!$T$2:$T$46,$A6,'Relevant - In CRM not valid'!$G$2:$G$46,"UK",'Relevant - In CRM not valid'!$M$2:$M$46,"Research",'Relevant - In CRM not valid'!$R$2:$R$46,"Senior") -> 55 | H6: =COUNTIFS('Relevant - In CRM valid'!$T$2:$T$4699,$A6,'Relevant - In CRM valid'!$G$2:$G$4699,"UK",'Relevant - In CRM valid'!$M$2:$M$4699,"Research",'Relevant - In CRM valid'!$R$2:$R$4699,"Operational")+COUNTIFS('Relevant - In CRM unknown'!$T$2:$T$253,$A6,'Relevant - In CRM unknown'!$G$2:$G$253,"UK",'Relevant - In CRM unknown'!$M$2:$M$253,"Research",'Relevant - In CRM unknown'!$R$2:$R$253,"Operational")+COUNTIFS('Relevant - IN NOW CRM valid'!$T$2:$T$2328,$A6,'Relevant - IN NOW CRM valid'!$G$2:$G$2328,"UK",'Relevant - IN NOW CRM valid'!$M$2:$M$2328,"Research",'Relevant - IN NOW CRM valid'!$R$2:$R$2328,"Operational")+COUNTIFS('Relevant - IN NOW CRM unknown'!$T$2:$T$1227,$A6,'Relevant - IN NOW CRM unknown'!$G$2:$G$1227,"UK",'Relevant - IN NOW CRM unknown'!$M$2:$M$1227,"Research",'Relevant - IN NOW CRM unknown'!$R$2:$R$1227,"Operational")+COUNTIFS('Relevant - Not CRM not valid'!$T$2:$T$416,$A6,'Relevant - Not CRM not valid'!$G$2:$G$416,"UK",'Relevant - Not CRM not valid'!$M$2:$M$416,"Research",'Relevant - Not CRM not valid'!$R$2:$R$416,"Operational")+COUNTIFS('Relevant - In CRM not valid'!$T$2:$T$46,$A6,'Relevant - In CRM not valid'!$G$2:$G$46,"UK",'Relevant - In CRM not valid'!$M$2:$M$46,"Research",'Relevant - In CRM not valid'!$R$2:$R$46,"Operational") -> 24 | I6: =COUNTIFS('Relevant - In CRM valid'!$T$2:$T$4699,$A6,'Relevant - In CRM valid'!$G$2:$G$4699,"UK",'Relevant - In CRM valid'!$M$2:$M$4699,"Research",'Relevant - In CRM valid'!$R$2:$R$4699,"Academic")+COUNTIFS('Relevant - In CRM unknown'!$T$2:$T$253,$A6,'Relevant - In CRM unknown'!$G$2:$G$253,"UK",'Relevant - In CRM unknown'!$M$2:$M$253,"Research",'Relevant - In CRM unknown'!$R$2:$R$253,"Academic")+COUNTIFS('Relevant - IN NOW CRM valid'!$T$2:$T$2328,$A6,'Relevant - IN NOW CRM valid'!$G$2:$G$2328,"UK",'Relevant - IN NOW CRM valid'!$M$2:$M$2328,"Research",'Relevant - IN NOW CRM valid'!$R$2:$R$2328,"Academic")+COUNTIFS('Relevant - IN NOW CRM unknown'!$T$2:$T$1227,$A6,'Relevant - IN NOW CRM unknown'!$G$2:$G$1227,"UK",'Relevant - IN NOW CRM unknown'!$M$2:$M$1227,"Research",'Relevant - IN NOW CRM unknown'!$R$2:$R$1227,"Academic")+COUNTIFS('Relevant - Not CRM not valid'!$T$2:$T$416,$A6,'Relevant - Not CRM not valid'!$G$2:$G$416,"UK",'Relevant - Not CRM not valid'!$M$2:$M$416,"Research",'Relevant - Not CRM not valid'!$R$2:$R$416,"Academic")+COUNTIFS('Relevant - In CRM not valid'!$T$2:$T$46,$A6,'Relevant - In CRM not valid'!$G$2:$G$46,"UK",'Relevant - In CRM not valid'!$M$2:$M$46,"Research",'Relevant - In CRM not valid'!$R$2:$R$46,"Academic") -> 5 | J6: =COUNTIFS('Relevant - In CRM valid'!$T$2:$T$4699,$A6,'Relevant - In CRM valid'!$G$2:$G$4699,"UK",'Relevant - In CRM valid'!$M$2:$M$4699,"Finance")+COUNTIFS('Relevant - In CRM unknown'!$T$2:$T$253,$A6,'Relevant - In CRM unknown'!$G$2:$G$253,"UK",'Relevant - In CRM unknown'!$M$2:$M$253,"Finance")+COUNTIFS('Relevant - IN NOW CRM valid'!$T$2:$T$2328,$A6,'Relevant - IN NOW CRM valid'!$G$2:$G$2328,"UK",'Relevant - IN NOW CRM valid'!$M$2:$M$2328,"Finance")+COUNTIFS('Relevant - IN NOW CRM unknown'!$T$2:$T$1227,$A6,'Relevant - IN NOW CRM unknown'!$G$2:$G$1227,"UK",'Relevant - IN NOW CRM unknown'!$M$2:$M$1227,"Finance")+COUNTIFS('Relevant - Not CRM not valid'!$T$2:$T$416,$A6,'Relevant - Not CRM not valid'!$G$2:$G$416,"UK",'Relevant - Not CRM not valid'!$M$2:$M$416,"Finance")+COUNTIFS('Relevant - In CRM not valid'!$T$2:$T$46,$A6,'Relevant - In CRM not valid'!$G$2:$G$46,"UK",'Relevant - In CRM not valid'!$M$2:$M$46,"Finance") -> 31 | K6: =COUNTIFS('Relevant - In CRM valid'!$T$2:$T$4699,$A6,'Relevant - In CRM valid'!$G$2:$G$4699,"UK",'Relevant - In CRM valid'!$M$2:$M$4699,"IT/Systems")+COUNTIFS('Relevant - In CRM unknown'!$T$2:$T$253,$A6,'Relevant - In CRM unknown'!$G$2:$G$253,"UK",'Relevant - In CRM unknown'!$M$2:$M$253,"IT/Systems")+COUNTIFS('Relevant - IN NOW CRM valid'!$T$2:$T$2328,$A6,'Relevant - IN NOW CRM valid'!$G$2:$G$2328,"UK",'Relevant - IN NOW CRM valid'!$M$2:$M$2328,"IT/Systems")+COUNTIFS('Relevant - IN NOW CRM unknown'!$T$2:$T$1227,$A6,'Relevant - IN NOW CRM unknown'!$G$2:$G$1227,"UK",'Relevant - IN NOW CRM unknown'!$M$2:$M$1227,"IT/Systems")+COUNTIFS('Relevant - Not CRM not valid'!$T$2:$T$416,$A6,'Relevant - Not CRM not valid'!$G$2:$G$416,"UK",'Relevant - Not CRM not valid'!$M$2:$M$416,"IT/Systems")+COUNTIFS('Relevant - In CRM not valid'!$T$2:$T$46,$A6,'Relevant - In CRM not valid'!$G$2:$G$46,"UK",'Relevant - In CRM not valid'!$M$2:$M$46,"IT/Systems") -> 7 | L6: =COUNTIFS('Relevant - In CRM valid'!$T$2:$T$4699,$A6,'Relevant - In CRM valid'!$G$2:$G$4699,"UK",'Relevant - In CRM valid'!$M$2:$M$4699,"")+COUNTIFS('Relevant - In CRM unknown'!$T$2:$T$253,$A6,'Relevant - In CRM unknown'!$G$2:$G$253,"UK",'Relevant - In CRM unknown'!$M$2:$M$253,"")+COUNTIFS('Relevant - IN NOW CRM valid'!$T$2:$T$2328,$A6,'Relevant - IN NOW CRM valid'!$G$2:$G$2328,"UK",'Relevant - IN NOW CRM valid'!$M$2:$M$2328,"")+COUNTIFS('Relevant - IN NOW CRM unknown'!$T$2:$T$1227,$A6,'Relevant - IN NOW CRM unknown'!$G$2:$G$1227,"UK",'Relevant - IN NOW CRM unknown'!$M$2:$M$1227,"")+COUNTIFS('Relevant - Not CRM not valid'!$T$2:$T$416,$A6,'Relevant - Not CRM not valid'!$G$2:$G$416,"UK",'Relevant - Not CRM not valid'!$M$2:$M$416,"")+COUNTIFS('Relevant - In CRM not valid'!$T$2:$T$46,$A6,'Relevant - In CRM not valid'!$G$2:$G$46,"UK",'Relevant - In CRM not valid'!$M$2:$M$46,"") -> 5 | M6: =(F6>0)+(J6>0)+(K6>0) -> 3 | N6: =COUNTIFS('Relevant - In CRM valid'!$T$2:$T$4699,$A6,'Relevant - In CRM valid'!$G$2:$G$4699,"UK",'Relevant - In CRM valid'!$Q$2:$Q$4699,"valid")+COUNTIFS('Relevant - In CRM unknown'!$T$2:$T$253,$A6,'Relevant - In CRM unknown'!$G$2:$G$253,"UK",'Relevant - In CRM unknown'!$Q$2:$Q$253,"valid")+COUNTIFS('Relevant - IN NOW CRM valid'!$T$2:$T$2328,$A6,'Relevant - IN NOW CRM valid'!$G$2:$G$2328,"UK",'Relevant - IN NOW CRM valid'!$Q$2:$Q$2328,"valid")+COUNTIFS('Relevant - IN NOW CRM unknown'!$T$2:$T$1227,$A6,'Relevant - IN NOW CRM unknown'!$G$2:$G$1227,"UK",'Relevant - IN NOW CRM unknown'!$Q$2:$Q$1227,"valid")+COUNTIFS('Relevant - Not CRM not valid'!$T$2:$T$416,$A6,'Relevant - Not CRM not valid'!$G$2:$G$416,"UK",'Relevant - Not CRM not valid'!$Q$2:$Q$416,"valid")+COUNTIFS('Relevant - In CRM not valid'!$T$2:$T$46,$A6,'Relevant - In CRM not valid'!$G$2:$G$46,"UK",'Relevant - In CRM not valid'!$Q$2:$Q$46,"valid") -> 121 | O6: =IF(F6=0,"Research ","")&IF(J6=0,"Finance ","")&IF(K6=0,"IT/Systems","")
A7: liverpool university | B7: University of Liverpool | C7: University | D7: =IFERROR(INDEX('UK Target Institutions'!$D$2:$D$727,MATCH($A7,'UK Target Institutions'!$A$2:$A$727,0)),"") -> Yes | E7: =COUNTIFS('Relevant - In CRM valid'!$T$2:$T$4699,$A7,'Relevant - In CRM valid'!$G$2:$G$4699,"UK")+COUNTIFS('Relevant - In CRM unknown'!$T$2:$T$253,$A7,'Relevant - In CRM unknown'!$G$2:$G$253,"UK")+COUNTIFS('Relevant - IN NOW CRM valid'!$T$2:$T$2328,$A7,'Relevant - IN NOW CRM valid'!$G$2:$G$2328,"UK")+COUNTIFS('Relevant - IN NOW CRM unknown'!$T$2:$T$1227,$A7,'Relevant - IN NOW CRM unknown'!$G$2:$G$1227,"UK")+COUNTIFS('Relevant - Not CRM not valid'!$T$2:$T$416,$A7,'Relevant - Not CRM not valid'!$G$2:$G$416,"UK")+COUNTIFS('Relevant - In CRM not valid'!$T$2:$T$46,$A7,'Relevant - In CRM not valid'!$G$2:$G$46,"UK") -> 124 | F7: =COUNTIFS('Relevant - In CRM valid'!$T$2:$T$4699,$A7,'Relevant - In CRM valid'!$G$2:$G$4699,"UK",'Relevant - In CRM valid'!$M$2:$M$4699,"Research")+COUNTIFS('Relevant - In CRM unknown'!$T$2:$T$253,$A7,'Relevant - In CRM unknown'!$G$2:$G$253,"UK",'Relevant - In CRM unknown'!$M$2:$M$253,"Research")+COUNTIFS('Relevant - IN NOW CRM valid'!$T$2:$T$2328,$A7,'Relevant - IN NOW CRM valid'!$G$2:$G$2328,"UK",'Relevant - IN NOW CRM valid'!$M$2:$M$2328,"Research")+COUNTIFS('Relevant - IN NOW CRM unknown'!$T$2:$T$1227,$A7,'Relevant - IN NOW CRM unknown'!$G$2:$G$1227,"UK",'Relevant - IN NOW CRM unknown'!$M$2:$M$1227,"Research")+COUNTIFS('Relevant - Not CRM not valid'!$T$2:$T$416,$A7,'Relevant - Not CRM not valid'!$G$2:$G$416,"UK",'Relevant - Not CRM not valid'!$M$2:$M$416,"Research")+COUNTIFS('Relevant - In CRM not valid'!$T$2:$T$46,$A7,'Relevant - In CRM not valid'!$G$2:$G$46,"UK",'Relevant - In CRM not valid'!$M$2:$M$46,"Research") -> 108 | G7: =COUNTIFS('Relevant - In CRM valid'!$T$2:$T$4699,$A7,'Relevant - In CRM valid'!$G$2:$G$4699,"UK",'Relevant - In CRM valid'!$M$2:$M$4699,"Research",'Relevant - In CRM valid'!$R$2:$R$4699,"Senior")+COUNTIFS('Relevant - In CRM unknown'!$T$2:$T$253,$A7,'Relevant - In CRM unknown'!$G$2:$G$253,"UK",'Relevant - In CRM unknown'!$M$2:$M$253,"Research",'Relevant - In CRM unknown'!$R$2:$R$253,"Senior")+COUNTIFS('Relevant - IN NOW CRM valid'!$T$2:$T$2328,$A7,'Relevant - IN NOW CRM valid'!$G$2:$G$2328,"UK",'Relevant - IN NOW CRM valid'!$M$2:$M$2328,"Research",'Relevant - IN NOW CRM valid'!$R$2:$R$2328,"Senior")+COUNTIFS('Relevant - IN NOW CRM unknown'!$T$2:$T$1227,$A7,'Relevant - IN NOW CRM unknown'!$G$2:$G$1227,"UK",'Relevant - IN NOW CRM unknown'!$M$2:$M$1227,"Research",'Relevant - IN NOW CRM unknown'!$R$2:$R$1227,"Senior")+COUNTIFS('Relevant - Not CRM not valid'!$T$2:$T$416,$A7,'Relevant - Not CRM not valid'!$G$2:$G$416,"UK",'Relevant - Not CRM not valid'!$M$2:$M$416,"Research",'Relevant - Not CRM not valid'!$R$2:$R$416,"Senior")+COUNTIFS('Relevant - In CRM not valid'!$T$2:$T$46,$A7,'Relevant - In CRM not valid'!$G$2:$G$46,"UK",'Relevant - In CRM not valid'!$M$2:$M$46,"Research",'Relevant - In CRM not valid'!$R$2:$R$46,"Senior") -> 42 | H7: =COUNTIFS('Relevant - In CRM valid'!$T$2:$T$4699,$A7,'Relevant - In CRM valid'!$G$2:$G$4699,"UK",'Relevant - In CRM valid'!$M$2:$M$4699,"Research",'Relevant - In CRM valid'!$R$2:$R$4699,"Operational")+COUNTIFS('Relevant - In CRM unknown'!$T$2:$T$253,$A7,'Relevant - In CRM unknown'!$G$2:$G$253,"UK",'Relevant - In CRM unknown'!$M$2:$M$253,"Research",'Relevant - In CRM unknown'!$R$2:$R$253,"Operational")+COUNTIFS('Relevant - IN NOW CRM valid'!$T$2:$T$2328,$A7,'Relevant - IN NOW CRM valid'!$G$2:$G$2328,"UK",'Relevant - IN NOW CRM valid'!$M$2:$M$2328,"Research",'Relevant - IN NOW CRM valid'!$R$2:$R$2328,"Operational")+COUNTIFS('Relevant - IN NOW CRM unknown'!$T$2:$T$1227,$A7,'Relevant - IN NOW CRM unknown'!$G$2:$G$1227,"UK",'Relevant - IN NOW CRM unknown'!$M$2:$M$1227,"Research",'Relevant - IN NOW CRM unknown'!$R$2:$R$1227,"Operational")+COUNTIFS('Relevant - Not CRM not valid'!$T$2:$T$416,$A7,'Relevant - Not CRM not valid'!$G$2:$G$416,"UK",'Relevant - Not CRM not valid'!$M$2:$M$416,"Research",'Relevant - Not CRM not valid'!$R$2:$R$416,"Operational")+COUNTIFS('Relevant - In CRM not valid'!$T$2:$T$46,$A7,'Relevant - In CRM not valid'!$G$2:$G$46,"UK",'Relevant - In CRM not valid'!$M$2:$M$46,"Research",'Relevant - In CRM not valid'!$R$2:$R$46,"Operational") -> 63 | I7: =COUNTIFS('Relevant - In CRM valid'!$T$2:$T$4699,$A7,'Relevant - In CRM valid'!$G$2:$G$4699,"UK",'Relevant - In CRM valid'!$M$2:$M$4699,"Research",'Relevant - In CRM valid'!$R$2:$R$4699,"Academic")+COUNTIFS('Relevant - In CRM unknown'!$T$2:$T$253,$A7,'Relevant - In CRM unknown'!$G$2:$G$253,"UK",'Relevant - In CRM unknown'!$M$2:$M$253,"Research",'Relevant - In CRM unknown'!$R$2:$R$253,"Academic")+COUNTIFS('Relevant - IN NOW CRM valid'!$T$2:$T$2328,$A7,'Relevant - IN NOW CRM valid'!$G$2:$G$2328,"UK",'Relevant - IN NOW CRM valid'!$M$2:$M$2328,"Research",'Relevant - IN NOW CRM valid'!$R$2:$R$2328,"Academic")+COUNTIFS('Relevant - IN NOW CRM unknown'!$T$2:$T$1227,$A7,'Relevant - IN NOW CRM unknown'!$G$2:$G$1227,"UK",'Relevant - IN NOW CRM unknown'!$M$2:$M$1227,"Research",'Relevant - IN NOW CRM unknown'!$R$2:$R$1227,"Academic")+COUNTIFS('Relevant - Not CRM not valid'!$T$2:$T$416,$A7,'Relevant - Not CRM not valid'!$G$2:$G$416,"UK",'Relevant - Not CRM not valid'!$M$2:$M$416,"Research",'Relevant - Not CRM not valid'!$R$2:$R$416,"Academic")+COUNTIFS('Relevant - In CRM not valid'!$T$2:$T$46,$A7,'Relevant - In CRM not valid'!$G$2:$G$46,"UK",'Relevant - In CRM not valid'!$M$2:$M$46,"Research",'Relevant - In CRM not valid'!$R$2:$R$46,"Academic") -> 1 | J7: =COUNTIFS('Relevant - In CRM valid'!$T$2:$T$4699,$A7,'Relevant - In CRM valid'!$G$2:$G$4699,"UK",'Relevant - In CRM valid'!$M$2:$M$4699,"Finance")+COUNTIFS('Relevant - In CRM unknown'!$T$2:$T$253,$A7,'Relevant - In CRM unknown'!$G$2:$G$253,"UK",'Relevant - In CRM unknown'!$M$2:$M$253,"Finance")+COUNTIFS('Relevant - IN NOW CRM valid'!$T$2:$T$2328,$A7,'Relevant - IN NOW CRM valid'!$G$2:$G$2328,"UK",'Relevant - IN NOW CRM valid'!$M$2:$M$2328,"Finance")+COUNTIFS('Relevant - IN NOW CRM unknown'!$T$2:$T$1227,$A7,'Relevant - IN NOW CRM unknown'!$G$2:$G$1227,"UK",'Relevant - IN NOW CRM unknown'!$M$2:$M$1227,"Finance")+COUNTIFS('Relevant - Not CRM not valid'!$T$2:$T$416,$A7,'Relevant - Not CRM not valid'!$G$2:$G$416,"UK",'Relevant - Not CRM not valid'!$M$2:$M$416,"Finance")+COUNTIFS('Relevant - In CRM not valid'!$T$2:$T$46,$A7,'Relevant - In CRM not valid'!$G$2:$G$46,"UK",'Relevant - In CRM not valid'!$M$2:$M$46,"Finance") -> 12 | K7: =COUNTIFS('Relevant - In CRM valid'!$T$2:$T$4699,$A7,'Relevant - In CRM valid'!$G$2:$G$4699,"UK",'Relevant - In CRM valid'!$M$2:$M$4699,"IT/Systems")+COUNTIFS('Relevant - In CRM unknown'!$T$2:$T$253,$A7,'Relevant - In CRM unknown'!$G$2:$G$253,"UK",'Relevant - In CRM unknown'!$M$2:$M$253,"IT/Systems")+COUNTIFS('Relevant - IN NOW CRM valid'!$T$2:$T$2328,$A7,'Relevant - IN NOW CRM valid'!$G$2:$G$2328,"UK",'Relevant - IN NOW CRM valid'!$M$2:$M$2328,"IT/Systems")+COUNTIFS('Relevant - IN NOW CRM unknown'!$T$2:$T$1227,$A7,'Relevant - IN NOW CRM unknown'!$G$2:$G$1227,"UK",'Relevant - IN NOW CRM unknown'!$M$2:$M$1227,"IT/Systems")+COUNTIFS('Relevant - Not CRM not valid'!$T$2:$T$416,$A7,'Relevant - Not CRM not valid'!$G$2:$G$416,"UK",'Relevant - Not CRM not valid'!$M$2:$M$416,"IT/Systems")+COUNTIFS('Relevant - In CRM not valid'!$T$2:$T$46,$A7,'Relevant - In CRM not valid'!$G$2:$G$46,"UK",'Relevant - In CRM not valid'!$M$2:$M$46,"IT/Systems") -> 2 | L7: =COUNTIFS('Relevant - In CRM valid'!$T$2:$T$4699,$A7,'Relevant - In CRM valid'!$G$2:$G$4699,"UK",'Relevant - In CRM valid'!$M$2:$M$4699,"")+COUNTIFS('Relevant - In CRM unknown'!$T$2:$T$253,$A7,'Relevant - In CRM unknown'!$G$2:$G$253,"UK",'Relevant - In CRM unknown'!$M$2:$M$253,"")+COUNTIFS('Relevant - IN NOW CRM valid'!$T$2:$T$2328,$A7,'Relevant - IN NOW CRM valid'!$G$2:$G$2328,"UK",'Relevant - IN NOW CRM valid'!$M$2:$M$2328,"")+COUNTIFS('Relevant - IN NOW CRM unknown'!$T$2:$T$1227,$A7,'Relevant - IN NOW CRM unknown'!$G$2:$G$1227,"UK",'Relevant - IN NOW CRM unknown'!$M$2:$M$1227,"")+COUNTIFS('Relevant - Not CRM not valid'!$T$2:$T$416,$A7,'Relevant - Not CRM not valid'!$G$2:$G$416,"UK",'Relevant - Not CRM not valid'!$M$2:$M$416,"")+COUNTIFS('Relevant - In CRM not valid'!$T$2:$T$46,$A7,'Relevant - In CRM not valid'!$G$2:$G$46,"UK",'Relevant - In CRM not valid'!$M$2:$M$46,"") -> 1 | M7: =(F7>0)+(J7>0)+(K7>0) -> 3 | N7: =COUNTIFS('Relevant - In CRM valid'!$T$2:$T$4699,$A7,'Relevant - In CRM valid'!$G$2:$G$4699,"UK",'Relevant - In CRM valid'!$Q$2:$Q$4699,"valid")+COUNTIFS('Relevant - In CRM unknown'!$T$2:$T$253,$A7,'Relevant - In CRM unknown'!$G$2:$G$253,"UK",'Relevant - In CRM unknown'!$Q$2:$Q$253,"valid")+COUNTIFS('Relevant - IN NOW CRM valid'!$T$2:$T$2328,$A7,'Relevant - IN NOW CRM valid'!$G$2:$G$2328,"UK",'Relevant - IN NOW CRM valid'!$Q$2:$Q$2328,"valid")+COUNTIFS('Relevant - IN NOW CRM unknown'!$T$2:$T$1227,$A7,'Relevant - IN NOW CRM unknown'!$G$2:$G$1227,"UK",'Relevant - IN NOW CRM unknown'!$Q$2:$Q$1227,"valid")+COUNTIFS('Relevant - Not CRM not valid'!$T$2:$T$416,$A7,'Relevant - Not CRM not valid'!$G$2:$G$416,"UK",'Relevant - Not CRM not valid'!$Q$2:$Q$416,"valid")+COUNTIFS('Relevant - In CRM not valid'!$T$2:$T$46,$A7,'Relevant - In CRM not valid'!$G$2:$G$46,"UK",'Relevant - In CRM not valid'!$Q$2:$Q$46,"valid") -> 30 | O7: =IF(F7=0,"Research ","")&IF(J7=0,"Finance ","")&IF(K7=0,"IT/Systems","")
A8: sheffield university | B8: The University of Sheffield | C8: University | D8: =IFERROR(INDEX('UK Target Institutions'!$D$2:$D$727,MATCH($A8,'UK Target Institutions'!$A$2:$A$727,0)),"") -> Yes | E8: =COUNTIFS('Relevant - In CRM valid'!$T$2:$T$4699,$A8,'Relevant - In CRM valid'!$G$2:$G$4699,"UK")+COUNTIFS('Relevant - In CRM unknown'!$T$2:$T$253,$A8,'Relevant - In CRM unknown'!$G$2:$G$253,"UK")+COUNTIFS('Relevant - IN NOW CRM valid'!$T$2:$T$2328,$A8,'Relevant - IN NOW CRM valid'!$G$2:$G$2328,"UK")+COUNTIFS('Relevant - IN NOW CRM unknown'!$T$2:$T$1227,$A8,'Relevant - IN NOW CRM unknown'!$G$2:$G$1227,"UK")+COUNTIFS('Relevant - Not CRM not valid'!$T$2:$T$416,$A8,'Relevant - Not CRM not valid'!$G$2:$G$416,"UK")+COUNTIFS('Relevant - In CRM not valid'!$T$2:$T$46,$A8,'Relevant - In CRM not valid'!$G$2:$G$46,"UK") -> 115 | F8: =COUNTIFS('Relevant - In CRM valid'!$T$2:$T$4699,$A8,'Relevant - In CRM valid'!$G$2:$G$4699,"UK",'Relevant - In CRM valid'!$M$2:$M$4699,"Research")+COUNTIFS('Relevant - In CRM unknown'!$T$2:$T$253,$A8,'Relevant - In CRM unknown'!$G$2:$G$253,"UK",'Relevant - In CRM unknown'!$M$2:$M$253,"Research")+COUNTIFS('Relevant - IN NOW CRM valid'!$T$2:$T$2328,$A8,'Relevant - IN NOW CRM valid'!$G$2:$G$2328,"UK",'Relevant - IN NOW CRM valid'!$M$2:$M$2328,"Research")+COUNTIFS('Relevant - IN NOW CRM unknown'!$T$2:$T$1227,$A8,'Relevant - IN NOW CRM unknown'!$G$2:$G$1227,"UK",'Relevant - IN NOW CRM unknown'!$M$2:$M$1227,"Research")+COUNTIFS('Relevant - Not CRM not valid'!$T$2:$T$416,$A8,'Relevant - Not CRM not valid'!$G$2:$G$416,"UK",'Relevant - Not CRM not valid'!$M$2:$M$416,"Research")+COUNTIFS('Relevant - In CRM not valid'!$T$2:$T$46,$A8,'Relevant - In CRM not valid'!$G$2:$G$46,"UK",'Relevant - In CRM not valid'!$M$2:$M$46,"Research") -> 95 | G8: =COUNTIFS('Relevant - In CRM valid'!$T$2:$T$4699,$A8,'Relevant - In CRM valid'!$G$2:$G$4699,"UK",'Relevant - In CRM valid'!$M$2:$M$4699,"Research",'Relevant - In CRM valid'!$R$2:$R$4699,"Senior")+COUNTIFS('Relevant - In CRM unknown'!$T$2:$T$253,$A8,'Relevant - In CRM unknown'!$G$2:$G$253,"UK",'Relevant - In CRM unknown'!$M$2:$M$253,"Research",'Relevant - In CRM unknown'!$R$2:$R$253,"Senior")+COUNTIFS('Relevant - IN NOW CRM valid'!$T$2:$T$2328,$A8,'Relevant - IN NOW CRM valid'!$G$2:$G$2328,"UK",'Relevant - IN NOW CRM valid'!$M$2:$M$2328,"Research",'Relevant - IN NOW CRM valid'!$R$2:$R$2328,"Senior")+COUNTIFS('Relevant - IN NOW CRM unknown'!$T$2:$T$1227,$A8,'Relevant - IN NOW CRM unknown'!$G$2:$G$1227,"UK",'Relevant - IN NOW CRM unknown'!$M$2:$M$1227,"Research",'Relevant - IN NOW CRM unknown'!$R$2:$R$1227,"Senior")+COUNTIFS('Relevant - Not CRM not valid'!$T$2:$T$416,$A8,'Relevant - Not CRM not valid'!$G$2:$G$416,"UK",'Relevant - Not CRM not valid'!$M$2:$M$416,"Research",'Relevant - Not CRM not valid'!$R$2:$R$416,"Senior")+COUNTIFS('Relevant - In CRM not valid'!$T$2:$T$46,$A8,'Relevant - In CRM not valid'!$G$2:$G$46,"UK",'Relevant - In CRM not valid'!$M$2:$M$46,"Research",'Relevant - In CRM not valid'!$R$2:$R$46,"Senior") -> 32 | H8: =COUNTIFS('Relevant - In CRM valid'!$T$2:$T$4699,$A8,'Relevant - In CRM valid'!$G$2:$G$4699,"UK",'Relevant - In CRM valid'!$M$2:$M$4699,"Research",'Relevant - In CRM valid'!$R$2:$R$4699,"Operational")+COUNTIFS('Relevant - In CRM unknown'!$T$2:$T$253,$A8,'Relevant - In CRM unknown'!$G$2:$G$253,"UK",'Relevant - In CRM unknown'!$M$2:$M$253,"Research",'Relevant - In CRM unknown'!$R$2:$R$253,"Operational")+COUNTIFS('Relevant - IN NOW CRM valid'!$T$2:$T$2328,$A8,'Relevant - IN NOW CRM valid'!$G$2:$G$2328,"UK",'Relevant - IN NOW CRM valid'!$M$2:$M$2328,"Research",'Relevant - IN NOW CRM valid'!$R$2:$R$2328,"Operational")+COUNTIFS('Relevant - IN NOW CRM unknown'!$T$2:$T$1227,$A8,'Relevant - IN NOW CRM unknown'!$G$2:$G$1227,"UK",'Relevant - IN NOW CRM unknown'!$M$2:$M$1227,"Research",'Relevant - IN NOW CRM unknown'!$R$2:$R$1227,"Operational")+COUNTIFS('Relevant - Not CRM not valid'!$T$2:$T$416,$A8,'Relevant - Not CRM not valid'!$G$2:$G$416,"UK",'Relevant - Not CRM not valid'!$M$2:$M$416,"Research",'Relevant - Not CRM not valid'!$R$2:$R$416,"Operational")+COUNTIFS('Relevant - In CRM not valid'!$T$2:$T$46,$A8,'Relevant - In CRM not valid'!$G$2:$G$46,"UK",'Relevant - In CRM not valid'!$M$2:$M$46,"Research",'Relevant - In CRM not valid'!$R$2:$R$46,"Operational") -> 60 | I8: =COUNTIFS('Relevant - In CRM valid'!$T$2:$T$4699,$A8,'Relevant - In CRM valid'!$G$2:$G$4699,"UK",'Relevant - In CRM valid'!$M$2:$M$4699,"Research",'Relevant - In CRM valid'!$R$2:$R$4699,"Academic")+COUNTIFS('Relevant - In CRM unknown'!$T$2:$T$253,$A8,'Relevant - In CRM unknown'!$G$2:$G$253,"UK",'Relevant - In CRM unknown'!$M$2:$M$253,"Research",'Relevant - In CRM unknown'!$R$2:$R$253,"Academic")+COUNTIFS('Relevant - IN NOW CRM valid'!$T$2:$T$2328,$A8,'Relevant - IN NOW CRM valid'!$G$2:$G$2328,"UK",'Relevant - IN NOW CRM valid'!$M$2:$M$2328,"Research",'Relevant - IN NOW CRM valid'!$R$2:$R$2328,"Academic")+COUNTIFS('Relevant - IN NOW CRM unknown'!$T$2:$T$1227,$A8,'Relevant - IN NOW CRM unknown'!$G$2:$G$1227,"UK",'Relevant - IN NOW CRM unknown'!$M$2:$M$1227,"Research",'Relevant - IN NOW CRM unknown'!$R$2:$R$1227,"Academic")+COUNTIFS('Relevant - Not CRM not valid'!$T$2:$T$416,$A8,'Relevant - Not CRM not valid'!$G$2:$G$416,"UK",'Relevant - Not CRM not valid'!$M$2:$M$416,"Research",'Relevant - Not CRM not valid'!$R$2:$R$416,"Academic")+COUNTIFS('Relevant - In CRM not valid'!$T$2:$T$46,$A8,'Relevant - In CRM not valid'!$G$2:$G$46,"UK",'Relevant - In CRM not valid'!$M$2:$M$46,"Research",'Relevant - In CRM not valid'!$R$2:$R$46,"Academic") -> 3 | J8: =COUNTIFS('Relevant - In CRM valid'!$T$2:$T$4699,$A8,'Relevant - In CRM valid'!$G$2:$G$4699,"UK",'Relevant - In CRM valid'!$M$2:$M$4699,"Finance")+COUNTIFS('Relevant - In CRM unknown'!$T$2:$T$253,$A8,'Relevant - In CRM unknown'!$G$2:$G$253,"UK",'Relevant - In CRM unknown'!$M$2:$M$253,"Finance")+COUNTIFS('Relevant - IN NOW CRM valid'!$T$2:$T$2328,$A8,'Relevant - IN NOW CRM valid'!$G$2:$G$2328,"UK",'Relevant - IN NOW CRM valid'!$M$2:$M$2328,"Finance")+COUNTIFS('Relevant - IN NOW CRM unknown'!$T$2:$T$1227,$A8,'Relevant - IN NOW CRM unknown'!$G$2:$G$1227,"UK",'Relevant - IN NOW CRM unknown'!$M$2:$M$1227,"Finance")+COUNTIFS('Relevant - Not CRM not valid'!$T$2:$T$416,$A8,'Relevant - Not CRM not valid'!$G$2:$G$416,"UK",'Relevant - Not CRM not valid'!$M$2:$M$416,"Finance")+COUNTIFS('Relevant - In CRM not valid'!$T$2:$T$46,$A8,'Relevant - In CRM not valid'!$G$2:$G$46,"UK",'Relevant - In CRM not valid'!$M$2:$M$46,"Finance") -> 14 | K8: =COUNTIFS('Relevant - In CRM valid'!$T$2:$T$4699,$A8,'Relevant - In CRM valid'!$G$2:$G$4699,"UK",'Relevant - In CRM valid'!$M$2:$M$4699,"IT/Systems")+COUNTIFS('Relevant - In CRM unknown'!$T$2:$T$253,$A8,'Relevant - In CRM unknown'!$G$2:$G$253,"UK",'Relevant - In CRM unknown'!$M$2:$M$253,"IT/Systems")+COUNTIFS('Relevant - IN NOW CRM valid'!$T$2:$T$2328,$A8,'Relevant - IN NOW CRM valid'!$G$2:$G$2328,"UK",'Relevant - IN NOW CRM valid'!$M$2:$M$2328,"IT/Systems")+COUNTIFS('Relevant - IN NOW CRM unknown'!$T$2:$T$1227,$A8,'Relevant - IN NOW CRM unknown'!$G$2:$G$1227,"UK",'Relevant - IN NOW CRM unknown'!$M$2:$M$1227,"IT/Systems")+COUNTIFS('Relevant - Not CRM not valid'!$T$2:$T$416,$A8,'Relevant - Not CRM not valid'!$G$2:$G$416,"UK",'Relevant - Not CRM not valid'!$M$2:$M$416,"IT/Systems")+COUNTIFS('Relevant - In CRM not valid'!$T$2:$T$46,$A8,'Relevant - In CRM not valid'!$G$2:$G$46,"UK",'Relevant - In CRM not valid'!$M$2:$M$46,"IT/Systems") -> 3 | L8: =COUNTIFS('Relevant - In CRM valid'!$T$2:$T$4699,$A8,'Relevant - In CRM valid'!$G$2:$G$4699,"UK",'Relevant - In CRM valid'!$M$2:$M$4699,"")+COUNTIFS('Relevant - In CRM unknown'!$T$2:$T$253,$A8,'Relevant - In CRM unknown'!$G$2:$G$253,"UK",'Relevant - In CRM unknown'!$M$2:$M$253,"")+COUNTIFS('Relevant - IN NOW CRM valid'!$T$2:$T$2328,$A8,'Relevant - IN NOW CRM valid'!$G$2:$G$2328,"UK",'Relevant - IN NOW CRM valid'!$M$2:$M$2328,"")+COUNTIFS('Relevant - IN NOW CRM unknown'!$T$2:$T$1227,$A8,'Relevant - IN NOW CRM unknown'!$G$2:$G$1227,"UK",'Relevant - IN NOW CRM unknown'!$M$2:$M$1227,"")+COUNTIFS('Relevant - Not CRM not valid'!$T$2:$T$416,$A8,'Relevant - Not CRM not valid'!$G$2:$G$416,"UK",'Relevant - Not CRM not valid'!$M$2:$M$416,"")+COUNTIFS('Relevant - In CRM not valid'!$T$2:$T$46,$A8,'Relevant - In CRM not valid'!$G$2:$G$46,"UK",'Relevant - In CRM not valid'!$M$2:$M$46,"") -> 3 | M8: =(F8>0)+(J8>0)+(K8>0) -> 3 | N8: =COUNTIFS('Relevant - In CRM valid'!$T$2:$T$4699,$A8,'Relevant - In CRM valid'!$G$2:$G$4699,"UK",'Relevant - In CRM valid'!$Q$2:$Q$4699,"valid")+COUNTIFS('Relevant - In CRM unknown'!$T$2:$T$253,$A8,'Relevant - In CRM unknown'!$G$2:$G$253,"UK",'Relevant - In CRM unknown'!$Q$2:$Q$253,"valid")+COUNTIFS('Relevant - IN NOW CRM valid'!$T$2:$T$2328,$A8,'Relevant - IN NOW CRM valid'!$G$2:$G$2328,"UK",'Relevant - IN NOW CRM valid'!$Q$2:$Q$2328,"valid")+COUNTIFS('Relevant - IN NOW CRM unknown'!$T$2:$T$1227,$A8,'Relevant - IN NOW CRM unknown'!$G$2:$G$1227,"UK",'Relevant - IN NOW CRM unknown'!$Q$2:$Q$1227,"valid")+COUNTIFS('Relevant - Not CRM not valid'!$T$2:$T$416,$A8,'Relevant - Not CRM not valid'!$G$2:$G$416,"UK",'Relevant - Not CRM not valid'!$Q$2:$Q$416,"valid")+COUNTIFS('Relevant - In CRM not valid'!$T$2:$T$46,$A8,'Relevant - In CRM not valid'!$G$2:$G$46,"UK",'Relevant - In CRM not valid'!$Q$2:$Q$46,"valid") -> 13 | O8: =IF(F8=0,"Research ","")&IF(J8=0,"Finance ","")&IF(K8=0,"IT/Systems","")
A9: manchester metropolitan university | B9: The Manchester Metropolitan University | C9: University | D9: =IFERROR(INDEX('UK Target Institutions'!$D$2:$D$727,MATCH($A9,'UK Target Institutions'!$A$2:$A$727,0)),"") -> Yes | E9: =COUNTIFS('Relevant - In CRM valid'!$T$2:$T$4699,$A9,'Relevant - In CRM valid'!$G$2:$G$4699,"UK")+COUNTIFS('Relevant - In CRM unknown'!$T$2:$T$253,$A9,'Relevant - In CRM unknown'!$G$2:$G$253,"UK")+COUNTIFS('Relevant - IN NOW CRM valid'!$T$2:$T$2328,$A9,'Relevant - IN NOW CRM valid'!$G$2:$G$2328,"UK")+COUNTIFS('Relevant - IN NOW CRM unknown'!$T$2:$T$1227,$A9,'Relevant - IN NOW CRM unknown'!$G$2:$G$1227,"UK")+COUNTIFS('Relevant - Not CRM not valid'!$T$2:$T$416,$A9,'Relevant - Not CRM not valid'!$G$2:$G$416,"UK")+COUNTIFS('Relevant - In CRM not valid'!$T$2:$T$46,$A9,'Relevant - In CRM not valid'!$G$2:$G$46,"UK") -> 109 | F9: =COUNTIFS('Relevant - In CRM valid'!$T$2:$T$4699,$A9,'Relevant - In CRM valid'!$G$2:$G$4699,"UK",'Relevant - In CRM valid'!$M$2:$M$4699,"Research")+COUNTIFS('Relevant - In CRM unknown'!$T$2:$T$253,$A9,'Relevant - In CRM unknown'!$G$2:$G$253,"UK",'Relevant - In CRM unknown'!$M$2:$M$253,"Research")+COUNTIFS('Relevant - IN NOW CRM valid'!$T$2:$T$2328,$A9,'Relevant - IN NOW CRM valid'!$G$2:$G$2328,"UK",'Relevant - IN NOW CRM valid'!$M$2:$M$2328,"Research")+COUNTIFS('Relevant - IN NOW CRM unknown'!$T$2:$T$1227,$A9,'Relevant - IN NOW CRM unknown'!$G$2:$G$1227,"UK",'Relevant - IN NOW CRM unknown'!$M$2:$M$1227,"Research")+COUNTIFS('Relevant - Not CRM not valid'!$T$2:$T$416,$A9,'Relevant - Not CRM not valid'!$G$2:$G$416,"UK",'Relevant - Not CRM not valid'!$M$2:$M$416,"Research")+COUNTIFS('Relevant - In CRM not valid'!$T$2:$T$46,$A9,'Relevant - In CRM not valid'!$G$2:$G$46,"UK",'Relevant - In CRM not valid'!$M$2:$M$46,"Research") -> 76 | G9: =COUNTIFS('Relevant - In CRM valid'!$T$2:$T$4699,$A9,'Relevant - In CRM valid'!$G$2:$G$4699,"UK",'Relevant - In CRM valid'!$M$2:$M$4699,"Research",'Relevant - In CRM valid'!$R$2:$R$4699,"Senior")+COUNTIFS('Relevant - In CRM unknown'!$T$2:$T$253,$A9,'Relevant - In CRM unknown'!$G$2:$G$253,"UK",'Relevant - In CRM unknown'!$M$2:$M$253,"Research",'Relevant - In CRM unknown'!$R$2:$R$253,"Senior")+COUNTIFS('Relevant - IN NOW CRM valid'!$T$2:$T$2328,$A9,'Relevant - IN NOW CRM valid'!$G$2:$G$2328,"UK",'Relevant - IN NOW CRM valid'!$M$2:$M$2328,"Research",'Relevant - IN NOW CRM valid'!$R$2:$R$2328,"Senior")+COUNTIFS('Relevant - IN NOW CRM unknown'!$T$2:$T$1227,$A9,'Relevant - IN NOW CRM unknown'!$G$2:$G$1227,"UK",'Relevant - IN NOW CRM unknown'!$M$2:$M$1227,"Research",'Relevant - IN NOW CRM unknown'!$R$2:$R$1227,"Senior")+COUNTIFS('Relevant - Not CRM not valid'!$T$2:$T$416,$A9,'Relevant - Not CRM not valid'!$G$2:$G$416,"UK",'Relevant - Not CRM not valid'!$M$2:$M$416,"Research",'Relevant - Not CRM not valid'!$R$2:$R$416,"Senior")+COUNTIFS('Relevant - In CRM not valid'!$T$2:$T$46,$A9,'Relevant - In CRM not valid'!$G$2:$G$46,"UK",'Relevant - In CRM not valid'!$M$2:$M$46,"Research",'Relevant - In CRM not valid'!$R$2:$R$46,"Senior") -> 40 | H9: =COUNTIFS('Relevant - In CRM valid'!$T$2:$T$4699,$A9,'Relevant - In CRM valid'!$G$2:$G$4699,"UK",'Relevant - In CRM valid'!$M$2:$M$4699,"Research",'Relevant - In CRM valid'!$R$2:$R$4699,"Operational")+COUNTIFS('Relevant - In CRM unknown'!$T$2:$T$253,$A9,'Relevant - In CRM unknown'!$G$2:$G$253,"UK",'Relevant - In CRM unknown'!$M$2:$M$253,"Research",'Relevant - In CRM unknown'!$R$2:$R$253,"Operational")+COUNTIFS('Relevant - IN NOW CRM valid'!$T$2:$T$2328,$A9,'Relevant - IN NOW CRM valid'!$G$2:$G$2328,"UK",'Relevant - IN NOW CRM valid'!$M$2:$M$2328,"Research",'Relevant - IN NOW CRM valid'!$R$2:$R$2328,"Operational")+COUNTIFS('Relevant - IN NOW CRM unknown'!$T$2:$T$1227,$A9,'Relevant - IN NOW CRM unknown'!$G$2:$G$1227,"UK",'Relevant - IN NOW CRM unknown'!$M$2:$M$1227,"Research",'Relevant - IN NOW CRM unknown'!$R$2:$R$1227,"Operational")+COUNTIFS('Relevant - Not CRM not valid'!$T$2:$T$416,$A9,'Relevant - Not CRM not valid'!$G$2:$G$416,"UK",'Relevant - Not CRM not valid'!$M$2:$M$416,"Research",'Relevant - Not CRM not valid'!$R$2:$R$416,"Operational")+COUNTIFS('Relevant - In CRM not valid'!$T$2:$T$46,$A9,'Relevant - In CRM not valid'!$G$2:$G$46,"UK",'Relevant - In CRM not valid'!$M$2:$M$46,"Research",'Relevant - In CRM not valid'!$R$2:$R$46,"Operational") -> 36 | I9: =COUNTIFS('Relevant - In CRM valid'!$T$2:$T$4699,$A9,'Relevant - In CRM valid'!$G$2:$G$4699,"UK",'Relevant - In CRM valid'!$M$2:$M$4699,"Research",'Relevant - In CRM valid'!$R$2:$R$4699,"Academic")+COUNTIFS('Relevant - In CRM unknown'!$T$2:$T$253,$A9,'Relevant - In CRM unknown'!$G$2:$G$253,"UK",'Relevant - In CRM unknown'!$M$2:$M$253,"Research",'Relevant - In CRM unknown'!$R$2:$R$253,"Academic")+COUNTIFS('Relevant - IN NOW CRM valid'!$T$2:$T$2328,$A9,'Relevant - IN NOW CRM valid'!$G$2:$G$2328,"UK",'Relevant - IN NOW CRM valid'!$M$2:$M$2328,"Research",'Relevant - IN NOW CRM valid'!$R$2:$R$2328,"Academic")+COUNTIFS('Relevant - IN NOW CRM unknown'!$T$2:$T$1227,$A9,'Relevant - IN NOW CRM unknown'!$G$2:$G$1227,"UK",'Relevant - IN NOW CRM unknown'!$M$2:$M$1227,"Research",'Relevant - IN NOW CRM unknown'!$R$2:$R$1227,"Academic")+COUNTIFS('Relevant - Not CRM not valid'!$T$2:$T$416,$A9,'Relevant - Not CRM not valid'!$G$2:$G$416,"UK",'Relevant - Not CRM not valid'!$M$2:$M$416,"Research",'Relevant - Not CRM not valid'!$R$2:$R$416,"Academic")+COUNTIFS('Relevant - In CRM not valid'!$T$2:$T$46,$A9,'Relevant - In CRM not valid'!$G$2:$G$46,"UK",'Relevant - In CRM not valid'!$M$2:$M$46,"Research",'Relevant - In CRM not valid'!$R$2:$R$46,"Academic") -> 0 | J9: =COUNTIFS('Relevant - In CRM valid'!$T$2:$T$4699,$A9,'Relevant - In CRM valid'!$G$2:$G$4699,"UK",'Relevant - In CRM valid'!$M$2:$M$4699,"Finance")+COUNTIFS('Relevant - In CRM unknown'!$T$2:$T$253,$A9,'Relevant - In CRM unknown'!$G$2:$G$253,"UK",'Relevant - In CRM unknown'!$M$2:$M$253,"Finance")+COUNTIFS('Relevant - IN NOW CRM valid'!$T$2:$T$2328,$A9,'Relevant - IN NOW CRM valid'!$G$2:$G$2328,"UK",'Relevant - IN NOW CRM valid'!$M$2:$M$2328,"Finance")+COUNTIFS('Relevant - IN NOW CRM unknown'!$T$2:$T$1227,$A9,'Relevant - IN NOW CRM unknown'!$G$2:$G$1227,"UK",'Relevant - IN NOW CRM unknown'!$M$2:$M$1227,"Finance")+COUNTIFS('Relevant - Not CRM not valid'!$T$2:$T$416,$A9,'Relevant - Not CRM not valid'!$G$2:$G$416,"UK",'Relevant - Not CRM not valid'!$M$2:$M$416,"Finance")+COUNTIFS('Relevant - In CRM not valid'!$T$2:$T$46,$A9,'Relevant - In CRM not valid'!$G$2:$G$46,"UK",'Relevant - In CRM not valid'!$M$2:$M$46,"Finance") -> 17 | K9: =COUNTIFS('Relevant - In CRM valid'!$T$2:$T$4699,$A9,'Relevant - In CRM valid'!$G$2:$G$4699,"UK",'Relevant - In CRM valid'!$M$2:$M$4699,"IT/Systems")+COUNTIFS('Relevant - In CRM unknown'!$T$2:$T$253,$A9,'Relevant - In CRM unknown'!$G$2:$G$253,"UK",'Relevant - In CRM unknown'!$M$2:$M$253,"IT/Systems")+COUNTIFS('Relevant - IN NOW CRM valid'!$T$2:$T$2328,$A9,'Relevant - IN NOW CRM valid'!$G$2:$G$2328,"UK",'Relevant - IN NOW CRM valid'!$M$2:$M$2328,"IT/Systems")+COUNTIFS('Relevant - IN NOW CRM unknown'!$T$2:$T$1227,$A9,'Relevant - IN NOW CRM unknown'!$G$2:$G$1227,"UK",'Relevant - IN NOW CRM unknown'!$M$2:$M$1227,"IT/Systems")+COUNTIFS('Relevant - Not CRM not valid'!$T$2:$T$416,$A9,'Relevant - Not CRM not valid'!$G$2:$G$416,"UK",'Relevant - Not CRM not valid'!$M$2:$M$416,"IT/Systems")+COUNTIFS('Relevant - In CRM not valid'!$T$2:$T$46,$A9,'Relevant - In CRM not valid'!$G$2:$G$46,"UK",'Relevant - In CRM not valid'!$M$2:$M$46,"IT/Systems") -> 14 | L9: =COUNTIFS('Relevant - In CRM valid'!$T$2:$T$4699,$A9,'Relevant - In CRM valid'!$G$2:$G$4699,"UK",'Relevant - In CRM valid'!$M$2:$M$4699,"")+COUNTIFS('Relevant - In CRM unknown'!$T$2:$T$253,$A9,'Relevant - In CRM unknown'!$G$2:$G$253,"UK",'Relevant - In CRM unknown'!$M$2:$M$253,"")+COUNTIFS('Relevant - IN NOW CRM valid'!$T$2:$T$2328,$A9,'Relevant - IN NOW CRM valid'!$G$2:$G$2328,"UK",'Relevant - IN NOW CRM valid'!$M$2:$M$2328,"")+COUNTIFS('Relevant - IN NOW CRM unknown'!$T$2:$T$1227,$A9,'Relevant - IN NOW CRM unknown'!$G$2:$G$1227,"UK",'Relevant - IN NOW CRM unknown'!$M$2:$M$1227,"")+COUNTIFS('Relevant - Not CRM not valid'!$T$2:$T$416,$A9,'Relevant - Not CRM not valid'!$G$2:$G$416,"UK",'Relevant - Not CRM not valid'!$M$2:$M$416,"")+COUNTIFS('Relevant - In CRM not valid'!$T$2:$T$46,$A9,'Relevant - In CRM not valid'!$G$2:$G$46,"UK",'Relevant - In CRM not valid'!$M$2:$M$46,"") -> 1 | M9: =(F9>0)+(J9>0)+(K9>0) -> 3 | N9: =COUNTIFS('Relevant - In CRM valid'!$T$2:$T$4699,$A9,'Relevant - In CRM valid'!$G$2:$G$4699,"UK",'Relevant - In CRM valid'!$Q$2:$Q$4699,"valid")+COUNTIFS('Relevant - In CRM unknown'!$T$2:$T$253,$A9,'Relevant - In CRM unknown'!$G$2:$G$253,"UK",'Relevant - In CRM unknown'!$Q$2:$Q$253,"valid")+COUNTIFS('Relevant - IN NOW CRM valid'!$T$2:$T$2328,$A9,'Relevant - IN NOW CRM valid'!$G$2:$G$2328,"UK",'Relevant - IN NOW CRM valid'!$Q$2:$Q$2328,"valid")+COUNTIFS('Relevant - IN NOW CRM unknown'!$T$2:$T$1227,$A9,'Relevant - IN NOW CRM unknown'!$G$2:$G$1227,"UK",'Relevant - IN NOW CRM unknown'!$Q$2:$Q$1227,"valid")+COUNTIFS('Relevant - Not CRM not valid'!$T$2:$T$416,$A9,'Relevant - Not CRM not valid'!$G$2:$G$416,"UK",'Relevant - Not CRM not valid'!$Q$2:$Q$416,"valid")+COUNTIFS('Relevant - In CRM not valid'!$T$2:$T$46,$A9,'Relevant - In CRM not valid'!$G$2:$G$46,"UK",'Relevant - In CRM not valid'!$Q$2:$Q$46,"valid") -> 105 | O9: =IF(F9=0,"Research ","")&IF(J9=0,"Finance ","")&IF(K9=0,"IT/Systems","")
A10: york university | B10: University of York | C10: University | D10: =IFERROR(INDEX('UK Target Institutions'!$D$2:$D$727,MATCH($A10,'UK Target Institutions'!$A$2:$A$727,0)),"") -> Yes | E10: =COUNTIFS('Relevant - In CRM valid'!$T$2:$T$4699,$A10,'Relevant - In CRM valid'!$G$2:$G$4699,"UK")+COUNTIFS('Relevant - In CRM unknown'!$T$2:$T$253,$A10,'Relevant - In CRM unknown'!$G$2:$G$253,"UK")+COUNTIFS('Relevant - IN NOW CRM valid'!$T$2:$T$2328,$A10,'Relevant - IN NOW CRM valid'!$G$2:$G$2328,"UK")+COUNTIFS('Relevant - IN NOW CRM unknown'!$T$2:$T$1227,$A10,'Relevant - IN NOW CRM unknown'!$G$2:$G$1227,"UK")+COUNTIFS('Relevant - Not CRM not valid'!$T$2:$T$416,$A10,'Relevant - Not CRM not valid'!$G$2:$G$416,"UK")+COUNTIFS('Relevant - In CRM not valid'!$T$2:$T$46,$A10,'Relevant - In CRM not valid'!$G$2:$G$46,"UK") -> 92 | F10: =COUNTIFS('Relevant - In CRM valid'!$T$2:$T$4699,$A10,'Relevant - In CRM valid'!$G$2:$G$4699,"UK",'Relevant - In CRM valid'!$M$2:$M$4699,"Research")+COUNTIFS('Relevant - In CRM unknown'!$T$2:$T$253,$A10,'Relevant - In CRM unknown'!$G$2:$G$253,"UK",'Relevant - In CRM unknown'!$M$2:$M$253,"Research")+COUNTIFS('Relevant - IN NOW CRM valid'!$T$2:$T$2328,$A10,'Relevant - IN NOW CRM valid'!$G$2:$G$2328,"UK",'Relevant - IN NOW CRM valid'!$M$2:$M$2328,"Research")+COUNTIFS('Relevant - IN NOW CRM unknown'!$T$2:$T$1227,$A10,'Relevant - IN NOW CRM unknown'!$G$2:$G$1227,"UK",'Relevant - IN NOW CRM unknown'!$M$2:$M$1227,"Research")+COUNTIFS('Relevant - Not CRM not valid'!$T$2:$T$416,$A10,'Relevant - Not CRM not valid'!$G$2:$G$416,"UK",'Relevant - Not CRM not valid'!$M$2:$M$416,"Research")+COUNTIFS('Relevant - In CRM not valid'!$T$2:$T$46,$A10,'Relevant - In CRM not valid'!$G$2:$G$46,"UK",'Relevant - In CRM not valid'!$M$2:$M$46,"Research") -> 77 | G10: =COUNTIFS('Relevant - In CRM valid'!$T$2:$T$4699,$A10,'Relevant - In CRM valid'!$G$2:$G$4699,"UK",'Relevant - In CRM valid'!$M$2:$M$4699,"Research",'Relevant - In CRM valid'!$R$2:$R$4699,"Senior")+COUNTIFS('Relevant - In CRM unknown'!$T$2:$T$253,$A10,'Relevant - In CRM unknown'!$G$2:$G$253,"UK",'Relevant - In CRM unknown'!$M$2:$M$253,"Research",'Relevant - In CRM unknown'!$R$2:$R$253,"Senior")+COUNTIFS('Relevant - IN NOW CRM valid'!$T$2:$T$2328,$A10,'Relevant - IN NOW CRM valid'!$G$2:$G$2328,"UK",'Relevant - IN NOW CRM valid'!$M$2:$M$2328,"Research",'Relevant - IN NOW CRM valid'!$R$2:$R$2328,"Senior")+COUNTIFS('Relevant - IN NOW CRM unknown'!$T$2:$T$1227,$A10,'Relevant - IN NOW CRM unknown'!$G$2:$G$1227,"UK",'Relevant - IN NOW CRM unknown'!$M$2:$M$1227,"Research",'Relevant - IN NOW CRM unknown'!$R$2:$R$1227,"Senior")+COUNTIFS('Relevant - Not CRM not valid'!$T$2:$T$416,$A10,'Relevant - Not CRM not valid'!$G$2:$G$416,"UK",'Relevant - Not CRM not valid'!$M$2:$M$416,"Research",'Relevant - Not CRM not valid'!$R$2:$R$416,"Senior")+COUNTIFS('Relevant - In CRM not valid'!$T$2:$T$46,$A10,'Relevant - In CRM not valid'!$G$2:$G$46,"UK",'Relevant - In CRM not valid'!$M$2:$M$46,"Research",'Relevant - In CRM not valid'!$R$2:$R$46,"Senior") -> 28 | H10: =COUNTIFS('Relevant - In CRM valid'!$T$2:$T$4699,$A10,'Relevant - In CRM valid'!$G$2:$G$4699,"UK",'Relevant - In CRM valid'!$M$2:$M$4699,"Research",'Relevant - In CRM valid'!$R$2:$R$4699,"Operational")+COUNTIFS('Relevant - In CRM unknown'!$T$2:$T$253,$A10,'Relevant - In CRM unknown'!$G$2:$G$253,"UK",'Relevant - In CRM unknown'!$M$2:$M$253,"Research",'Relevant - In CRM unknown'!$R$2:$R$253,"Operational")+COUNTIFS('Relevant - IN NOW CRM valid'!$T$2:$T$2328,$A10,'Relevant - IN NOW CRM valid'!$G$2:$G$2328,"UK",'Relevant - IN NOW CRM valid'!$M$2:$M$2328,"Research",'Relevant - IN NOW CRM valid'!$R$2:$R$2328,"Operational")+COUNTIFS('Relevant - IN NOW CRM unknown'!$T$2:$T$1227,$A10,'Relevant - IN NOW CRM unknown'!$G$2:$G$1227,"UK",'Relevant - IN NOW CRM unknown'!$M$2:$M$1227,"Research",'Relevant - IN NOW CRM unknown'!$R$2:$R$1227,"Operational")+COUNTIFS('Relevant - Not CRM not valid'!$T$2:$T$416,$A10,'Relevant - Not CRM not valid'!$G$2:$G$416,"UK",'Relevant - Not CRM not valid'!$M$2:$M$416,"Research",'Relevant - Not CRM not valid'!$R$2:$R$416,"Operational")+COUNTIFS('Relevant - In CRM not valid'!$T$2:$T$46,$A10,'Relevant - In CRM not valid'!$G$2:$G$46,"UK",'Relevant - In CRM not valid'!$M$2:$M$46,"Research",'Relevant - In CRM not valid'!$R$2:$R$46,"Operational") -> 44 | I10: =COUNTIFS('Relevant - In CRM valid'!$T$2:$T$4699,$A10,'Relevant - In CRM valid'!$G$2:$G$4699,"UK",'Relevant - In CRM valid'!$M$2:$M$4699,"Research",'Relevant - In CRM valid'!$R$2:$R$4699,"Academic")+COUNTIFS('Relevant - In CRM unknown'!$T$2:$T$253,$A10,'Relevant - In CRM unknown'!$G$2:$G$253,"UK",'Relevant - In CRM unknown'!$M$2:$M$253,"Research",'Relevant - In CRM unknown'!$R$2:$R$253,"Academic")+COUNTIFS('Relevant - IN NOW CRM valid'!$T$2:$T$2328,$A10,'Relevant - IN NOW CRM valid'!$G$2:$G$2328,"UK",'Relevant - IN NOW CRM valid'!$M$2:$M$2328,"Research",'Relevant - IN NOW CRM valid'!$R$2:$R$2328,"Academic")+COUNTIFS('Relevant - IN NOW CRM unknown'!$T$2:$T$1227,$A10,'Relevant - IN NOW CRM unknown'!$G$2:$G$1227,"UK",'Relevant - IN NOW CRM unknown'!$M$2:$M$1227,"Research",'Relevant - IN NOW CRM unknown'!$R$2:$R$1227,"Academic")+COUNTIFS('Relevant - Not CRM not valid'!$T$2:$T$416,$A10,'Relevant - Not CRM not valid'!$G$2:$G$416,"UK",'Relevant - Not CRM not valid'!$M$2:$M$416,"Research",'Relevant - Not CRM not valid'!$R$2:$R$416,"Academic")+COUNTIFS('Relevant - In CRM not valid'!$T$2:$T$46,$A10,'Relevant - In CRM not valid'!$G$2:$G$46,"UK",'Relevant - In CRM not valid'!$M$2:$M$46,"Research",'Relevant - In CRM not valid'!$R$2:$R$46,"Academic") -> 5 | J10: =COUNTIFS('Relevant - In CRM valid'!$T$2:$T$4699,$A10,'Relevant - In CRM valid'!$G$2:$G$4699,"UK",'Relevant - In CRM valid'!$M$2:$M$4699,"Finance")+COUNTIFS('Relevant - In CRM unknown'!$T$2:$T$253,$A10,'Relevant - In CRM unknown'!$G$2:$G$253,"UK",'Relevant - In CRM unknown'!$M$2:$M$253,"Finance")+COUNTIFS('Relevant - IN NOW CRM valid'!$T$2:$T$2328,$A10,'Relevant - IN NOW CRM valid'!$G$2:$G$2328,"UK",'Relevant - IN NOW CRM valid'!$M$2:$M$2328,"Finance")+COUNTIFS('Relevant - IN NOW CRM unknown'!$T$2:$T$1227,$A10,'Relevant - IN NOW CRM unknown'!$G$2:$G$1227,"UK",'Relevant - IN NOW CRM unknown'!$M$2:$M$1227,"Finance")+COUNTIFS('Relevant - Not CRM not valid'!$T$2:$T$416,$A10,'Relevant - Not CRM not valid'!$G$2:$G$416,"UK",'Relevant - Not CRM not valid'!$M$2:$M$416,"Finance")+COUNTIFS('Relevant - In CRM not valid'!$T$2:$T$46,$A10,'Relevant - In CRM not valid'!$G$2:$G$46,"UK",'Relevant - In CRM not valid'!$M$2:$M$46,"Finance") -> 10 | K10: =COUNTIFS('Relevant - In CRM valid'!$T$2:$T$4699,$A10,'Relevant - In CRM valid'!$G$2:$G$4699,"UK",'Relevant - In CRM valid'!$M$2:$M$4699,"IT/Systems")+COUNTIFS('Relevant - In CRM unknown'!$T$2:$T$253,$A10,'Relevant - In CRM unknown'!$G$2:$G$253,"UK",'Relevant - In CRM unknown'!$M$2:$M$253,"IT/Systems")+COUNTIFS('Relevant - IN NOW CRM valid'!$T$2:$T$2328,$A10,'Relevant - IN NOW CRM valid'!$G$2:$G$2328,"UK",'Relevant - IN NOW CRM valid'!$M$2:$M$2328,"IT/Systems")+COUNTIFS('Relevant - IN NOW CRM unknown'!$T$2:$T$1227,$A10,'Relevant - IN NOW CRM unknown'!$G$2:$G$1227,"UK",'Relevant - IN NOW CRM unknown'!$M$2:$M$1227,"IT/Systems")+COUNTIFS('Relevant - Not CRM not valid'!$T$2:$T$416,$A10,'Relevant - Not CRM not valid'!$G$2:$G$416,"UK",'Relevant - Not CRM not valid'!$M$2:$M$416,"IT/Systems")+COUNTIFS('Relevant - In CRM not valid'!$T$2:$T$46,$A10,'Relevant - In CRM not valid'!$G$2:$G$46,"UK",'Relevant - In CRM not valid'!$M$2:$M$46,"IT/Systems") -> 3 | L10: =COUNTIFS('Relevant - In CRM valid'!$T$2:$T$4699,$A10,'Relevant - In CRM valid'!$G$2:$G$4699,"UK",'Relevant - In CRM valid'!$M$2:$M$4699,"")+COUNTIFS('Relevant - In CRM unknown'!$T$2:$T$253,$A10,'Relevant - In CRM unknown'!$G$2:$G$253,"UK",'Relevant - In CRM unknown'!$M$2:$M$253,"")+COUNTIFS('Relevant - IN NOW CRM valid'!$T$2:$T$2328,$A10,'Relevant - IN NOW CRM valid'!$G$2:$G$2328,"UK",'Relevant - IN NOW CRM valid'!$M$2:$M$2328,"")+COUNTIFS('Relevant - IN NOW CRM unknown'!$T$2:$T$1227,$A10,'Relevant - IN NOW CRM unknown'!$G$2:$G$1227,"UK",'Relevant - IN NOW CRM unknown'!$M$2:$M$1227,"")+COUNTIFS('Relevant - Not CRM not valid'!$T$2:$T$416,$A10,'Relevant - Not CRM not valid'!$G$2:$G$416,"UK",'Relevant - Not CRM not valid'!$M$2:$M$416,"")+COUNTIFS('Relevant - In CRM not valid'!$T$2:$T$46,$A10,'Relevant - In CRM not valid'!$G$2:$G$46,"UK",'Relevant - In CRM not valid'!$M$2:$M$46,"") -> 2 | M10: =(F10>0)+(J10>0)+(K10>0) -> 3 | N10: =COUNTIFS('Relevant - In CRM valid'!$T$2:$T$4699,$A10,'Relevant - In CRM valid'!$G$2:$G$4699,"UK",'Relevant - In CRM valid'!$Q$2:$Q$4699,"valid")+COUNTIFS('Relevant - In CRM unknown'!$T$2:$T$253,$A10,'Relevant - In CRM unknown'!$G$2:$G$253,"UK",'Relevant - In CRM unknown'!$Q$2:$Q$253,"valid")+COUNTIFS('Relevant - IN NOW CRM valid'!$T$2:$T$2328,$A10,'Relevant - IN NOW CRM valid'!$G$2:$G$2328,"UK",'Relevant - IN NOW CRM valid'!$Q$2:$Q$2328,"valid")+COUNTIFS('Relevant - IN NOW CRM unknown'!$T$2:$T$1227,$A10,'Relevant - IN NOW CRM unknown'!$G$2:$G$1227,"UK",'Relevant - IN NOW CRM unknown'!$Q$2:$Q$1227,"valid")+COUNTIFS('Relevant - Not CRM not valid'!$T$2:$T$416,$A10,'Relevant - Not CRM not valid'!$G$2:$G$416,"UK",'Relevant - Not CRM not valid'!$Q$2:$Q$416,"valid")+COUNTIFS('Relevant - In CRM not valid'!$T$2:$T$46,$A10,'Relevant - In CRM not valid'!$G$2:$G$46,"UK",'Relevant - In CRM not valid'!$Q$2:$Q$46,"valid") -> 81 | O10: =IF(F10=0,"Research ","")&IF(J10=0,"Finance ","")&IF(K10=0,"IT/Systems","")
A11: cardiff university | B11: Cardiff University | C11: University | D11: =IFERROR(INDEX('UK Target Institutions'!$D$2:$D$727,MATCH($A11,'UK Target Institutions'!$A$2:$A$727,0)),"") -> Yes | E11: =COUNTIFS('Relevant - In CRM valid'!$T$2:$T$4699,$A11,'Relevant - In CRM valid'!$G$2:$G$4699,"UK")+COUNTIFS('Relevant - In CRM unknown'!$T$2:$T$253,$A11,'Relevant - In CRM unknown'!$G$2:$G$253,"UK")+COUNTIFS('Relevant - IN NOW CRM valid'!$T$2:$T$2328,$A11,'Relevant - IN NOW CRM valid'!$G$2:$G$2328,"UK")+COUNTIFS('Relevant - IN NOW CRM unknown'!$T$2:$T$1227,$A11,'Relevant - IN NOW CRM unknown'!$G$2:$G$1227,"UK")+COUNTIFS('Relevant - Not CRM not valid'!$T$2:$T$416,$A11,'Relevant - Not CRM not valid'!$G$2:$G$416,"UK")+COUNTIFS('Relevant - In CRM not valid'!$T$2:$T$46,$A11,'Relevant - In CRM not valid'!$G$2:$G$46,"UK") -> 86 | F11: =COUNTIFS('Relevant - In CRM valid'!$T$2:$T$4699,$A11,'Relevant - In CRM valid'!$G$2:$G$4699,"UK",'Relevant - In CRM valid'!$M$2:$M$4699,"Research")+COUNTIFS('Relevant - In CRM unknown'!$T$2:$T$253,$A11,'Relevant - In CRM unknown'!$G$2:$G$253,"UK",'Relevant - In CRM unknown'!$M$2:$M$253,"Research")+COUNTIFS('Relevant - IN NOW CRM valid'!$T$2:$T$2328,$A11,'Relevant - IN NOW CRM valid'!$G$2:$G$2328,"UK",'Relevant - IN NOW CRM valid'!$M$2:$M$2328,"Research")+COUNTIFS('Relevant - IN NOW CRM unknown'!$T$2:$T$1227,$A11,'Relevant - IN NOW CRM unknown'!$G$2:$G$1227,"UK",'Relevant - IN NOW CRM unknown'!$M$2:$M$1227,"Research")+COUNTIFS('Relevant - Not CRM not valid'!$T$2:$T$416,$A11,'Relevant - Not CRM not valid'!$G$2:$G$416,"UK",'Relevant - Not CRM not valid'!$M$2:$M$416,"Research")+COUNTIFS('Relevant - In CRM not valid'!$T$2:$T$46,$A11,'Relevant - In CRM not valid'!$G$2:$G$46,"UK",'Relevant - In CRM not valid'!$M$2:$M$46,"Research") -> 52 | G11: =COUNTIFS('Relevant - In CRM valid'!$T$2:$T$4699,$A11,'Relevant - In CRM valid'!$G$2:$G$4699,"UK",'Relevant - In CRM valid'!$M$2:$M$4699,"Research",'Relevant - In CRM valid'!$R$2:$R$4699,"Senior")+COUNTIFS('Relevant - In CRM unknown'!$T$2:$T$253,$A11,'Relevant - In CRM unknown'!$G$2:$G$253,"UK",'Relevant - In CRM unknown'!$M$2:$M$253,"Research",'Relevant - In CRM unknown'!$R$2:$R$253,"Senior")+COUNTIFS('Relevant - IN NOW CRM valid'!$T$2:$T$2328,$A11,'Relevant - IN NOW CRM valid'!$G$2:$G$2328,"UK",'Relevant - IN NOW CRM valid'!$M$2:$M$2328,"Research",'Relevant - IN NOW CRM valid'!$R$2:$R$2328,"Senior")+COUNTIFS('Relevant - IN NOW CRM unknown'!$T$2:$T$1227,$A11,'Relevant - IN NOW CRM unknown'!$G$2:$G$1227,"UK",'Relevant - IN NOW CRM unknown'!$M$2:$M$1227,"Research",'Relevant - IN NOW CRM unknown'!$R$2:$R$1227,"Senior")+COUNTIFS('Relevant - Not CRM not valid'!$T$2:$T$416,$A11,'Relevant - Not CRM not valid'!$G$2:$G$416,"UK",'Relevant - Not CRM not valid'!$M$2:$M$416,"Research",'Relevant - Not CRM not valid'!$R$2:$R$416,"Senior")+COUNTIFS('Relevant - In CRM not valid'!$T$2:$T$46,$A11,'Relevant - In CRM not valid'!$G$2:$G$46,"UK",'Relevant - In CRM not valid'!$M$2:$M$46,"Research",'Relevant - In CRM not valid'!$R$2:$R$46,"Senior") -> 22 | H11: =COUNTIFS('Relevant - In CRM valid'!$T$2:$T$4699,$A11,'Relevant - In CRM valid'!$G$2:$G$4699,"UK",'Relevant - In CRM valid'!$M$2:$M$4699,"Research",'Relevant - In CRM valid'!$R$2:$R$4699,"Operational")+COUNTIFS('Relevant - In CRM unknown'!$T$2:$T$253,$A11,'Relevant - In CRM unknown'!$G$2:$G$253,"UK",'Relevant - In CRM unknown'!$M$2:$M$253,"Research",'Relevant - In CRM unknown'!$R$2:$R$253,"Operational")+COUNTIFS('Relevant - IN NOW CRM valid'!$T$2:$T$2328,$A11,'Relevant - IN NOW CRM valid'!$G$2:$G$2328,"UK",'Relevant - IN NOW CRM valid'!$M$2:$M$2328,"Research",'Relevant - IN NOW CRM valid'!$R$2:$R$2328,"Operational")+COUNTIFS('Relevant - IN NOW CRM unknown'!$T$2:$T$1227,$A11,'Relevant - IN NOW CRM unknown'!$G$2:$G$1227,"UK",'Relevant - IN NOW CRM unknown'!$M$2:$M$1227,"Research",'Relevant - IN NOW CRM unknown'!$R$2:$R$1227,"Operational")+COUNTIFS('Relevant - Not CRM not valid'!$T$2:$T$416,$A11,'Relevant - Not CRM not valid'!$G$2:$G$416,"UK",'Relevant - Not CRM not valid'!$M$2:$M$416,"Research",'Relevant - Not CRM not valid'!$R$2:$R$416,"Operational")+COUNTIFS('Relevant - In CRM not valid'!$T$2:$T$46,$A11,'Relevant - In CRM not valid'!$G$2:$G$46,"UK",'Relevant - In CRM not valid'!$M$2:$M$46,"Research",'Relevant - In CRM not valid'!$R$2:$R$46,"Operational") -> 26 | I11: =COUNTIFS('Relevant - In CRM valid'!$T$2:$T$4699,$A11,'Relevant - In CRM valid'!$G$2:$G$4699,"UK",'Relevant - In CRM valid'!$M$2:$M$4699,"Research",'Relevant - In CRM valid'!$R$2:$R$4699,"Academic")+COUNTIFS('Relevant - In CRM unknown'!$T$2:$T$253,$A11,'Relevant - In CRM unknown'!$G$2:$G$253,"UK",'Relevant - In CRM unknown'!$M$2:$M$253,"Research",'Relevant - In CRM unknown'!$R$2:$R$253,"Academic")+COUNTIFS('Relevant - IN NOW CRM valid'!$T$2:$T$2328,$A11,'Relevant - IN NOW CRM valid'!$G$2:$G$2328,"UK",'Relevant - IN NOW CRM valid'!$M$2:$M$2328,"Research",'Relevant - IN NOW CRM valid'!$R$2:$R$2328,"Academic")+COUNTIFS('Relevant - IN NOW CRM unknown'!$T$2:$T$1227,$A11,'Relevant - IN NOW CRM unknown'!$G$2:$G$1227,"UK",'Relevant - IN NOW CRM unknown'!$M$2:$M$1227,"Research",'Relevant - IN NOW CRM unknown'!$R$2:$R$1227,"Academic")+COUNTIFS('Relevant - Not CRM not valid'!$T$2:$T$416,$A11,'Relevant - Not CRM not valid'!$G$2:$G$416,"UK",'Relevant - Not CRM not valid'!$M$2:$M$416,"Research",'Relevant - Not CRM not valid'!$R$2:$R$416,"Academic")+COUNTIFS('Relevant - In CRM not valid'!$T$2:$T$46,$A11,'Relevant - In CRM not valid'!$G$2:$G$46,"UK",'Relevant - In CRM not valid'!$M$2:$M$46,"Research",'Relevant - In CRM not valid'!$R$2:$R$46,"Academic") -> 3 | J11: =COUNTIFS('Relevant - In CRM valid'!$T$2:$T$4699,$A11,'Relevant - In CRM valid'!$G$2:$G$4699,"UK",'Relevant - In CRM valid'!$M$2:$M$4699,"Finance")+COUNTIFS('Relevant - In CRM unknown'!$T$2:$T$253,$A11,'Relevant - In CRM unknown'!$G$2:$G$253,"UK",'Relevant - In CRM unknown'!$M$2:$M$253,"Finance")+COUNTIFS('Relevant - IN NOW CRM valid'!$T$2:$T$2328,$A11,'Relevant - IN NOW CRM valid'!$G$2:$G$2328,"UK",'Relevant - IN NOW CRM valid'!$M$2:$M$2328,"Finance")+COUNTIFS('Relevant - IN NOW CRM unknown'!$T$2:$T$1227,$A11,'Relevant - IN NOW CRM unknown'!$G$2:$G$1227,"UK",'Relevant - IN NOW CRM unknown'!$M$2:$M$1227,"Finance")+COUNTIFS('Relevant - Not CRM not valid'!$T$2:$T$416,$A11,'Relevant - Not CRM not valid'!$G$2:$G$416,"UK",'Relevant - Not CRM not valid'!$M$2:$M$416,"Finance")+COUNTIFS('Relevant - In CRM not valid'!$T$2:$T$46,$A11,'Relevant - In CRM not valid'!$G$2:$G$46,"UK",'Relevant - In CRM not valid'!$M$2:$M$46,"Finance") -> 19 | K11: =COUNTIFS('Relevant - In CRM valid'!$T$2:$T$4699,$A11,'Relevant - In CRM valid'!$G$2:$G$4699,"UK",'Relevant - In CRM valid'!$M$2:$M$4699,"IT/Systems")+COUNTIFS('Relevant - In CRM unknown'!$T$2:$T$253,$A11,'Relevant - In CRM unknown'!$G$2:$G$253,"UK",'Relevant - In CRM unknown'!$M$2:$M$253,"IT/Systems")+COUNTIFS('Relevant - IN NOW CRM valid'!$T$2:$T$2328,$A11,'Relevant - IN NOW CRM valid'!$G$2:$G$2328,"UK",'Relevant - IN NOW CRM valid'!$M$2:$M$2328,"IT/Systems")+COUNTIFS('Relevant - IN NOW CRM unknown'!$T$2:$T$1227,$A11,'Relevant - IN NOW CRM unknown'!$G$2:$G$1227,"UK",'Relevant - IN NOW CRM unknown'!$M$2:$M$1227,"IT/Systems")+COUNTIFS('Relevant - Not CRM not valid'!$T$2:$T$416,$A11,'Relevant - Not CRM not valid'!$G$2:$G$416,"UK",'Relevant - Not CRM not valid'!$M$2:$M$416,"IT/Systems")+COUNTIFS('Relevant - In CRM not valid'!$T$2:$T$46,$A11,'Relevant - In CRM not valid'!$G$2:$G$46,"UK",'Relevant - In CRM not valid'!$M$2:$M$46,"IT/Systems") -> 7 | L11: =COUNTIFS('Relevant - In CRM valid'!$T$2:$T$4699,$A11,'Relevant - In CRM valid'!$G$2:$G$4699,"UK",'Relevant - In CRM valid'!$M$2:$M$4699,"")+COUNTIFS('Relevant - In CRM unknown'!$T$2:$T$253,$A11,'Relevant - In CRM unknown'!$G$2:$G$253,"UK",'Relevant - In CRM unknown'!$M$2:$M$253,"")+COUNTIFS('Relevant - IN NOW CRM valid'!$T$2:$T$2328,$A11,'Relevant - IN NOW CRM valid'!$G$2:$G$2328,"UK",'Relevant - IN NOW CRM valid'!$M$2:$M$2328,"")+COUNTIFS('Relevant - IN NOW CRM unknown'!$T$2:$T$1227,$A11,'Relevant - IN NOW CRM unknown'!$G$2:$G$1227,"UK",'Relevant - IN NOW CRM unknown'!$M$2:$M$1227,"")+COUNTIFS('Relevant - Not CRM not valid'!$T$2:$T$416,$A11,'Relevant - Not CRM not valid'!$G$2:$G$416,"UK",'Relevant - Not CRM not valid'!$M$2:$M$416,"")+COUNTIFS('Relevant - In CRM not valid'!$T$2:$T$46,$A11,'Relevant - In CRM not valid'!$G$2:$G$46,"UK",'Relevant - In CRM not valid'!$M$2:$M$46,"") -> 8 | M11: =(F11>0)+(J11>0)+(K11>0) -> 3 | N11: =COUNTIFS('Relevant - In CRM valid'!$T$2:$T$4699,$A11,'Relevant - In CRM valid'!$G$2:$G$4699,"UK",'Relevant - In CRM valid'!$Q$2:$Q$4699,"valid")+COUNTIFS('Relevant - In CRM unknown'!$T$2:$T$253,$A11,'Relevant - In CRM unknown'!$G$2:$G$253,"UK",'Relevant - In CRM unknown'!$Q$2:$Q$253,"valid")+COUNTIFS('Relevant - IN NOW CRM valid'!$T$2:$T$2328,$A11,'Relevant - IN NOW CRM valid'!$G$2:$G$2328,"UK",'Relevant - IN NOW CRM valid'!$Q$2:$Q$2328,"valid")+COUNTIFS('Relevant - IN NOW CRM unknown'!$T$2:$T$1227,$A11,'Relevant - IN NOW CRM unknown'!$G$2:$G$1227,"UK",'Relevant - IN NOW CRM unknown'!$Q$2:$Q$1227,"valid")+COUNTIFS('Relevant - Not CRM not valid'!$T$2:$T$416,$A11,'Relevant - Not CRM not valid'!$G$2:$G$416,"UK",'Relevant - Not CRM not valid'!$Q$2:$Q$416,"valid")+COUNTIFS('Relevant - In CRM not valid'!$T$2:$T$46,$A11,'Relevant - In CRM not valid'!$G$2:$G$46,"UK",'Relevant - In CRM not valid'!$Q$2:$Q$46,"valid") -> 17 | O11: =IF(F11=0,"Research ","")&IF(J11=0,"Finance ","")&IF(K11=0,"IT/Systems","")
A12: exeter university | B12: University Of Exeter | C12: University | D12: =IFERROR(INDEX('UK Target Institutions'!$D$2:$D$727,MATCH($A12,'UK Target Institutions'!$A$2:$A$727,0)),"") -> Yes | E12: =COUNTIFS('Relevant - In CRM valid'!$T$2:$T$4699,$A12,'Relevant - In CRM valid'!$G$2:$G$4699,"UK")+COUNTIFS('Relevant - In CRM unknown'!$T$2:$T$253,$A12,'Relevant - In CRM unknown'!$G$2:$G$253,"UK")+COUNTIFS('Relevant - IN NOW CRM valid'!$T$2:$T$2328,$A12,'Relevant - IN NOW CRM valid'!$G$2:$G$2328,"UK")+COUNTIFS('Relevant - IN NOW CRM unknown'!$T$2:$T$1227,$A12,'Relevant - IN NOW CRM unknown'!$G$2:$G$1227,"UK")+COUNTIFS('Relevant - Not CRM not valid'!$T$2:$T$416,$A12,'Relevant - Not CRM not valid'!$G$2:$G$416,"UK")+COUNTIFS('Relevant - In CRM not valid'!$T$2:$T$46,$A12,'Relevant - In CRM not valid'!$G$2:$G$46,"UK") -> 95 | F12: =COUNTIFS('Relevant - In CRM valid'!$T$2:$T$4699,$A12,'Relevant - In CRM valid'!$G$2:$G$4699,"UK",'Relevant - In CRM valid'!$M$2:$M$4699,"Research")+COUNTIFS('Relevant - In CRM unknown'!$T$2:$T$253,$A12,'Relevant - In CRM unknown'!$G$2:$G$253,"UK",'Relevant - In CRM unknown'!$M$2:$M$253,"Research")+COUNTIFS('Relevant - IN NOW CRM valid'!$T$2:$T$2328,$A12,'Relevant - IN NOW CRM valid'!$G$2:$G$2328,"UK",'Relevant - IN NOW CRM valid'!$M$2:$M$2328,"Research")+COUNTIFS('Relevant - IN NOW CRM unknown'!$T$2:$T$1227,$A12,'Relevant - IN NOW CRM unknown'!$G$2:$G$1227,"UK",'Relevant - IN NOW CRM unknown'!$M$2:$M$1227,"Research")+COUNTIFS('Relevant - Not CRM not valid'!$T$2:$T$416,$A12,'Relevant - Not CRM not valid'!$G$2:$G$416,"UK",'Relevant - Not CRM not valid'!$M$2:$M$416,"Research")+COUNTIFS('Relevant - In CRM not valid'!$T$2:$T$46,$A12,'Relevant - In CRM not valid'!$G$2:$G$46,"UK",'Relevant - In CRM not valid'!$M$2:$M$46,"Research") -> 73 | G12: =COUNTIFS('Relevant - In CRM valid'!$T$2:$T$4699,$A12,'Relevant - In CRM valid'!$G$2:$G$4699,"UK",'Relevant - In CRM valid'!$M$2:$M$4699,"Research",'Relevant - In CRM valid'!$R$2:$R$4699,"Senior")+COUNTIFS('Relevant - In CRM unknown'!$T$2:$T$253,$A12,'Relevant - In CRM unknown'!$G$2:$G$253,"UK",'Relevant - In CRM unknown'!$M$2:$M$253,"Research",'Relevant - In CRM unknown'!$R$2:$R$253,"Senior")+COUNTIFS('Relevant - IN NOW CRM valid'!$T$2:$T$2328,$A12,'Relevant - IN NOW CRM valid'!$G$2:$G$2328,"UK",'Relevant - IN NOW CRM valid'!$M$2:$M$2328,"Research",'Relevant - IN NOW CRM valid'!$R$2:$R$2328,"Senior")+COUNTIFS('Relevant - IN NOW CRM unknown'!$T$2:$T$1227,$A12,'Relevant - IN NOW CRM unknown'!$G$2:$G$1227,"UK",'Relevant - IN NOW CRM unknown'!$M$2:$M$1227,"Research",'Relevant - IN NOW CRM unknown'!$R$2:$R$1227,"Senior")+COUNTIFS('Relevant - Not CRM not valid'!$T$2:$T$416,$A12,'Relevant - Not CRM not valid'!$G$2:$G$416,"UK",'Relevant - Not CRM not valid'!$M$2:$M$416,"Research",'Relevant - Not CRM not valid'!$R$2:$R$416,"Senior")+COUNTIFS('Relevant - In CRM not valid'!$T$2:$T$46,$A12,'Relevant - In CRM not valid'!$G$2:$G$46,"UK",'Relevant - In CRM not valid'!$M$2:$M$46,"Research",'Relevant - In CRM not valid'!$R$2:$R$46,"Senior") -> 25 | H12: =COUNTIFS('Relevant - In CRM valid'!$T$2:$T$4699,$A12,'Relevant - In CRM valid'!$G$2:$G$4699,"UK",'Relevant - In CRM valid'!$M$2:$M$4699,"Research",'Relevant - In CRM valid'!$R$2:$R$4699,"Operational")+COUNTIFS('Relevant - In CRM unknown'!$T$2:$T$253,$A12,'Relevant - In CRM unknown'!$G$2:$G$253,"UK",'Relevant - In CRM unknown'!$M$2:$M$253,"Research",'Relevant - In CRM unknown'!$R$2:$R$253,"Operational")+COUNTIFS('Relevant - IN NOW CRM valid'!$T$2:$T$2328,$A12,'Relevant - IN NOW CRM valid'!$G$2:$G$2328,"UK",'Relevant - IN NOW CRM valid'!$M$2:$M$2328,"Research",'Relevant - IN NOW CRM valid'!$R$2:$R$2328,"Operational")+COUNTIFS('Relevant - IN NOW CRM unknown'!$T$2:$T$1227,$A12,'Relevant - IN NOW CRM unknown'!$G$2:$G$1227,"UK",'Relevant - IN NOW CRM unknown'!$M$2:$M$1227,"Research",'Relevant - IN NOW CRM unknown'!$R$2:$R$1227,"Operational")+COUNTIFS('Relevant - Not CRM not valid'!$T$2:$T$416,$A12,'Relevant - Not CRM not valid'!$G$2:$G$416,"UK",'Relevant - Not CRM not valid'!$M$2:$M$416,"Research",'Relevant - Not CRM not valid'!$R$2:$R$416,"Operational")+COUNTIFS('Relevant - In CRM not valid'!$T$2:$T$46,$A12,'Relevant - In CRM not valid'!$G$2:$G$46,"UK",'Relevant - In CRM not valid'!$M$2:$M$46,"Research",'Relevant - In CRM not valid'!$R$2:$R$46,"Operational") -> 43 | I12: =COUNTIFS('Relevant - In CRM valid'!$T$2:$T$4699,$A12,'Relevant - In CRM valid'!$G$2:$G$4699,"UK",'Relevant - In CRM valid'!$M$2:$M$4699,"Research",'Relevant - In CRM valid'!$R$2:$R$4699,"Academic")+COUNTIFS('Relevant - In CRM unknown'!$T$2:$T$253,$A12,'Relevant - In CRM unknown'!$G$2:$G$253,"UK",'Relevant - In CRM unknown'!$M$2:$M$253,"Research",'Relevant - In CRM unknown'!$R$2:$R$253,"Academic")+COUNTIFS('Relevant - IN NOW CRM valid'!$T$2:$T$2328,$A12,'Relevant - IN NOW CRM valid'!$G$2:$G$2328,"UK",'Relevant - IN NOW CRM valid'!$M$2:$M$2328,"Research",'Relevant - IN NOW CRM valid'!$R$2:$R$2328,"Academic")+COUNTIFS('Relevant - IN NOW CRM unknown'!$T$2:$T$1227,$A12,'Relevant - IN NOW CRM unknown'!$G$2:$G$1227,"UK",'Relevant - IN NOW CRM unknown'!$M$2:$M$1227,"Research",'Relevant - IN NOW CRM unknown'!$R$2:$R$1227,"Academic")+COUNTIFS('Relevant - Not CRM not valid'!$T$2:$T$416,$A12,'Relevant - Not CRM not valid'!$G$2:$G$416,"UK",'Relevant - Not CRM not valid'!$M$2:$M$416,"Research",'Relevant - Not CRM not valid'!$R$2:$R$416,"Academic")+COUNTIFS('Relevant - In CRM not valid'!$T$2:$T$46,$A12,'Relevant - In CRM not valid'!$G$2:$G$46,"UK",'Relevant - In CRM not valid'!$M$2:$M$46,"Research",'Relevant - In CRM not valid'!$R$2:$R$46,"Academic") -> 5 | J12: =COUNTIFS('Relevant - In CRM valid'!$T$2:$T$4699,$A12,'Relevant - In CRM valid'!$G$2:$G$4699,"UK",'Relevant - In CRM valid'!$M$2:$M$4699,"Finance")+COUNTIFS('Relevant - In CRM unknown'!$T$2:$T$253,$A12,'Relevant - In CRM unknown'!$G$2:$G$253,"UK",'Relevant - In CRM unknown'!$M$2:$M$253,"Finance")+COUNTIFS('Relevant - IN NOW CRM valid'!$T$2:$T$2328,$A12,'Relevant - IN NOW CRM valid'!$G$2:$G$2328,"UK",'Relevant - IN NOW CRM valid'!$M$2:$M$2328,"Finance")+COUNTIFS('Relevant - IN NOW CRM unknown'!$T$2:$T$1227,$A12,'Relevant - IN NOW CRM unknown'!$G$2:$G$1227,"UK",'Relevant - IN NOW CRM unknown'!$M$2:$M$1227,"Finance")+COUNTIFS('Relevant - Not CRM not valid'!$T$2:$T$416,$A12,'Relevant - Not CRM not valid'!$G$2:$G$416,"UK",'Relevant - Not CRM not valid'!$M$2:$M$416,"Finance")+COUNTIFS('Relevant - In CRM not valid'!$T$2:$T$46,$A12,'Relevant - In CRM not valid'!$G$2:$G$46,"UK",'Relevant - In CRM not valid'!$M$2:$M$46,"Finance") -> 13 | K12: =COUNTIFS('Relevant - In CRM valid'!$T$2:$T$4699,$A12,'Relevant - In CRM valid'!$G$2:$G$4699,"UK",'Relevant - In CRM valid'!$M$2:$M$4699,"IT/Systems")+COUNTIFS('Relevant - In CRM unknown'!$T$2:$T$253,$A12,'Relevant - In CRM unknown'!$G$2:$G$253,"UK",'Relevant - In CRM unknown'!$M$2:$M$253,"IT/Systems")+COUNTIFS('Relevant - IN NOW CRM valid'!$T$2:$T$2328,$A12,'Relevant - IN NOW CRM valid'!$G$2:$G$2328,"UK",'Relevant - IN NOW CRM valid'!$M$2:$M$2328,"IT/Systems")+COUNTIFS('Relevant - IN NOW CRM unknown'!$T$2:$T$1227,$A12,'Relevant - IN NOW CRM unknown'!$G$2:$G$1227,"UK",'Relevant - IN NOW CRM unknown'!$M$2:$M$1227,"IT/Systems")+COUNTIFS('Relevant - Not CRM not valid'!$T$2:$T$416,$A12,'Relevant - Not CRM not valid'!$G$2:$G$416,"UK",'Relevant - Not CRM not valid'!$M$2:$M$416,"IT/Systems")+COUNTIFS('Relevant - In CRM not valid'!$T$2:$T$46,$A12,'Relevant - In CRM not valid'!$G$2:$G$46,"UK",'Relevant - In CRM not valid'!$M$2:$M$46,"IT/Systems") -> 9 | L12: =COUNTIFS('Relevant - In CRM valid'!$T$2:$T$4699,$A12,'Relevant - In CRM valid'!$G$2:$G$4699,"UK",'Relevant - In CRM valid'!$M$2:$M$4699,"")+COUNTIFS('Relevant - In CRM unknown'!$T$2:$T$253,$A12,'Relevant - In CRM unknown'!$G$2:$G$253,"UK",'Relevant - In CRM unknown'!$M$2:$M$253,"")+COUNTIFS('Relevant - IN NOW CRM valid'!$T$2:$T$2328,$A12,'Relevant - IN NOW CRM valid'!$G$2:$G$2328,"UK",'Relevant - IN NOW CRM valid'!$M$2:$M$2328,"")+COUNTIFS('Relevant - IN NOW CRM unknown'!$T$2:$T$1227,$A12,'Relevant - IN NOW CRM unknown'!$G$2:$G$1227,"UK",'Relevant - IN NOW CRM unknown'!$M$2:$M$1227,"")+COUNTIFS('Relevant - Not CRM not valid'!$T$2:$T$416,$A12,'Relevant - Not CRM not valid'!$G$2:$G$416,"UK",'Relevant - Not CRM not valid'!$M$2:$M$416,"")+COUNTIFS('Relevant - In CRM not valid'!$T$2:$T$46,$A12,'Relevant - In CRM not valid'!$G$2:$G$46,"UK",'Relevant - In CRM not valid'!$M$2:$M$46,"") -> 0 | M12: =(F12>0)+(J12>0)+(K12>0) -> 3 | N12: =COUNTIFS('Relevant - In CRM valid'!$T$2:$T$4699,$A12,'Relevant - In CRM valid'!$G$2:$G$4699,"UK",'Relevant - In CRM valid'!$Q$2:$Q$4699,"valid")+COUNTIFS('Relevant - In CRM unknown'!$T$2:$T$253,$A12,'Relevant - In CRM unknown'!$G$2:$G$253,"UK",'Relevant - In CRM unknown'!$Q$2:$Q$253,"valid")+COUNTIFS('Relevant - IN NOW CRM valid'!$T$2:$T$2328,$A12,'Relevant - IN NOW CRM valid'!$G$2:$G$2328,"UK",'Relevant - IN NOW CRM valid'!$Q$2:$Q$2328,"valid")+COUNTIFS('Relevant - IN NOW CRM unknown'!$T$2:$T$1227,$A12,'Relevant - IN NOW CRM unknown'!$G$2:$G$1227,"UK",'Relevant - IN NOW CRM unknown'!$Q$2:$Q$1227,"valid")+COUNTIFS('Relevant - Not CRM not valid'!$T$2:$T$416,$A12,'Relevant - Not CRM not valid'!$G$2:$G$416,"UK",'Relevant - Not CRM not valid'!$Q$2:$Q$416,"valid")+COUNTIFS('Relevant - In CRM not valid'!$T$2:$T$46,$A12,'Relevant - In CRM not valid'!$G$2:$G$46,"UK",'Relevant - In CRM not valid'!$Q$2:$Q$46,"valid") -> 49 | O12: =IF(F12=0,"Research ","")&IF(J12=0,"Finance ","")&IF(K12=0,"IT/Systems","")
A13: newcastle university | B13: Newcastle University | C13: University | D13: =IFERROR(INDEX('UK Target Institutions'!$D$2:$D$727,MATCH($A13,'UK Target Institutions'!$A$2:$A$727,0)),"") -> Yes | E13: =COUNTIFS('Relevant - In CRM valid'!$T$2:$T$4699,$A13,'Relevant - In CRM valid'!$G$2:$G$4699,"UK")+COUNTIFS('Relevant - In CRM unknown'!$T$2:$T$253,$A13,'Relevant - In CRM unknown'!$G$2:$G$253,"UK")+COUNTIFS('Relevant - IN NOW CRM valid'!$T$2:$T$2328,$A13,'Relevant - IN NOW CRM valid'!$G$2:$G$2328,"UK")+COUNTIFS('Relevant - IN NOW CRM unknown'!$T$2:$T$1227,$A13,'Relevant - IN NOW CRM unknown'!$G$2:$G$1227,"UK")+COUNTIFS('Relevant - Not CRM not valid'!$T$2:$T$416,$A13,'Relevant - Not CRM not valid'!$G$2:$G$416,"UK")+COUNTIFS('Relevant - In CRM not valid'!$T$2:$T$46,$A13,'Relevant - In CRM not valid'!$G$2:$G$46,"UK") -> 87 | F13: =COUNTIFS('Relevant - In CRM valid'!$T$2:$T$4699,$A13,'Relevant - In CRM valid'!$G$2:$G$4699,"UK",'Relevant - In CRM valid'!$M$2:$M$4699,"Research")+COUNTIFS('Relevant - In CRM unknown'!$T$2:$T$253,$A13,'Relevant - In CRM unknown'!$G$2:$G$253,"UK",'Relevant - In CRM unknown'!$M$2:$M$253,"Research")+COUNTIFS('Relevant - IN NOW CRM valid'!$T$2:$T$2328,$A13,'Relevant - IN NOW CRM valid'!$G$2:$G$2328,"UK",'Relevant - IN NOW CRM valid'!$M$2:$M$2328,"Research")+COUNTIFS('Relevant - IN NOW CRM unknown'!$T$2:$T$1227,$A13,'Relevant - IN NOW CRM unknown'!$G$2:$G$1227,"UK",'Relevant - IN NOW CRM unknown'!$M$2:$M$1227,"Research")+COUNTIFS('Relevant - Not CRM not valid'!$T$2:$T$416,$A13,'Relevant - Not CRM not valid'!$G$2:$G$416,"UK",'Relevant - Not CRM not valid'!$M$2:$M$416,"Research")+COUNTIFS('Relevant - In CRM not valid'!$T$2:$T$46,$A13,'Relevant - In CRM not valid'!$G$2:$G$46,"UK",'Relevant - In CRM not valid'!$M$2:$M$46,"Research") -> 86 | G13: =COUNTIFS('Relevant - In CRM valid'!$T$2:$T$4699,$A13,'Relevant - In CRM valid'!$G$2:$G$4699,"UK",'Relevant - In CRM valid'!$M$2:$M$4699,"Research",'Relevant - In CRM valid'!$R$2:$R$4699,"Senior")+COUNTIFS('Relevant - In CRM unknown'!$T$2:$T$253,$A13,'Relevant - In CRM unknown'!$G$2:$G$253,"UK",'Relevant - In CRM unknown'!$M$2:$M$253,"Research",'Relevant - In CRM unknown'!$R$2:$R$253,"Senior")+COUNTIFS('Relevant - IN NOW CRM valid'!$T$2:$T$2328,$A13,'Relevant - IN NOW CRM valid'!$G$2:$G$2328,"UK",'Relevant - IN NOW CRM valid'!$M$2:$M$2328,"Research",'Relevant - IN NOW CRM valid'!$R$2:$R$2328,"Senior")+COUNTIFS('Relevant - IN NOW CRM unknown'!$T$2:$T$1227,$A13,'Relevant - IN NOW CRM unknown'!$G$2:$G$1227,"UK",'Relevant - IN NOW CRM unknown'!$M$2:$M$1227,"Research",'Relevant - IN NOW CRM unknown'!$R$2:$R$1227,"Senior")+COUNTIFS('Relevant - Not CRM not valid'!$T$2:$T$416,$A13,'Relevant - Not CRM not valid'!$G$2:$G$416,"UK",'Relevant - Not CRM not valid'!$M$2:$M$416,"Research",'Relevant - Not CRM not valid'!$R$2:$R$416,"Senior")+COUNTIFS('Relevant - In CRM not valid'!$T$2:$T$46,$A13,'Relevant - In CRM not valid'!$G$2:$G$46,"UK",'Relevant - In CRM not valid'!$M$2:$M$46,"Research",'Relevant - In CRM not valid'!$R$2:$R$46,"Senior") -> 23 | H13: =COUNTIFS('Relevant - In CRM valid'!$T$2:$T$4699,$A13,'Relevant - In CRM valid'!$G$2:$G$4699,"UK",'Relevant - In CRM valid'!$M$2:$M$4699,"Research",'Relevant - In CRM valid'!$R$2:$R$4699,"Operational")+COUNTIFS('Relevant - In CRM unknown'!$T$2:$T$253,$A13,'Relevant - In CRM unknown'!$G$2:$G$253,"UK",'Relevant - In CRM unknown'!$M$2:$M$253,"Research",'Relevant - In CRM unknown'!$R$2:$R$253,"Operational")+COUNTIFS('Relevant - IN NOW CRM valid'!$T$2:$T$2328,$A13,'Relevant - IN NOW CRM valid'!$G$2:$G$2328,"UK",'Relevant - IN NOW CRM valid'!$M$2:$M$2328,"Research",'Relevant - IN NOW CRM valid'!$R$2:$R$2328,"Operational")+COUNTIFS('Relevant - IN NOW CRM unknown'!$T$2:$T$1227,$A13,'Relevant - IN NOW CRM unknown'!$G$2:$G$1227,"UK",'Relevant - IN NOW CRM unknown'!$M$2:$M$1227,"Research",'Relevant - IN NOW CRM unknown'!$R$2:$R$1227,"Operational")+COUNTIFS('Relevant - Not CRM not valid'!$T$2:$T$416,$A13,'Relevant - Not CRM not valid'!$G$2:$G$416,"UK",'Relevant - Not CRM not valid'!$M$2:$M$416,"Research",'Relevant - Not CRM not valid'!$R$2:$R$416,"Operational")+COUNTIFS('Relevant - In CRM not valid'!$T$2:$T$46,$A13,'Relevant - In CRM not valid'!$G$2:$G$46,"UK",'Relevant - In CRM not valid'!$M$2:$M$46,"Research",'Relevant - In CRM not valid'!$R$2:$R$46,"Operational") -> 62 | I13: =COUNTIFS('Relevant - In CRM valid'!$T$2:$T$4699,$A13,'Relevant - In CRM valid'!$G$2:$G$4699,"UK",'Relevant - In CRM valid'!$M$2:$M$4699,"Research",'Relevant - In CRM valid'!$R$2:$R$4699,"Academic")+COUNTIFS('Relevant - In CRM unknown'!$T$2:$T$253,$A13,'Relevant - In CRM unknown'!$G$2:$G$253,"UK",'Relevant - In CRM unknown'!$M$2:$M$253,"Research",'Relevant - In CRM unknown'!$R$2:$R$253,"Academic")+COUNTIFS('Relevant - IN NOW CRM valid'!$T$2:$T$2328,$A13,'Relevant - IN NOW CRM valid'!$G$2:$G$2328,"UK",'Relevant - IN NOW CRM valid'!$M$2:$M$2328,"Research",'Relevant - IN NOW CRM valid'!$R$2:$R$2328,"Academic")+COUNTIFS('Relevant - IN NOW CRM unknown'!$T$2:$T$1227,$A13,'Relevant - IN NOW CRM unknown'!$G$2:$G$1227,"UK",'Relevant - IN NOW CRM unknown'!$M$2:$M$1227,"Research",'Relevant - IN NOW CRM unknown'!$R$2:$R$1227,"Academic")+COUNTIFS('Relevant - Not CRM not valid'!$T$2:$T$416,$A13,'Relevant - Not CRM not valid'!$G$2:$G$416,"UK",'Relevant - Not CRM not valid'!$M$2:$M$416,"Research",'Relevant - Not CRM not valid'!$R$2:$R$416,"Academic")+COUNTIFS('Relevant - In CRM not valid'!$T$2:$T$46,$A13,'Relevant - In CRM not valid'!$G$2:$G$46,"UK",'Relevant - In CRM not valid'!$M$2:$M$46,"Research",'Relevant - In CRM not valid'!$R$2:$R$46,"Academic") -> 0 | J13: =COUNTIFS('Relevant - In CRM valid'!$T$2:$T$4699,$A13,'Relevant - In CRM valid'!$G$2:$G$4699,"UK",'Relevant - In CRM valid'!$M$2:$M$4699,"Finance")+COUNTIFS('Relevant - In CRM unknown'!$T$2:$T$253,$A13,'Relevant - In CRM unknown'!$G$2:$G$253,"UK",'Relevant - In CRM unknown'!$M$2:$M$253,"Finance")+COUNTIFS('Relevant - IN NOW CRM valid'!$T$2:$T$2328,$A13,'Relevant - IN NOW CRM valid'!$G$2:$G$2328,"UK",'Relevant - IN NOW CRM valid'!$M$2:$M$2328,"Finance")+COUNTIFS('Relevant - IN NOW CRM unknown'!$T$2:$T$1227,$A13,'Relevant - IN NOW CRM unknown'!$G$2:$G$1227,"UK",'Relevant - IN NOW CRM unknown'!$M$2:$M$1227,"Finance")+COUNTIFS('Relevant - Not CRM not valid'!$T$2:$T$416,$A13,'Relevant - Not CRM not valid'!$G$2:$G$416,"UK",'Relevant - Not CRM not valid'!$M$2:$M$416,"Finance")+COUNTIFS('Relevant - In CRM not valid'!$T$2:$T$46,$A13,'Relevant - In CRM not valid'!$G$2:$G$46,"UK",'Relevant - In CRM not valid'!$M$2:$M$46,"Finance") -> 0 | K13: =COUNTIFS('Relevant - In CRM valid'!$T$2:$T$4699,$A13,'Relevant - In CRM valid'!$G$2:$G$4699,"UK",'Relevant - In CRM valid'!$M$2:$M$4699,"IT/Systems")+COUNTIFS('Relevant - In CRM unknown'!$T$2:$T$253,$A13,'Relevant - In CRM unknown'!$G$2:$G$253,"UK",'Relevant - In CRM unknown'!$M$2:$M$253,"IT/Systems")+COUNTIFS('Relevant - IN NOW CRM valid'!$T$2:$T$2328,$A13,'Relevant - IN NOW CRM valid'!$G$2:$G$2328,"UK",'Relevant - IN NOW CRM valid'!$M$2:$M$2328,"IT/Systems")+COUNTIFS('Relevant - IN NOW CRM unknown'!$T$2:$T$1227,$A13,'Relevant - IN NOW CRM unknown'!$G$2:$G$1227,"UK",'Relevant - IN NOW CRM unknown'!$M$2:$M$1227,"IT/Systems")+COUNTIFS('Relevant - Not CRM not valid'!$T$2:$T$416,$A13,'Relevant - Not CRM not valid'!$G$2:$G$416,"UK",'Relevant - Not CRM not valid'!$M$2:$M$416,"IT/Systems")+COUNTIFS('Relevant - In CRM not valid'!$T$2:$T$46,$A13,'Relevant - In CRM not valid'!$G$2:$G$46,"UK",'Relevant - In CRM not valid'!$M$2:$M$46,"IT/Systems") -> 1 | L13: =COUNTIFS('Relevant - In CRM valid'!$T$2:$T$4699,$A13,'Relevant - In CRM valid'!$G$2:$G$4699,"UK",'Relevant - In CRM valid'!$M$2:$M$4699,"")+COUNTIFS('Relevant - In CRM unknown'!$T$2:$T$253,$A13,'Relevant - In CRM unknown'!$G$2:$G$253,"UK",'Relevant - In CRM unknown'!$M$2:$M$253,"")+COUNTIFS('Relevant - IN NOW CRM valid'!$T$2:$T$2328,$A13,'Relevant - IN NOW CRM valid'!$G$2:$G$2328,"UK",'Relevant - IN NOW CRM valid'!$M$2:$M$2328,"")+COUNTIFS('Relevant - IN NOW CRM unknown'!$T$2:$T$1227,$A13,'Relevant - IN NOW CRM unknown'!$G$2:$G$1227,"UK",'Relevant - IN NOW CRM unknown'!$M$2:$M$1227,"")+COUNTIFS('Relevant - Not CRM not valid'!$T$2:$T$416,$A13,'Relevant - Not CRM not valid'!$G$2:$G$416,"UK",'Relevant - Not CRM not valid'!$M$2:$M$416,"")+COUNTIFS('Relevant - In CRM not valid'!$T$2:$T$46,$A13,'Relevant - In CRM not valid'!$G$2:$G$46,"UK",'Relevant - In CRM not valid'!$M$2:$M$46,"") -> 0 | M13: =(F13>0)+(J13>0)+(K13>0) -> 2 | N13: =COUNTIFS('Relevant - In CRM valid'!$T$2:$T$4699,$A13,'Relevant - In CRM valid'!$G$2:$G$4699,"UK",'Relevant - In CRM valid'!$Q$2:$Q$4699,"valid")+COUNTIFS('Relevant - In CRM unknown'!$T$2:$T$253,$A13,'Relevant - In CRM unknown'!$G$2:$G$253,"UK",'Relevant - In CRM unknown'!$Q$2:$Q$253,"valid")+COUNTIFS('Relevant - IN NOW CRM valid'!$T$2:$T$2328,$A13,'Relevant - IN NOW CRM valid'!$G$2:$G$2328,"UK",'Relevant - IN NOW CRM valid'!$Q$2:$Q$2328,"valid")+COUNTIFS('Relevant - IN NOW CRM unknown'!$T$2:$T$1227,$A13,'Relevant - IN NOW CRM unknown'!$G$2:$G$1227,"UK",'Relevant - IN NOW CRM unknown'!$Q$2:$Q$1227,"valid")+COUNTIFS('Relevant - Not CRM not valid'!$T$2:$T$416,$A13,'Relevant - Not CRM not valid'!$G$2:$G$416,"UK",'Relevant - Not CRM not valid'!$Q$2:$Q$416,"valid")+COUNTIFS('Relevant - In CRM not valid'!$T$2:$T$46,$A13,'Relevant - In CRM not valid'!$G$2:$G$46,"UK",'Relevant - In CRM not valid'!$Q$2:$Q$46,"valid") -> 0 | O13: =IF(F13=0,"Research ","")&IF(J13=0,"Finance ","")&IF(K13=0,"IT/Systems","") -> Finance
... A727: yorkshire universities | B727: Yorkshire Universities | C727: University | D727: =IFERROR(INDEX('UK Target Institutions'!$D$2:$D$727,MATCH($A727,'UK Target Institutions'!$A$2:$A$727,0)),"") -> Yes | E727: =COUNTIFS('Relevant - In CRM valid'!$T$2:$T$4699,$A727,'Relevant - In CRM valid'!$G$2:$G$4699,"UK")+COUNTIFS('Relevant - In CRM unknown'!$T$2:$T$253,$A727,'Relevant - In CRM unknown'!$G$2:$G$253,"UK")+COUNTIFS('Relevant - IN NOW CRM valid'!$T$2:$T$2328,$A727,'Relevant - IN NOW CRM valid'!$G$2:$G$2328,"UK")+COUNTIFS('Relevant - IN NOW CRM unknown'!$T$2:$T$1227,$A727,'Relevant - IN NOW CRM unknown'!$G$2:$G$1227,"UK")+COUNTIFS('Relevant - Not CRM not valid'!$T$2:$T$416,$A727,'Relevant - Not CRM not valid'!$G$2:$G$416,"UK")+COUNTIFS('Relevant - In CRM not valid'!$T$2:$T$46,$A727,'Relevant - In CRM not valid'!$G$2:$G$46,"UK") -> 1 | F727: =COUNTIFS('Relevant - In CRM valid'!$T$2:$T$4699,$A727,'Relevant - In CRM valid'!$G$2:$G$4699,"UK",'Relevant - In CRM valid'!$M$2:$M$4699,"Research")+COUNTIFS('Relevant - In CRM unknown'!$T$2:$T$253,$A727,'Relevant - In CRM unknown'!$G$2:$G$253,"UK",'Relevant - In CRM unknown'!$M$2:$M$253,"Research")+COUNTIFS('Relevant - IN NOW CRM valid'!$T$2:$T$2328,$A727,'Relevant - IN NOW CRM valid'!$G$2:$G$2328,"UK",'Relevant - IN NOW CRM valid'!$M$2:$M$2328,"Research")+COUNTIFS('Relevant - IN NOW CRM unknown'!$T$2:$T$1227,$A727,'Relevant - IN NOW CRM unknown'!$G$2:$G$1227,"UK",'Relevant - IN NOW CRM unknown'!$M$2:$M$1227,"Research")+COUNTIFS('Relevant - Not CRM not valid'!$T$2:$T$416,$A727,'Relevant - Not CRM not valid'!$G$2:$G$416,"UK",'Relevant - Not CRM not valid'!$M$2:$M$416,"Research")+COUNTIFS('Relevant - In CRM not valid'!$T$2:$T$46,$A727,'Relevant - In CRM not valid'!$G$2:$G$46,"UK",'Relevant - In CRM not valid'!$M$2:$M$46,"Research") -> 0 | G727: =COUNTIFS('Relevant - In CRM valid'!$T$2:$T$4699,$A727,'Relevant - In CRM valid'!$G$2:$G$4699,"UK",'Relevant - In CRM valid'!$M$2:$M$4699,"Research",'Relevant - In CRM valid'!$R$2:$R$4699,"Senior")+COUNTIFS('Relevant - In CRM unknown'!$T$2:$T$253,$A727,'Relevant - In CRM unknown'!$G$2:$G$253,"UK",'Relevant - In CRM unknown'!$M$2:$M$253,"Research",'Relevant - In CRM unknown'!$R$2:$R$253,"Senior")+COUNTIFS('Relevant - IN NOW CRM valid'!$T$2:$T$2328,$A727,'Relevant - IN NOW CRM valid'!$G$2:$G$2328,"UK",'Relevant - IN NOW CRM valid'!$M$2:$M$2328,"Research",'Relevant - IN NOW CRM valid'!$R$2:$R$2328,"Senior")+COUNTIFS('Relevant - IN NOW CRM unknown'!$T$2:$T$1227,$A727,'Relevant - IN NOW CRM unknown'!$G$2:$G$1227,"UK",'Relevant - IN NOW CRM unknown'!$M$2:$M$1227,"Research",'Relevant - IN NOW CRM unknown'!$R$2:$R$1227,"Senior")+COUNTIFS('Relevant - Not CRM not valid'!$T$2:$T$416,$A727,'Relevant - Not CRM not valid'!$G$2:$G$416,"UK",'Relevant - Not CRM not valid'!$M$2:$M$416,"Research",'Relevant - Not CRM not valid'!$R$2:$R$416,"Senior")+COUNTIFS('Relevant - In CRM not valid'!$T$2:$T$46,$A727,'Relevant - In CRM not valid'!$G$2:$G$46,"UK",'Relevant - In CRM not valid'!$M$2:$M$46,"Research",'Relevant - In CRM not valid'!$R$2:$R$46,"Senior") -> 0 | H727: =COUNTIFS('Relevant - In CRM valid'!$T$2:$T$4699,$A727,'Relevant - In CRM valid'!$G$2:$G$4699,"UK",'Relevant - In CRM valid'!$M$2:$M$4699,"Research",'Relevant - In CRM valid'!$R$2:$R$4699,"Operational")+COUNTIFS('Relevant - In CRM unknown'!$T$2:$T$253,$A727,'Relevant - In CRM unknown'!$G$2:$G$253,"UK",'Relevant - In CRM unknown'!$M$2:$M$253,"Research",'Relevant - In CRM unknown'!$R$2:$R$253,"Operational")+COUNTIFS('Relevant - IN NOW CRM valid'!$T$2:$T$2328,$A727,'Relevant - IN NOW CRM valid'!$G$2:$G$2328,"UK",'Relevant - IN NOW CRM valid'!$M$2:$M$2328,"Research",'Relevant - IN NOW CRM valid'!$R$2:$R$2328,"Operational")+COUNTIFS('Relevant - IN NOW CRM unknown'!$T$2:$T$1227,$A727,'Relevant - IN NOW CRM unknown'!$G$2:$G$1227,"UK",'Relevant - IN NOW CRM unknown'!$M$2:$M$1227,"Research",'Relevant - IN NOW CRM unknown'!$R$2:$R$1227,"Operational")+COUNTIFS('Relevant - Not CRM not valid'!$T$2:$T$416,$A727,'Relevant - Not CRM not valid'!$G$2:$G$416,"UK",'Relevant - Not CRM not valid'!$M$2:$M$416,"Research",'Relevant - Not CRM not valid'!$R$2:$R$416,"Operational")+COUNTIFS('Relevant - In CRM not valid'!$T$2:$T$46,$A727,'Relevant - In CRM not valid'!$G$2:$G$46,"UK",'Relevant - In CRM not valid'!$M$2:$M$46,"Research",'Relevant - In CRM not valid'!$R$2:$R$46,"Operational") -> 0 | I727: =COUNTIFS('Relevant - In CRM valid'!$T$2:$T$4699,$A727,'Relevant - In CRM valid'!$G$2:$G$4699,"UK",'Relevant - In CRM valid'!$M$2:$M$4699,"Research",'Relevant - In CRM valid'!$R$2:$R$4699,"Academic")+COUNTIFS('Relevant - In CRM unknown'!$T$2:$T$253,$A727,'Relevant - In CRM unknown'!$G$2:$G$253,"UK",'Relevant - In CRM unknown'!$M$2:$M$253,"Research",'Relevant - In CRM unknown'!$R$2:$R$253,"Academic")+COUNTIFS('Relevant - IN NOW CRM valid'!$T$2:$T$2328,$A727,'Relevant - IN NOW CRM valid'!$G$2:$G$2328,"UK",'Relevant - IN NOW CRM valid'!$M$2:$M$2328,"Research",'Relevant - IN NOW CRM valid'!$R$2:$R$2328,"Academic")+COUNTIFS('Relevant - IN NOW CRM unknown'!$T$2:$T$1227,$A727,'Relevant - IN NOW CRM unknown'!$G$2:$G$1227,"UK",'Relevant - IN NOW CRM unknown'!$M$2:$M$1227,"Research",'Relevant - IN NOW CRM unknown'!$R$2:$R$1227,"Academic")+COUNTIFS('Relevant - Not CRM not valid'!$T$2:$T$416,$A727,'Relevant - Not CRM not valid'!$G$2:$G$416,"UK",'Relevant - Not CRM not valid'!$M$2:$M$416,"Research",'Relevant - Not CRM not valid'!$R$2:$R$416,"Academic")+COUNTIFS('Relevant - In CRM not valid'!$T$2:$T$46,$A727,'Relevant - In CRM not valid'!$G$2:$G$46,"UK",'Relevant - In CRM not valid'!$M$2:$M$46,"Research",'Relevant - In CRM not valid'!$R$2:$R$46,"Academic") -> 0 | J727: =COUNTIFS('Relevant - In CRM valid'!$T$2:$T$4699,$A727,'Relevant - In CRM valid'!$G$2:$G$4699,"UK",'Relevant - In CRM valid'!$M$2:$M$4699,"Finance")+COUNTIFS('Relevant - In CRM unknown'!$T$2:$T$253,$A727,'Relevant - In CRM unknown'!$G$2:$G$253,"UK",'Relevant - In CRM unknown'!$M$2:$M$253,"Finance")+COUNTIFS('Relevant - IN NOW CRM valid'!$T$2:$T$2328,$A727,'Relevant - IN NOW CRM valid'!$G$2:$G$2328,"UK",'Relevant - IN NOW CRM valid'!$M$2:$M$2328,"Finance")+COUNTIFS('Relevant - IN NOW CRM unknown'!$T$2:$T$1227,$A727,'Relevant - IN NOW CRM unknown'!$G$2:$G$1227,"UK",'Relevant - IN NOW CRM unknown'!$M$2:$M$1227,"Finance")+COUNTIFS('Relevant - Not CRM not valid'!$T$2:$T$416,$A727,'Relevant - Not CRM not valid'!$G$2:$G$416,"UK",'Relevant - Not CRM not valid'!$M$2:$M$416,"Finance")+COUNTIFS('Relevant - In CRM not valid'!$T$2:$T$46,$A727,'Relevant - In CRM not valid'!$G$2:$G$46,"UK",'Relevant - In CRM not valid'!$M$2:$M$46,"Finance") -> 0 | K727: =COUNTIFS('Relevant - In CRM valid'!$T$2:$T$4699,$A727,'Relevant - In CRM valid'!$G$2:$G$4699,"UK",'Relevant - In CRM valid'!$M$2:$M$4699,"IT/Systems")+COUNTIFS('Relevant - In CRM unknown'!$T$2:$T$253,$A727,'Relevant - In CRM unknown'!$G$2:$G$253,"UK",'Relevant - In CRM unknown'!$M$2:$M$253,"IT/Systems")+COUNTIFS('Relevant - IN NOW CRM valid'!$T$2:$T$2328,$A727,'Relevant - IN NOW CRM valid'!$G$2:$G$2328,"UK",'Relevant - IN NOW CRM valid'!$M$2:$M$2328,"IT/Systems")+COUNTIFS('Relevant - IN NOW CRM unknown'!$T$2:$T$1227,$A727,'Relevant - IN NOW CRM unknown'!$G$2:$G$1227,"UK",'Relevant - IN NOW CRM unknown'!$M$2:$M$1227,"IT/Systems")+COUNTIFS('Relevant - Not CRM not valid'!$T$2:$T$416,$A727,'Relevant - Not CRM not valid'!$G$2:$G$416,"UK",'Relevant - Not CRM not valid'!$M$2:$M$416,"IT/Systems")+COUNTIFS('Relevant - In CRM not valid'!$T$2:$T$46,$A727,'Relevant - In CRM not valid'!$G$2:$G$46,"UK",'Relevant - In CRM not valid'!$M$2:$M$46,"IT/Systems") -> 0 | L727: =COUNTIFS('Relevant - In CRM valid'!$T$2:$T$4699,$A727,'Relevant - In CRM valid'!$G$2:$G$4699,"UK",'Relevant - In CRM valid'!$M$2:$M$4699,"")+COUNTIFS('Relevant - In CRM unknown'!$T$2:$T$253,$A727,'Relevant - In CRM unknown'!$G$2:$G$253,"UK",'Relevant - In CRM unknown'!$M$2:$M$253,"")+COUNTIFS('Relevant - IN NOW CRM valid'!$T$2:$T$2328,$A727,'Relevant - IN NOW CRM valid'!$G$2:$G$2328,"UK",'Relevant - IN NOW CRM valid'!$M$2:$M$2328,"")+COUNTIFS('Relevant - IN NOW CRM unknown'!$T$2:$T$1227,$A727,'Relevant - IN NOW CRM unknown'!$G$2:$G$1227,"UK",'Relevant - IN NOW CRM unknown'!$M$2:$M$1227,"")+COUNTIFS('Relevant - Not CRM not valid'!$T$2:$T$416,$A727,'Relevant - Not CRM not valid'!$G$2:$G$416,"UK",'Relevant - Not CRM not valid'!$M$2:$M$416,"")+COUNTIFS('Relevant - In CRM not valid'!$T$2:$T$46,$A727,'Relevant - In CRM not valid'!$G$2:$G$46,"UK",'Relevant - In CRM not valid'!$M$2:$M$46,"") -> 1 | M727: =(F727>0)+(J727>0)+(K727>0) -> 0 | N727: =COUNTIFS('Relevant - In CRM valid'!$T$2:$T$4699,$A727,'Relevant - In CRM valid'!$G$2:$G$4699,"UK",'Relevant - In CRM valid'!$Q$2:$Q$4699,"valid")+COUNTIFS('Relevant - In CRM unknown'!$T$2:$T$253,$A727,'Relevant - In CRM unknown'!$G$2:$G$253,"UK",'Relevant - In CRM unknown'!$Q$2:$Q$253,"valid")+COUNTIFS('Relevant - IN NOW CRM valid'!$T$2:$T$2328,$A727,'Relevant - IN NOW CRM valid'!$G$2:$G$2328,"UK",'Relevant - IN NOW CRM valid'!$Q$2:$Q$2328,"valid")+COUNTIFS('Relevant - IN NOW CRM unknown'!$T$2:$T$1227,$A727,'Relevant - IN NOW CRM unknown'!$G$2:$G$1227,"UK",'Relevant - IN NOW CRM unknown'!$Q$2:$Q$1227,"valid")+COUNTIFS('Relevant - Not CRM not valid'!$T$2:$T$416,$A727,'Relevant - Not CRM not valid'!$G$2:$G$416,"UK",'Relevant - Not CRM not valid'!$Q$2:$Q$416,"valid")+COUNTIFS('Relevant - In CRM not valid'!$T$2:$T$46,$A727,'Relevant - In CRM not valid'!$G$2:$G$46,"UK",'Relevant - In CRM not valid'!$Q$2:$Q$46,"valid") -> 1 | O727: =IF(F727=0,"Research ","")&IF(J727=0,"Finance ","")&IF(K727=0,"IT/Systems","") -> Research Finance IT/Systems

Sheet Persona Gaps & Priorities
A1: Institution | B1: Contacts held | C1: Research | D1: Finance | E1: IT/Systems | F1: Personas held | G1: What is missing | H1: Priority | I1: Lookup key (canonical)
A2: {=_xlfn._xlws.FILTER('UK Target Institutions'!B2:B729,'UK Target Institutions'!D2:D729="Yes")} -> University of Manchester | B2: =IF($I2="","",IFERROR(INDEX('UK Institution Coverage'!$E$2:$E$727,MATCH($I2,'UK Institution Coverage'!$A$2:$A$727,0)),0)) -> 205 | C2: =IF($I2="","",IFERROR(INDEX('UK Institution Coverage'!$F$2:$F$727,MATCH($I2,'UK Institution Coverage'!$A$2:$A$727,0)),0)) -> 156 | D2: =IF($I2="","",IFERROR(INDEX('UK Institution Coverage'!$J$2:$J$727,MATCH($I2,'UK Institution Coverage'!$A$2:$A$727,0)),0)) -> 39 | E2: =IF($I2="","",IFERROR(INDEX('UK Institution Coverage'!$K$2:$K$727,MATCH($I2,'UK Institution Coverage'!$A$2:$A$727,0)),0)) -> 8 | F2: =IF($I2="","",IFERROR(INDEX('UK Institution Coverage'!$M$2:$M$727,MATCH($I2,'UK Institution Coverage'!$A$2:$A$727,0)),0)) -> 3 | G2: =IF($I2="","",IF($F2=3,"complete",IF($C2=0,"Research ","")&IF($D2=0,"Finance ","")&IF($E2=0,"IT/Systems",""))) -> complete | H2: =IF($I2="","",IF($F2=3,"-",IF($B2>=20,"1 - high",IF($B2>=5,"2 - medium","3 - low")))) -> - | I2: {=_xlfn._xlws.FILTER('UK Target Institutions'!A2:A729,'UK Target Institutions'!D2:D729="Yes")} -> manchester university
A3: King's College London | B3: =IF($I3="","",IFERROR(INDEX('UK Institution Coverage'!$E$2:$E$727,MATCH($I3,'UK Institution Coverage'!$A$2:$A$727,0)),0)) -> 177 | C3: =IF($I3="","",IFERROR(INDEX('UK Institution Coverage'!$F$2:$F$727,MATCH($I3,'UK Institution Coverage'!$A$2:$A$727,0)),0)) -> 173 | D3: =IF($I3="","",IFERROR(INDEX('UK Institution Coverage'!$J$2:$J$727,MATCH($I3,'UK Institution Coverage'!$A$2:$A$727,0)),0)) -> 2 | E3: =IF($I3="","",IFERROR(INDEX('UK Institution Coverage'!$K$2:$K$727,MATCH($I3,'UK Institution Coverage'!$A$2:$A$727,0)),0)) -> 1 | F3: =IF($I3="","",IFERROR(INDEX('UK Institution Coverage'!$M$2:$M$727,MATCH($I3,'UK Institution Coverage'!$A$2:$A$727,0)),0)) -> 3 | G3: =IF($I3="","",IF($F3=3,"complete",IF($C3=0,"Research ","")&IF($D3=0,"Finance ","")&IF($E3=0,"IT/Systems",""))) -> complete | H3: =IF($I3="","",IF($F3=3,"-",IF($B3>=20,"1 - high",IF($B3>=5,"2 - medium","3 - low")))) -> - | I3: king s college london
A4: Coventry University | B4: =IF($I4="","",IFERROR(INDEX('UK Institution Coverage'!$E$2:$E$727,MATCH($I4,'UK Institution Coverage'!$A$2:$A$727,0)),0)) -> 168 | C4: =IF($I4="","",IFERROR(INDEX('UK Institution Coverage'!$F$2:$F$727,MATCH($I4,'UK Institution Coverage'!$A$2:$A$727,0)),0)) -> 147 | D4: =IF($I4="","",IFERROR(INDEX('UK Institution Coverage'!$J$2:$J$727,MATCH($I4,'UK Institution Coverage'!$A$2:$A$727,0)),0)) -> 10 | E4: =IF($I4="","",IFERROR(INDEX('UK Institution Coverage'!$K$2:$K$727,MATCH($I4,'UK Institution Coverage'!$A$2:$A$727,0)),0)) -> 4 | F4: =IF($I4="","",IFERROR(INDEX('UK Institution Coverage'!$M$2:$M$727,MATCH($I4,'UK Institution Coverage'!$A$2:$A$727,0)),0)) -> 3 | G4: =IF($I4="","",IF($F4=3,"complete",IF($C4=0,"Research ","")&IF($D4=0,"Finance ","")&IF($E4=0,"IT/Systems",""))) -> complete | H4: =IF($I4="","",IF($F4=3,"-",IF($B4>=20,"1 - high",IF($B4>=5,"2 - medium","3 - low")))) -> - | I4: coventry university
A5: University of Sussex | B5: =IF($I5="","",IFERROR(INDEX('UK Institution Coverage'!$E$2:$E$727,MATCH($I5,'UK Institution Coverage'!$A$2:$A$727,0)),0)) -> 158 | C5: =IF($I5="","",IFERROR(INDEX('UK Institution Coverage'!$F$2:$F$727,MATCH($I5,'UK Institution Coverage'!$A$2:$A$727,0)),0)) -> 117 | D5: =IF($I5="","",IFERROR(INDEX('UK Institution Coverage'!$J$2:$J$727,MATCH($I5,'UK Institution Coverage'!$A$2:$A$727,0)),0)) -> 22 | E5: =IF($I5="","",IFERROR(INDEX('UK Institution Coverage'!$K$2:$K$727,MATCH($I5,'UK Institution Coverage'!$A$2:$A$727,0)),0)) -> 4 | F5: =IF($I5="","",IFERROR(INDEX('UK Institution Coverage'!$M$2:$M$727,MATCH($I5,'UK Institution Coverage'!$A$2:$A$727,0)),0)) -> 3 | G5: =IF($I5="","",IF($F5=3,"complete",IF($C5=0,"Research ","")&IF($D5=0,"Finance ","")&IF($E5=0,"IT/Systems",""))) -> complete | H5: =IF($I5="","",IF($F5=3,"-",IF($B5>=20,"1 - high",IF($B5>=5,"2 - medium","3 - low")))) -> - | I5: sussex university
A6: University of Edinburgh | B6: =IF($I6="","",IFERROR(INDEX('UK Institution Coverage'!$E$2:$E$727,MATCH($I6,'UK Institution Coverage'!$A$2:$A$727,0)),0)) -> 131 | C6: =IF($I6="","",IFERROR(INDEX('UK Institution Coverage'!$F$2:$F$727,MATCH($I6,'UK Institution Coverage'!$A$2:$A$727,0)),0)) -> 86 | D6: =IF($I6="","",IFERROR(INDEX('UK Institution Coverage'!$J$2:$J$727,MATCH($I6,'UK Institution Coverage'!$A$2:$A$727,0)),0)) -> 31 | E6: =IF($I6="","",IFERROR(INDEX('UK Institution Coverage'!$K$2:$K$727,MATCH($I6,'UK Institution Coverage'!$A$2:$A$727,0)),0)) -> 7 | F6: =IF($I6="","",IFERROR(INDEX('UK Institution Coverage'!$M$2:$M$727,MATCH($I6,'UK Institution Coverage'!$A$2:$A$727,0)),0)) -> 3 | G6: =IF($I6="","",IF($F6=3,"complete",IF($C6=0,"Research ","")&IF($D6=0,"Finance ","")&IF($E6=0,"IT/Systems",""))) -> complete | H6: =IF($I6="","",IF($F6=3,"-",IF($B6>=20,"1 - high",IF($B6>=5,"2 - medium","3 - low")))) -> - | I6: edinburgh university
A7: University of Liverpool | B7: =IF($I7="","",IFERROR(INDEX('UK Institution Coverage'!$E$2:$E$727,MATCH($I7,'UK Institution Coverage'!$A$2:$A$727,0)),0)) -> 124 | C7: =IF($I7="","",IFERROR(INDEX('UK Institution Coverage'!$F$2:$F$727,MATCH($I7,'UK Institution Coverage'!$A$2:$A$727,0)),0)) -> 108 | D7: =IF($I7="","",IFERROR(INDEX('UK Institution Coverage'!$J$2:$J$727,MATCH($I7,'UK Institution Coverage'!$A$2:$A$727,0)),0)) -> 12 | E7: =IF($I7="","",IFERROR(INDEX('UK Institution Coverage'!$K$2:$K$727,MATCH($I7,'UK Institution Coverage'!$A$2:$A$727,0)),0)) -> 2 | F7: =IF($I7="","",IFERROR(INDEX('UK Institution Coverage'!$M$2:$M$727,MATCH($I7,'UK Institution Coverage'!$A$2:$A$727,0)),0)) -> 3 | G7: =IF($I7="","",IF($F7=3,"complete",IF($C7=0,"Research ","")&IF($D7=0,"Finance ","")&IF($E7=0,"IT/Systems",""))) -> complete | H7: =IF($I7="","",IF($F7=3,"-",IF($B7>=20,"1 - high",IF($B7>=5,"2 - medium","3 - low")))) -> - | I7: liverpool university
A8: The University of Sheffield | B8: =IF($I8="","",IFERROR(INDEX('UK Institution Coverage'!$E$2:$E$727,MATCH($I8,'UK Institution Coverage'!$A$2:$A$727,0)),0)) -> 115 | C8: =IF($I8="","",IFERROR(INDEX('UK Institution Coverage'!$F$2:$F$727,MATCH($I8,'UK Institution Coverage'!$A$2:$A$727,0)),0)) -> 95 | D8: =IF($I8="","",IFERROR(INDEX('UK Institution Coverage'!$J$2:$J$727,MATCH($I8,'UK Institution Coverage'!$A$2:$A$727,0)),0)) -> 14 | E8: =IF($I8="","",IFERROR(INDEX('UK Institution Coverage'!$K$2:$K$727,MATCH($I8,'UK Institution Coverage'!$A$2:$A$727,0)),0)) -> 3 | F8: =IF($I8="","",IFERROR(INDEX('UK Institution Coverage'!$M$2:$M$727,MATCH($I8,'UK Institution Coverage'!$A$2:$A$727,0)),0)) -> 3 | G8: =IF($I8="","",IF($F8=3,"complete",IF($C8=0,"Research ","")&IF($D8=0,"Finance ","")&IF($E8=0,"IT/Systems",""))) -> complete | H8: =IF($I8="","",IF($F8=3,"-",IF($B8>=20,"1 - high",IF($B8>=5,"2 - medium","3 - low")))) -> - | I8: sheffield university
A9: The Manchester Metropolitan University | B9: =IF($I9="","",IFERROR(INDEX('UK Institution Coverage'!$E$2:$E$727,MATCH($I9,'UK Institution Coverage'!$A$2:$A$727,0)),0)) -> 109 | C9: =IF($I9="","",IFERROR(INDEX('UK Institution Coverage'!$F$2:$F$727,MATCH($I9,'UK Institution Coverage'!$A$2:$A$727,0)),0)) -> 76 | D9: =IF($I9="","",IFERROR(INDEX('UK Institution Coverage'!$J$2:$J$727,MATCH($I9,'UK Institution Coverage'!$A$2:$A$727,0)),0)) -> 17 | E9: =IF($I9="","",IFERROR(INDEX('UK Institution Coverage'!$K$2:$K$727,MATCH($I9,'UK Institution Coverage'!$A$2:$A$727,0)),0)) -> 14 | F9: =IF($I9="","",IFERROR(INDEX('UK Institution Coverage'!$M$2:$M$727,MATCH($I9,'UK Institution Coverage'!$A$2:$A$727,0)),0)) -> 3 | G9: =IF($I9="","",IF($F9=3,"complete",IF($C9=0,"Research ","")&IF($D9=0,"Finance ","")&IF($E9=0,"IT/Systems",""))) -> complete | H9: =IF($I9="","",IF($F9=3,"-",IF($B9>=20,"1 - high",IF($B9>=5,"2 - medium","3 - low")))) -> - | I9: manchester metropolitan university
A10: University of York | B10: =IF($I10="","",IFERROR(INDEX('UK Institution Coverage'!$E$2:$E$727,MATCH($I10,'UK Institution Coverage'!$A$2:$A$727,0)),0)) -> 92 | C10: =IF($I10="","",IFERROR(INDEX('UK Institution Coverage'!$F$2:$F$727,MATCH($I10,'UK Institution Coverage'!$A$2:$A$727,0)),0)) -> 77 | D10: =IF($I10="","",IFERROR(INDEX('UK Institution Coverage'!$J$2:$J$727,MATCH($I10,'UK Institution Coverage'!$A$2:$A$727,0)),0)) -> 10 | E10: =IF($I10="","",IFERROR(INDEX('UK Institution Coverage'!$K$2:$K$727,MATCH($I10,'UK Institution Coverage'!$A$2:$A$727,0)),0)) -> 3 | F10: =IF($I10="","",IFERROR(INDEX('UK Institution Coverage'!$M$2:$M$727,MATCH($I10,'UK Institution Coverage'!$A$2:$A$727,0)),0)) -> 3 | G10: =IF($I10="","",IF($F10=3,"complete",IF($C10=0,"Research ","")&IF($D10=0,"Finance ","")&IF($E10=0,"IT/Systems",""))) -> complete | H10: =IF($I10="","",IF($F10=3,"-",IF($B10>=20,"1 - high",IF($B10>=5,"2 - medium","3 - low")))) -> - | I10: york university
A11: Cardiff University | B11: =IF($I11="","",IFERROR(INDEX('UK Institution Coverage'!$E$2:$E$727,MATCH($I11,'UK Institution Coverage'!$A$2:$A$727,0)),0)) -> 86 | C11: =IF($I11="","",IFERROR(INDEX('UK Institution Coverage'!$F$2:$F$727,MATCH($I11,'UK Institution Coverage'!$A$2:$A$727,0)),0)) -> 52 | D11: =IF($I11="","",IFERROR(INDEX('UK Institution Coverage'!$J$2:$J$727,MATCH($I11,'UK Institution Coverage'!$A$2:$A$727,0)),0)) -> 19 | E11: =IF($I11="","",IFERROR(INDEX('UK Institution Coverage'!$K$2:$K$727,MATCH($I11,'UK Institution Coverage'!$A$2:$A$727,0)),0)) -> 7 | F11: =IF($I11="","",IFERROR(INDEX('UK Institution Coverage'!$M$2:$M$727,MATCH($I11,'UK Institution Coverage'!$A$2:$A$727,0)),0)) -> 3 | G11: =IF($I11="","",IF($F11=3,"complete",IF($C11=0,"Research ","")&IF($D11=0,"Finance ","")&IF($E11=0,"IT/Systems",""))) -> complete | H11: =IF($I11="","",IF($F11=3,"-",IF($B11>=20,"1 - high",IF($B11>=5,"2 - medium","3 - low")))) -> - | I11: cardiff university
A12: University Of Exeter | B12: =IF($I12="","",IFERROR(INDEX('UK Institution Coverage'!$E$2:$E$727,MATCH($I12,'UK Institution Coverage'!$A$2:$A$727,0)),0)) -> 95 | C12: =IF($I12="","",IFERROR(INDEX('UK Institution Coverage'!$F$2:$F$727,MATCH($I12,'UK Institution Coverage'!$A$2:$A$727,0)),0)) -> 73 | D12: =IF($I12="","",IFERROR(INDEX('UK Institution Coverage'!$J$2:$J$727,MATCH($I12,'UK Institution Coverage'!$A$2:$A$727,0)),0)) -> 13 | E12: =IF($I12="","",IFERROR(INDEX('UK Institution Coverage'!$K$2:$K$727,MATCH($I12,'UK Institution Coverage'!$A$2:$A$727,0)),0)) -> 9 | F12: =IF($I12="","",IFERROR(INDEX('UK Institution Coverage'!$M$2:$M$727,MATCH($I12,'UK Institution Coverage'!$A$2:$A$727,0)),0)) -> 3 | G12: =IF($I12="","",IF($F12=3,"complete",IF($C12=0,"Research ","")&IF($D12=0,"Finance ","")&IF($E12=0,"IT/Systems",""))) -> complete | H12: =IF($I12="","",IF($F12=3,"-",IF($B12>=20,"1 - high",IF($B12>=5,"2 - medium","3 - low")))) -> - | I12: exeter university
A13: Newcastle University | B13: =IF($I13="","",IFERROR(INDEX('UK Institution Coverage'!$E$2:$E$727,MATCH($I13,'UK Institution Coverage'!$A$2:$A$727,0)),0)) -> 87 | C13: =IF($I13="","",IFERROR(INDEX('UK Institution Coverage'!$F$2:$F$727,MATCH($I13,'UK Institution Coverage'!$A$2:$A$727,0)),0)) -> 86 | D13: =IF($I13="","",IFERROR(INDEX('UK Institution Coverage'!$J$2:$J$727,MATCH($I13,'UK Institution Coverage'!$A$2:$A$727,0)),0)) -> 0 | E13: =IF($I13="","",IFERROR(INDEX('UK Institution Coverage'!$K$2:$K$727,MATCH($I13,'UK Institution Coverage'!$A$2:$A$727,0)),0)) -> 1 | F13: =IF($I13="","",IFERROR(INDEX('UK Institution Coverage'!$M$2:$M$727,MATCH($I13,'UK Institution Coverage'!$A$2:$A$727,0)),0)) -> 2 | G13: =IF($I13="","",IF($F13=3,"complete",IF($C13=0,"Research ","")&IF($D13=0,"Finance ","")&IF($E13=0,"IT/Systems",""))) -> Finance | H13: =IF($I13="","",IF($F13=3,"-",IF($B13>=20,"1 - high",IF($B13>=5,"2 - medium","3 - low")))) -> 1 - high | I13: newcastle university
A14: The Open University | B14: =IF($I14="","",IFERROR(INDEX('UK Institution Coverage'!$E$2:$E$727,MATCH($I14,'UK Institution Coverage'!$A$2:$A$727,0)),0)) -> 90 | C14: =IF($I14="","",IFERROR(INDEX('UK Institution Coverage'!$F$2:$F$727,MATCH($I14,'UK Institution Coverage'!$A$2:$A$727,0)),0)) -> 70 | D14: =IF($I14="","",IFERROR(INDEX('UK Institution Coverage'!$J$2:$J$727,MATCH($I14,'UK Institution Coverage'!$A$2:$A$727,0)),0)) -> 12 | E14: =IF($I14="","",IFERROR(INDEX('UK Institution Coverage'!$K$2:$K$727,MATCH($I14,'UK Institution Coverage'!$A$2:$A$727,0)),0)) -> 5 | F14: =IF($I14="","",IFERROR(INDEX('UK Institution Coverage'!$M$2:$M$727,MATCH($I14,'UK Institution Coverage'!$A$2:$A$727,0)),0)) -> 3 | G14: =IF($I14="","",IF($F14=3,"complete",IF($C14=0,"Research ","")&IF($D14=0,"Finance ","")&IF($E14=0,"IT/Systems",""))) -> complete | H14: =IF($I14="","",IF($F14=3,"-",IF($B14>=20,"1 - high",IF($B14>=5,"2 - medium","3 - low")))) -> - | I14: open university
... A309: Yorkshire Universities | B309: =IF($I309="","",IFERROR(INDEX('UK Institution Coverage'!$E$2:$E$727,MATCH($I309,'UK Institution Coverage'!$A$2:$A$727,0)),0)) -> 1 | C309: =IF($I309="","",IFERROR(INDEX('UK Institution Coverage'!$F$2:$F$727,MATCH($I309,'UK Institution Coverage'!$A$2:$A$727,0)),0)) -> 0 | D309: =IF($I309="","",IFERROR(INDEX('UK Institution Coverage'!$J$2:$J$727,MATCH($I309,'UK Institution Coverage'!$A$2:$A$727,0)),0)) -> 0 | E309: =IF($I309="","",IFERROR(INDEX('UK Institution Coverage'!$K$2:$K$727,MATCH($I309,'UK Institution Coverage'!$A$2:$A$727,0)),0)) -> 0 | F309: =IF($I309="","",IFERROR(INDEX('UK Institution Coverage'!$M$2:$M$727,MATCH($I309,'UK Institution Coverage'!$A$2:$A$727,0)),0)) -> 0 | G309: =IF($I309="","",IF($F309=3,"complete",IF($C309=0,"Research ","")&IF($D309=0,"Finance ","")&IF($E309=0,"IT/Systems",""))) -> Research Finance IT/Systems | H309: =IF($I309="","",IF($F309=3,"-",IF($B309>=20,"1 - high",IF($B309>=5,"2 - medium","3 - low")))) -> 3 - low | I309: yorkshire universities
B310: =IF($I310="","",IFERROR(INDEX('UK Institution Coverage'!$E$2:$E$727,MATCH($I310,'UK Institution Coverage'!$A$2:$A$727,0)),0)) | C310: =IF($I310="","",IFERROR(INDEX('UK Institution Coverage'!$F$2:$F$727,MATCH($I310,'UK Institution Coverage'!$A$2:$A$727,0)),0)) | D310: =IF($I310="","",IFERROR(INDEX('UK Institution Coverage'!$J$2:$J$727,MATCH($I310,'UK Institution Coverage'!$A$2:$A$727,0)),0)) | E310: =IF($I310="","",IFERROR(INDEX('UK Institution Coverage'!$K$2:$K$727,MATCH($I310,'UK Institution Coverage'!$A$2:$A$727,0)),0)) | F310: =IF($I310="","",IFERROR(INDEX('UK Institution Coverage'!$M$2:$M$727,MATCH($I310,'UK Institution Coverage'!$A$2:$A$727,0)),0)) | G310: =IF($I310="","",IF($F310=3,"complete",IF($C310=0,"Research ","")&IF($D310=0,"Finance ","")&IF($E310=0,"IT/Systems",""))) | H310: =IF($I310="","",IF($F310=3,"-",IF($B310>=20,"1 - high",IF($B310>=5,"2 - medium","3 - low"))))
B311: =IF($I311="","",IFERROR(INDEX('UK Institution Coverage'!$E$2:$E$727,MATCH($I311,'UK Institution Coverage'!$A$2:$A$727,0)),0)) | C311: =IF($I311="","",IFERROR(INDEX('UK Institution Coverage'!$F$2:$F$727,MATCH($I311,'UK Institution Coverage'!$A$2:$A$727,0)),0)) | D311: =IF($I311="","",IFERROR(INDEX('UK Institution Coverage'!$J$2:$J$727,MATCH($I311,'UK Institution Coverage'!$A$2:$A$727,0)),0)) | E311: =IF($I311="","",IFERROR(INDEX('UK Institution Coverage'!$K$2:$K$727,MATCH($I311,'UK Institution Coverage'!$A$2:$A$727,0)),0)) | F311: =IF($I311="","",IFERROR(INDEX('UK Institution Coverage'!$M$2:$M$727,MATCH($I311,'UK Institution Coverage'!$A$2:$A$727,0)),0)) | G311: =IF($I311="","",IF($F311=3,"complete",IF($C311=0,"Research ","")&IF($D311=0,"Finance ","")&IF($E311=0,"IT/Systems",""))) | H311: =IF($I311="","",IF($F311=3,"-",IF($B311>=20,"1 - high",IF($B311>=5,"2 - medium","3 - low"))))
B312: =IF($I312="","",IFERROR(INDEX('UK Institution Coverage'!$E$2:$E$727,MATCH($I312,'UK Institution Coverage'!$A$2:$A$727,0)),0)) | C312: =IF($I312="","",IFERROR(INDEX('UK Institution Coverage'!$F$2:$F$727,MATCH($I312,'UK Institution Coverage'!$A$2:$A$727,0)),0)) | D312: =IF($I312="","",IFERROR(INDEX('UK Institution Coverage'!$J$2:$J$727,MATCH($I312,'UK Institution Coverage'!$A$2:$A$727,0)),0)) | E312: =IF($I312="","",IFERROR(INDEX('UK Institution Coverage'!$K$2:$K$727,MATCH($I312,'UK Institution Coverage'!$A$2:$A$727,0)),0)) | F312: =IF($I312="","",IFERROR(INDEX('UK Institution Coverage'!$M$2:$M$727,MATCH($I312,'UK Institution Coverage'!$A$2:$A$727,0)),0)) | G312: =IF($I312="","",IF($F312=3,"complete",IF($C312=0,"Research ","")&IF($D312=0,"Finance ","")&IF($E312=0,"IT/Systems",""))) | H312: =IF($I312="","",IF($F312=3,"-",IF($B312>=20,"1 - high",IF($B312>=5,"2 - medium","3 - low"))))
B313: =IF($I313="","",IFERROR(INDEX('UK Institution Coverage'!$E$2:$E$727,MATCH($I313,'UK Institution Coverage'!$A$2:$A$727,0)),0)) | C313: =IF($I313="","",IFERROR(INDEX('UK Institution Coverage'!$F$2:$F$727,MATCH($I313,'UK Institution Coverage'!$A$2:$A$727,0)),0)) | D313: =IF($I313="","",IFERROR(INDEX('UK Institution Coverage'!$J$2:$J$727,MATCH($I313,'UK Institution Coverage'!$A$2:$A$727,0)),0)) | E313: =IF($I313="","",IFERROR(INDEX('UK Institution Coverage'!$K$2:$K$727,MATCH($I313,'UK Institution Coverage'!$A$2:$A$727,0)),0)) | F313: =IF($I313="","",IFERROR(INDEX('UK Institution Coverage'!$M$2:$M$727,MATCH($I313,'UK Institution Coverage'!$A$2:$A$727,0)),0)) | G313: =IF($I313="","",IF($F313=3,"complete",IF($C313=0,"Research ","")&IF($D313=0,"Finance ","")&IF($E313=0,"IT/Systems",""))) | H313: =IF($I313="","",IF($F313=3,"-",IF($B313>=20,"1 - high",IF($B313>=5,"2 - medium","3 - low"))))
B314: =IF($I314="","",IFERROR(INDEX('UK Institution Coverage'!$E$2:$E$727,MATCH($I314,'UK Institution Coverage'!$A$2:$A$727,0)),0)) | C314: =IF($I314="","",IFERROR(INDEX('UK Institution Coverage'!$F$2:$F$727,MATCH($I314,'UK Institution Coverage'!$A$2:$A$727,0)),0)) | D314: =IF($I314="","",IFERROR(INDEX('UK Institution Coverage'!$J$2:$J$727,MATCH($I314,'UK Institution Coverage'!$A$2:$A$727,0)),0)) | E314: =IF($I314="","",IFERROR(INDEX('UK Institution Coverage'!$K$2:$K$727,MATCH($I314,'UK Institution Coverage'!$A$2:$A$727,0)),0)) | F314: =IF($I314="","",IFERROR(INDEX('UK Institution Coverage'!$M$2:$M$727,MATCH($I314,'UK Institution Coverage'!$A$2:$A$727,0)),0)) | G314: =IF($I314="","",IF($F314=3,"complete",IF($C314=0,"Research ","")&IF($D314=0,"Finance ","")&IF($E314=0,"IT/Systems",""))) | H314: =IF($I314="","",IF($F314=3,"-",IF($B314>=20,"1 - high",IF($B314>=5,"2 - medium","3 - low"))))
B315: =IF($I315="","",IFERROR(INDEX('UK Institution Coverage'!$E$2:$E$727,MATCH($I315,'UK Institution Coverage'!$A$2:$A$727,0)),0)) | C315: =IF($I315="","",IFERROR(INDEX('UK Institution Coverage'!$F$2:$F$727,MATCH($I315,'UK Institution Coverage'!$A$2:$A$727,0)),0)) | D315: =IF($I315="","",IFERROR(INDEX('UK Institution Coverage'!$J$2:$J$727,MATCH($I315,'UK Institution Coverage'!$A$2:$A$727,0)),0)) | E315: =IF($I315="","",IFERROR(INDEX('UK Institution Coverage'!$K$2:$K$727,MATCH($I315,'UK Institution Coverage'!$A$2:$A$727,0)),0)) | F315: =IF($I315="","",IFERROR(INDEX('UK Institution Coverage'!$M$2:$M$727,MATCH($I315,'UK Institution Coverage'!$A$2:$A$727,0)),0)) | G315: =IF($I315="","",IF($F315=3,"complete",IF($C315=0,"Research ","")&IF($D315=0,"Finance ","")&IF($E315=0,"IT/Systems",""))) | H315: =IF($I315="","",IF($F315=3,"-",IF($B315>=20,"1 - high",IF($B315>=5,"2 - medium","3 - low"))))
B316: =IF($I316="","",IFERROR(INDEX('UK Institution Coverage'!$E$2:$E$727,MATCH($I316,'UK Institution Coverage'!$A$2:$A$727,0)),0)) | C316: =IF($I316="","",IFERROR(INDEX('UK Institution Coverage'!$F$2:$F$727,MATCH($I316,'UK Institution Coverage'!$A$2:$A$727,0)),0)) | D316: =IF($I316="","",IFERROR(INDEX('UK Institution Coverage'!$J$2:$J$727,MATCH($I316,'UK Institution Coverage'!$A$2:$A$727,0)),0)) | E316: =IF($I316="","",IFERROR(INDEX('UK Institution Coverage'!$K$2:$K$727,MATCH($I316,'UK Institution Coverage'!$A$2:$A$727,0)),0)) | F316: =IF($I316="","",IFERROR(INDEX('UK Institution Coverage'!$M$2:$M$727,MATCH($I316,'UK Institution Coverage'!$A$2:$A$727,0)),0)) | G316: =IF($I316="","",IF($F316=3,"complete",IF($C316=0,"Research ","")&IF($D316=0,"Finance ","")&IF($E316=0,"IT/Systems",""))) | H316: =IF($I316="","",IF($F316=3,"-",IF($B316>=20,"1 - high",IF($B316>=5,"2 - medium","3 - low"))))
B317: =IF($I317="","",IFERROR(INDEX('UK Institution Coverage'!$E$2:$E$727,MATCH($I317,'UK Institution Coverage'!$A$2:$A$727,0)),0)) | C317: =IF($I317="","",IFERROR(INDEX('UK Institution Coverage'!$F$2:$F$727,MATCH($I317,'UK Institution Coverage'!$A$2:$A$727,0)),0)) | D317: =IF($I317="","",IFERROR(INDEX('UK Institution Coverage'!$J$2:$J$727,MATCH($I317,'UK Institution Coverage'!$A$2:$A$727,0)),0)) | E317: =IF($I317="","",IFERROR(INDEX('UK Institution Coverage'!$K$2:$K$727,MATCH($I317,'UK Institution Coverage'!$A$2:$A$727,0)),0)) | F317: =IF($I317="","",IFERROR(INDEX('UK Institution Coverage'!$M$2:$M$727,MATCH($I317,'UK Institution Coverage'!$A$2:$A$727,0)),0)) | G317: =IF($I317="","",IF($F317=3,"complete",IF($C317=0,"Research ","")&IF($D317=0,"Finance ","")&IF($E317=0,"IT/Systems",""))) | H317: =IF($I317="","",IF($F317=3,"-",IF($B317>=20,"1 - high",IF($B317>=5,"2 - medium","3 - low"))))
B318: =IF($I318="","",IFERROR(INDEX('UK Institution Coverage'!$E$2:$E$727,MATCH($I318,'UK Institution Coverage'!$A$2:$A$727,0)),0)) | C318: =IF($I318="","",IFERROR(INDEX('UK Institution Coverage'!$F$2:$F$727,MATCH($I318,'UK Institution Coverage'!$A$2:$A$727,0)),0)) | D318: =IF($I318="","",IFERROR(INDEX('UK Institution Coverage'!$J$2:$J$727,MATCH($I318,'UK Institution Coverage'!$A$2:$A$727,0)),0)) | E318: =IF($I318="","",IFERROR(INDEX('UK Institution Coverage'!$K$2:$K$727,MATCH($I318,'UK Institution Coverage'!$A$2:$A$727,0)),0)) | F318: =IF($I318="","",IFERROR(INDEX('UK Institution Coverage'!$M$2:$M$727,MATCH($I318,'UK Institution Coverage'!$A$2:$A$727,0)),0)) | G318: =IF($I318="","",IF($F318=3,"complete",IF($C318=0,"Research ","")&IF($D318=0,"Finance ","")&IF($E318=0,"IT/Systems",""))) | H318: =IF($I318="","",IF($F318=3,"-",IF($B318>=20,"1 - high",IF($B318>=5,"2 - medium","3 - low"))))
B319: =IF($I319="","",IFERROR(INDEX('UK Institution Coverage'!$E$2:$E$727,MATCH($I319,'UK Institution Coverage'!$A$2:$A$727,0)),0)) | C319: =IF($I319="","",IFERROR(INDEX('UK Institution Coverage'!$F$2:$F$727,MATCH($I319,'UK Institution Coverage'!$A$2:$A$727,0)),0)) | D319: =IF($I319="","",IFERROR(INDEX('UK Institution Coverage'!$J$2:$J$727,MATCH($I319,'UK Institution Coverage'!$A$2:$A$727,0)),0)) | E319: =IF($I319="","",IFERROR(INDEX('UK Institution Coverage'!$K$2:$K$727,MATCH($I319,'UK Institution Coverage'!$A$2:$A$727,0)),0)) | F319: =IF($I319="","",IFERROR(INDEX('UK Institution Coverage'!$M$2:$M$727,MATCH($I319,'UK Institution Coverage'!$A$2:$A$727,0)),0)) | G319: =IF($I319="","",IF($F319=3,"complete",IF($C319=0,"Research ","")&IF($D319=0,"Finance ","")&IF($E319=0,"IT/Systems",""))) | H319: =IF($I319="","",IF($F319=3,"-",IF($B319>=20,"1 - high",IF($B319>=5,"2 - medium","3 - low"))))
B320: =IF($I320="","",IFERROR(INDEX('UK Institution Coverage'!$E$2:$E$727,MATCH($I320,'UK Institution Coverage'!$A$2:$A$727,0)),0)) | C320: =IF($I320="","",IFERROR(INDEX('UK Institution Coverage'!$F$2:$F$727,MATCH($I320,'UK Institution Coverage'!$A$2:$A$727,0)),0)) | D320: =IF($I320="","",IFERROR(INDEX('UK Institution Coverage'!$J$2:$J$727,MATCH($I320,'UK Institution Coverage'!$A$2:$A$727,0)),0)) | E320: =IF($I320="","",IFERROR(INDEX('UK Institution Coverage'!$K$2:$K$727,MATCH($I320,'UK Institution Coverage'!$A$2:$A$727,0)),0)) | F320: =IF($I320="","",IFERROR(INDEX('UK Institution Coverage'!$M$2:$M$727,MATCH($I320,'UK Institution Coverage'!$A$2:$A$727,0)),0)) | G320: =IF($I320="","",IF($F320=3,"complete",IF($C320=0,"Research ","")&IF($D320=0,"Finance ","")&IF($E320=0,"IT/Systems",""))) | H320: =IF($I320="","",IF($F320=3,"-",IF($B320>=20,"1 - high",IF($B320>=5,"2 - medium","3 - low"))))
B321: =IF($I321="","",IFERROR(INDEX('UK Institution Coverage'!$E$2:$E$727,MATCH($I321,'UK Institution Coverage'!$A$2:$A$727,0)),0)) | C321: =IF($I321="","",IFERROR(INDEX('UK Institution Coverage'!$F$2:$F$727,MATCH($I321,'UK Institution Coverage'!$A$2:$A$727,0)),0)) | D321: =IF($I321="","",IFERROR(INDEX('UK Institution Coverage'!$J$2:$J$727,MATCH($I321,'UK Institution Coverage'!$A$2:$A$727,0)),0)) | E321: =IF($I321="","",IFERROR(INDEX('UK Institution Coverage'!$K$2:$K$727,MATCH($I321,'UK Institution Coverage'!$A$2:$A$727,0)),0)) | F321: =IF($I321="","",IFERROR(INDEX('UK Institution Coverage'!$M$2:$M$727,MATCH($I321,'UK Institution Coverage'!$A$2:$A$727,0)),0)) | G321: =IF($I321="","",IF($F321=3,"complete",IF($C321=0,"Research ","")&IF($D321=0,"Finance ","")&IF($E321=0,"IT/Systems",""))) | H321: =IF($I321="","",IF($F321=3,"-",IF($B321>=20,"1 - high",IF($B321>=5,"2 - medium","3 - low"))))
... B729: =IF($I729="","",IFERROR(INDEX('UK Institution Coverage'!$E$2:$E$727,MATCH($I729,'UK Institution Coverage'!$A$2:$A$727,0)),0)) | C729: =IF($I729="","",IFERROR(INDEX('UK Institution Coverage'!$F$2:$F$727,MATCH($I729,'UK Institution Coverage'!$A$2:$A$727,0)),0)) | D729: =IF($I729="","",IFERROR(INDEX('UK Institution Coverage'!$J$2:$J$727,MATCH($I729,'UK Institution Coverage'!$A$2:$A$727,0)),0)) | E729: =IF($I729="","",IFERROR(INDEX('UK Institution Coverage'!$K$2:$K$727,MATCH($I729,'UK Institution Coverage'!$A$2:$A$727,0)),0)) | F729: =IF($I729="","",IFERROR(INDEX('UK Institution Coverage'!$M$2:$M$727,MATCH($I729,'UK Institution Coverage'!$A$2:$A$727,0)),0)) | G729: =IF($I729="","",IF($F729=3,"complete",IF($C729=0,"Research ","")&IF($D729=0,"Finance ","")&IF($E729=0,"IT/Systems",""))) | H729: =IF($I729="","",IF($F729=3,"-",IF($B729>=20,"1 - high",IF($B729>=5,"2 - medium","3 - low"))))

Sheet Monthly Persona Email Report
A1: Monthly Persona Email Report
A2: One block per month. Zero is a valid answer — the point is to show the gap.
A4: Month: ____________
A5: Persona | B5: Emails sent | C5: Contacts reached | D5: Planned next month | E5: Monthly target | F5: Gap to target | G5: Notes
A6: Research — senior | E6: 2 | F6: =IF(B6="","",B6-E6)
A7: Research — operational | E7: 2 | F7: =IF(B7="","",B7-E7)
A8: Finance | E8: 2 | F8: =IF(B8="","",B8-E8)
A9: IT/Systems | E9: 2 | F9: =IF(B9="","",B9-E9)
A10: Total | B10: =SUM(B6:B9) -> 0 | D10: =SUM(D6:D9) -> 0
A13: Month: ____________
A14: Persona | B14: Emails sent | C14: Contacts reached | D14: Planned next month | E14: Monthly target | F14: Gap to target | G14: Notes
A15: Research — senior | E15: 2 | F15: =IF(B15="","",B15-E15)
A16: Research — operational | E16: 2 | F16: =IF(B16="","",B16-E16)
A17: Finance | E17: 2 | F17: =IF(B17="","",B17-E17)
A18: IT/Systems | E18: 2 | F18: =IF(B18="","",B18-E18)
A19: Total | B19: =SUM(B15:B18) -> 0 | D19: =SUM(D15:D18) -> 0
A22: Month: ____________
A23: Persona | B23: Emails sent | C23: Contacts reached | D23: Planned next month | E23: Monthly target | F23: Gap to target | G23: Notes
A24: Research — senior | E24: 2 | F24: =IF(B24="","",B24-E24)
A25: Research — operational | E25: 2 | F25: =IF(B25="","",B25-E25)
A26: Finance | E26: 2 | F26: =IF(B26="","",B26-E26)
A27: IT/Systems | E27: 2 | F27: =IF(B27="","",B27-E27)
A28: Total | B28: =SUM(B24:B27) -> 0 | D28: =SUM(D24:D27) -> 0
A31: Target is 2 emails per persona per month, 3 maximum. A negative gap means that persona is under-contacted; above 3 means over-contacted.

Sheet Marketing Performance Report
A1: Rolling Monthly Marketing Performance
A2: Enquiries and form completions are the objective. Clicks are a step, not the goal.
A4: HEADLINE METRICS
A5: Metric | B5: Month 1 | C5: Month 2 | D5: Month 3 | E5: Month 4 | F5: Month 5 | G5: Month 6
A6: Emails sent
A7: Emails delivered
A8: Delivery rate | B8: =IFERROR(B7/B6,"") | C8: =IFERROR(C7/C6,"") | D8: =IFERROR(D7/D6,"") | E8: =IFERROR(E7/E6,"") | F8: =IFERROR(F7/F6,"") | G8: =IFERROR(G7/G6,"")
A9: Opened
A10: Open rate | B10: =IFERROR(B9/B7,"") | C10: =IFERROR(C9/C7,"") | D10: =IFERROR(D9/D7,"") | E10: =IFERROR(E9/E7,"") | F10: =IFERROR(F9/F7,"") | G10: =IFERROR(G9/G7,"")
A11: Clicks
A12: Click rate | B12: =IFERROR(B11/B7,"") | C12: =IFERROR(C11/C7,"") | D12: =IFERROR(D11/D7,"") | E12: =IFERROR(E11/E7,"") | F12: =IFERROR(F11/F7,"") | G12: =IFERROR(G11/G7,"")
A13: Form completions / downloads
A14: Enquiries generated
A15: Click-to-enquiry rate | B15: =IFERROR(B14/B11,"") | C15: =IFERROR(C14/C11,"") | D15: =IFERROR(D14/D11,"") | E15: =IFERROR(E14/E11,"") | F15: =IFERROR(F14/F11,"") | G15: =IFERROR(G14/G11,"")
A16: Bounces
A17: Bounce rate | B17: =IFERROR(B16/B6,"") | C17: =IFERROR(C16/C6,"") | D17: =IFERROR(D16/D6,"") | E17: =IFERROR(E16/E6,"") | F17: =IFERROR(F16/F6,"") | G17: =IFERROR(G16/G6,"")
A18: Unsubscribes
A21: BY CONTENT TYPE
A22: Content type | B22: Sent | C22: Opened | D22: Clicks | E22: Form completions | F22: Enquiries | G22: Notes
A23: Whitepaper email
A24: Event email
A25: Product email
A26: Newsletter
A27: Other informational
A30: BEST vs WORST PERFORMING
B31: Best performing | C31: Worst performing | D31: What differed | E31: What we change next
A32: Email name
A33: Audience / persona
A34: Subject line
A35: Send day & time
A36: Email length
A37: Call to action
A38: Open rate
A39: Click rate
A40: Enquiries

Sheet Persona - To Review
A1: Sheet | B1: Row | C1: Job Title | D1: Institution | E1: Persona applied | F1: Why flagged
A2: Relevant - In CRM unknown | B2: 744 | C2: Acting Head of Research Finance | D2: Cardiff University | E2: Finance | F2: Research/Finance hybrid - confirm
A3: Relevant - In CRM valid | B3: 3204 | C3: Associate Professor In Accounting/Departmental Research Director | D3: University Of Nottingham | E3: Finance | F3: Research/Finance hybrid - confirm
A4: Relevant - In CRM valid | B4: 1706 | C4: Finance Post Award Analyst | D4: Liverpool School Of Tropical Medicine | E4: Finance | F4: Research/Finance hybrid - confirm
A5: Relevant - In CRM unknown | B5: 705 | C5: Head of Finance - Research & Innovation | D5: Sheffield Hallam University | E5: Finance | F5: Research/Finance hybrid - confirm
A6: Relevant - In CRM valid | B6: 1770 | C6: Head of Financial Planning and Analysis (FP&A) & Research | D6: Middlesex University | E6: Finance | F6: Research/Finance hybrid - confirm
A7: Relevant - In CRM unknown | B7: 695 | C7: Head of Research & Enterprise Finance | D7: Aston University | E7: Finance | F7: Research/Finance hybrid - confirm
A8: Relevant - In CRM unknown | B8: 694 | C8: Head of Research Accounting, Monitoring and Claims | D8: Cranfield University | E8: Finance | F8: Research/Finance hybrid - confirm
A9: Relevant - In CRM unknown | B9: 691 | C9: Head of Spatial Finance Initiative / Head of Innovation and Impact, CGFI | D9: University of Oxford | E9: Finance | F9: Research/Finance hybrid - confirm
A10: Relevant - In CRM unknown | B10: 688 | C10: Head of Transition Finance Research, Oxford Sustainable Finance Group | D10: University of Oxford | E10: Finance | F10: Research/Finance hybrid - confirm
A11: Relevant - In CRM unknown | B11: 684 | C11: Interim Head of Research, Finance and Governance | D11: University of Liverpool | E11: Finance | F11: Research/Finance hybrid - confirm
A12: Relevant - In CRM valid | B12: 3066 | C12: Laboratory And Finance Manager | D12: The University of Edinburgh | E12: Finance | F12: Research/Finance hybrid - confirm
A13: Relevant - In CRM valid | B13: 1393 | C13: Post Award Finance And Project Officer | D13: Durham University | E13: Finance | F13: Research/Finance hybrid - confirm
... A23: Relevant - In CRM valid | B23: 3354 | C23: Senior Research Finance Officer | D23: University of Sussex | E23: Finance | F23: Research/Finance hybrid - confirm
A24: Relevant - In CRM valid | B24: 2515 | C24: (no job title) | D24: Pearson | F24: blank title
A25: Relevant - In CRM valid | B25: 2516 | C25: (no job title) | D25: Stanford University | F25: blank title
A26: Relevant - In CRM valid | B26: 2517 | C26: (no job title) | D26: Brown University | F26: blank title
A27: Relevant - In CRM valid | B27: 2518 | C27: (no job title) | D27: Brown University | F27: blank title
A28: Relevant - In CRM valid | B28: 2519 | C28: (no job title) | D28: Brown University | F28: blank title
A29: Relevant - In CRM valid | B29: 2520 | C29: (no job title) | D29: Pearson | F29: blank title
A30: Relevant - In CRM valid | B30: 2521 | C30: (no job title) | D30: Brown University | F30: blank title
A31: Relevant - In CRM valid | B31: 2522 | C31: (no job title) | D31: Brown University | F31: blank title
A32: Relevant - In CRM valid | B32: 2523 | C32: (no job title) | D32: Brown University | F32: blank title
A33: Relevant - In CRM valid | B33: 2524 | C33: (no job title) | D33: Brown University | F33: blank title
A34: Relevant - In CRM valid | B34: 2525 | C34: (no job title) | D34: University of Nottingham | F34: blank title
A35: Relevant - In CRM valid | B35: 2526 | C35: (no job title) | D35: Pearson | F35: blank title
... A37: Relevant - In CRM valid | B37: 2528 | C37: (no job title) | D37: Brown University | F37: blank title
A38: Relevant - In CRM valid | B38: 2529 | C38: (no job title) | F38: blank title
A39: Relevant - In CRM valid | B39: 1321 | C39: (profile page unavailable) | D39: Coventry University | F39: no signal
A40: Relevant - In CRM valid | B40: 2722 | C40: Acting Team Leader Schools Of Business & Management | D40: Queen Mary University Of London | F40: no signal
A41: Relevant - In CRM valid | B41: 1341 | C41: Acting University Director | D41: Danmarks Tekniske Universitet - DTU | F41: no signal
A42: Relevant - In CRM valid | B42: 3487 | C42: Administrative Director | D42: University of Fribourg | F42: no signal
A43: Relevant - In CRM valid | B43: 1453 | C43: Administrative Executive Director | D43: GFZ Helmholtz Centre for Geosciences | F43: no signal
A44: Relevant - In CRM valid | B44: 1350 | C44: Administrative Officer, AFRI | D44: Danmarks Tekniske Universitet - DTU | F44: no signal
A45: Relevant - In CRM valid | B45: 3370 | C45: Administrator | D45: University of Sussex | F45: no signal
A46: Relevant - In CRM valid | B46: 3666 | C46: Administrator, Moross Integrated Cancer Center | D46: Weizmann Institute of Science | F46: no signal
A47: Relevant - In CRM valid | B47: 3633 | C47: Assistant Director | D47: University of York | F47: no signal
A48: Relevant - In CRM valid | B48: 1472 | C48: Assistant Director - Higher Education | D48: Centrus | F48: no signal
A49: Relevant - In CRM valid | B49: 3380 | C49: Associate Director | D49: University of Sussex | F49: no signal
A50: Relevant - In CRM valid | B50: 1661 | C50: Business Improvement & Compliance Manager | D50: Historic Environment Scotland | F50: no signal
... A321: Relevant - In CRM valid | B321: 2683 | C321: Workday Application Team Manager (HCM) | D321: Nuffield Health | F321: no signal
A322: Relevant - In CRM valid | B322: 4010, 4017 | C322: Aarti Rayrella | D322: Birkbeck, University of London / California Polytechnic State University-San Luis Obispo | F322: same LinkedIn profile at more than one institution - which is current?
A323: Relevant - In CRM valid | B323: 4007, 4014 | C323: Ada Yang | D323: Birkbeck, University of London / California Polytechnic State University | F323: same LinkedIn profile at more than one institution - which is current?
A324: Relevant - In CRM valid | B324: 4009, 4016 | C324: Adam Bayliss | D324: Keele University / California Polytechnic State University | F324: same LinkedIn profile at more than one institution - which is current?
A325: Relevant - In CRM valid | B325: 4008, 4015 | C325: Adam Taylor | D325: University of Bristol / California Polytechnic State University | F325: same LinkedIn profile at more than one institution - which is current?
A326: Relevant - In CRM valid | B326: 602, 4529 | C326: Amanda Pixton | D326: University of East London / University of Manchester | F326: same LinkedIn profile at more than one institution - which is current?
A327: Relevant - In CRM valid | B327: 598, 3998 | C327: Amer Alwarea | D327: University of the Arts London / University for the Creative Arts | F327: same LinkedIn profile at more than one institution - which is current?
A328: Relevant - In CRM valid | B328: 595, 4656, 4667 | C328: Andreas Fring | D328: City St George's, University of London / City University Of London / Stanford University | F328: same LinkedIn profile at more than one institution - which is current?
A329: Relevant - In CRM valid | B329: 548, 4654, 4665 | C329: Beth Lockhart | D329: Heriot-Watt University / University of Strathclyde / Staffordshire University | F329: same LinkedIn profile at more than one institution - which is current?
A330: Relevant - In CRM valid | B330: 534, 4669 | C330: Catherine Jones | D330: University Of Exeter / Stanford University | F330: same LinkedIn profile at more than one institution - which is current?
A331: Relevant - In CRM valid | B331: 4013, 4020 | C331: David Amigoni | D331: Keele University / Canterbury Christ Church University | F331: same LinkedIn profile at more than one institution - which is current?
A332: Relevant - In CRM valid | B332: 396, 4575 | C332: Ian Dickens | D332: University of Roehampton London / London Metropolitan University | F332: same LinkedIn profile at more than one institution - which is current?
A333: Relevant - In CRM valid | B333: 348, 4333 | C333: John Montgomery | D333: City St George's, University of London / City University Of London | F333: same LinkedIn profile at more than one institution - which is current?
... A350: Relevant - In CRM valid | B350: 4650, 4661 | C350: Jo Harris | D350: Appalachian State University / Solent University (Southampton) | F350: same LinkedIn profile at more than one institution - which is current?

Sheet Relevant - In CRM valid
A1: LinkedIn URL | B1: First Name | C1: Last Name | D1: Company / Account Name | E1: Account In ZOHO CRM | F1: Job Title | G1: Country | H1: Email | I1: Mobile | J1: Direct | K1: Office | L1: HQ | M1: Persona | N1: Band | O1: Reason | P1: Source(s) | Q1: Snov Status | R1: Research Tier | S1: Persona Check | T1: Institution (canonical) | U1: Alternate Email | V1: Moved from
A2: https://www.linkedin.com/sales/lead/ACwAABwlB2YB7R0kIBaNDmlthZEM0BWV3w58PCQ | B2: Peter | C2: Welsh | D2: The Manchester Metropolitan University | E2: Yes | F2: Contracts Manager | G2: UK | H2: p.welsh@mmu.ac.uk | M2: Research | N2: Review | O2: Contracts (research context assumed) | P2: Worktribe | Q2: valid | R2: Operational | T2: manchester metropolitan university
A3: https://www.linkedin.com/sales/lead/ACwAABn6CbsBGljKSxtJLf1F406jGoSL6U1nB34 | B3: Rohinder | C3: Bains | D3: The Manchester Metropolitan University | E3: Yes | F3: Research and Innovation Contracts Manager | G3: UK | H3: r.bains@mmu.ac.uk | M3: Research | N3: Keep | O3: Research & Innovation | P3: Worktribe | Q3: valid | R3: Operational | T3: manchester metropolitan university
A4: https://www.linkedin.com/sales/lead/ACwAAAi6C7oB7U5BtUoq5IAPJ7vi8nqmJ8Wdncg,NAME_SEARCH,KTvL?_ntb=v3Inm3E0RIiQBuBSF3Umhg%3D%3D | B4: Jose | C4: Magalhaes | D4: University of Roehampton London | E4: Yes | F4: Head Of Research And Knowledge Exchange Development | G4: UK | H4: jose.magalhaes@roehampton.ac.uk | M4: Research | N4: Keep | O4: Research & Knowledge Exchange | P4: masterlist-141uni, masterlist-ukuni, ARMA-Prospect-Verified Contacts, Masterlist-UK, masterlist-all, GN-Already Approached | Q4: valid | R4: Senior | T4: roehampton london university
A5: https://www.linkedin.com/sales/lead/ACwAAAdmsSsBQaHnBMImL0TkvOeWUrFX3WiMIzg | B5: Alona | C5: Kiriak | D5: The Manchester Metropolitan University | E5: Yes | F5: Research & Innovation Contracts Manager | G5: UK | H5: a.kiriak@mmu.ac.uk | M5: Research | N5: Keep | O5: Research & Innovation | P5: Worktribe | Q5: valid | R5: Operational | T5: manchester metropolitan university
A6: https://www.linkedin.com/in/zulfi/ | B6: Zulfiqur | C6: Ali | D6: University of Cumbria | E6: Yes | F6: Pro Vice Chancellor, Research And Knowledge Exchan | G6: UK | H6: zulfiqur.ali@cumbria.ac.uk | M6: Research | N6: Keep | O6: PVC/DVC Research | P6: Masterlist-UK, Masterlist-UAE, masterlist-all, GN-Already Approached, masterlist-141uni, ARMA-Prospect-Verified Contacts | Q6: valid | R6: Senior | T6: cumbria university
A7: https://www.linkedin.com/in/yvonne-barnett-270a0629/ | B7: Yvonne | C7: Barnett | D7: Anglia Ruskin University | E7: Yes | F7: Deputy Vice Chancellor (Research and Innovation) | G7: UK | H7: yvonne.barnett@aru.ac.uk | I7: +44 1245 493131 | M7: Research | N7: Keep | O7: PVC/DVC Research | P7: masterlist-141uni, GN-Untouched - UK, ARMA-Prospect-Verified Contacts, Masterlist-UK, masterlist-all, masterlist-ukuni, Worktribe | Q7: valid | R7: Senior | T7: anglia ruskin university
A8: https://www.linkedin.com/in/yochai-shavit-03a40758 | B8: Yochai | C8: Shavit | D8: Stanford University | E8: Yes | F8: Director Of Research | G8: USA | H8: yochais@stanford.edu | M8: Research | N8: Keep | O8: Director of Research | P8: GN-Untouched - USA, masterlist-usa, masterlist-all | Q8: valid | R8: Senior | T8: stanford university
A9: https://www.linkedin.com/in/xc-finance | B9: Xing | C9: Chang | D9: Stanford University | E9: Yes | F9: Senior Director Of Finance | G9: USA | H9: xingchang@stanford.edu | M9: Finance | N9: Keep | O9: Director of Finance | P9: GN-Untouched - USA, masterlist-usa, masterlist-all | Q9: valid | T9: stanford university
A10: https://www.linkedin.com/in/william-morrison-746ba987/ | B10: William | C10: Morrison | D10: University of Glasgow | E10: Yes | F10: Head of IT - College of Science & Engineering | G10: UK | H10: william.morrison@glasgow.ac.uk | M10: IT/Systems | N10: Keep | O10: IT Director / Head of IT | P10: masterlist-ukuni, GN-Untouched - UK, masterlist-all | Q10: valid | T10: glasgow university
A11: https://www.linkedin.com/in/vincent-fusco-53937640 | B11: Vincent | C11: Fusco | D11: Queen's University Belfast | E11: Yes | F11: Research Director | G11: UK | H11: v.fusco@qub.ac.uk | M11: Research | N11: Keep | O11: Director of Research | P11: masterlist-141uni, GN-Already Approached, masterlist-ukuni, ARMA-Prospect-Verified Contacts, Masterlist-UK, masterlist-all | Q11: valid | R11: Senior | T11: queen s university belfast
A12: https://www.linkedin.com/in/viktoriia-pryima-8b7765224 | B12: Viktoriia | C12: Pryima | D12: Queen Mary University of London | E12: Yes | F12: Assistant Post-Award Research Finance Manager | G12: UK | H12: v.pryima@qmul.ac.uk | M12: Research | N12: Keep | O12: Pre/Post-Award | P12: Worktribe | Q12: valid | R12: Operational | T12: queen mary university of london
A13: https://www.linkedin.com/in/victoria-holt-b2369b2b9 | B13: Victoria | C13: Holt | D13: The Manchester Metropolitan University | E13: Yes | F13: Director Of Research Development & Delivery | G13: UK | H13: v.holt@mmu.ac.uk | L13: +44 161 247 2000 | M13: Research | N13: Keep | O13: Director of Research | P13: Masterlist-UK, masterlist-141uni, GN-Already Approached, ARMA-Prospect-Verified Contacts, masterlist-ukuni, masterlist-all, Worktribe | Q13: valid | R13: Senior | T13: manchester metropolitan university
A14: https://www.linkedin.com/in/victoria-cabrera-sharp | B14: Victoria | C14: Sharp | D14: University of Birmingham | E14: Yes | F14: Director Operations (Research & Knowledge Transfer | G14: UK | H14: v.sharp@bham.ac.uk | M14: Research | N14: Keep | O14: Research signal (reclassified from Irrelevant) | P14: Worktribe, masterlist-141uni, masterlist-ukuni, GN-Untouched - UK, ARMA-Prospect-Unknown Contacts, Masterlist-UK, masterlist-all | Q14: valid | R14: Senior | T14: birmingham university
A15: https://www.linkedin.com/in/vasubhatiaa | B15: Vasu | C15: Bhatia | D15: University of Lincoln | E15: Yes | F15: Finance And Grants Manager | G15: UK | H15: vbhatia@lincoln.ac.uk | M15: Research | N15: Keep | O15: Grants role | P15: Worktribe | Q15: valid | R15: Operational | T15: lincoln university
A16: https://www.linkedin.com/in/valentina-guerrieri-746aa9246 | B16: Valentina | C16: Guerrieri | D16: University of Edinburgh | E16: Yes | F16: EFI Head Of Research Support | G16: UK | H16: valentina.guerrieri@ed.ac.uk | M16: Research | N16: Keep | O16: Head of Research / Research Office | P16: masterlist-141uni, ARMA-Prospect-Verified Contacts, Masterlist-UK, GN-Already Approached, Worktribe | Q16: valid | R16: Senior | T16: edinburgh university
A17: https://www.linkedin.com/in/tshegofatso-seabi/ | B17: Tshegofatso | C17: Seabi | D17: University of Manchester | E17: Yes | F17: Strategic Research Facilitator | G17: UK | H17: Tshegofatso.Seabi@manchester.ac.uk | L17: +44 (0)161 306 6000 | M17: Research | N17: Keep | O17: Research office role | P17: ARMA-Leads | Q17: valid | R17: Operational | T17: manchester university
A18: https://www.linkedin.com/in/trudie-wardle-aba375207 | B18: Trudie | C18: Wardle | D18: University of Leicester | E18: Yes | F18: Head of Pre-Award and Contracts | G18: UK | H18: ta16@leicester.ac.uk | M18: Research | N18: Keep | O18: Pre/Post-Award | P18: Worktribe, masterlist-141uni, masterlist-ukuni, GN-Untouched - UK, ARMA-Prospect-Verified Contacts, Masterlist-UK, masterlist-all | Q18: valid | R18: Senior | T18: leicester university
A19: https://www.linkedin.com/in/trevor-keeble-955127162 | B19: Trevor | C19: Keeble | D19: University of the Arts London | E19: Yes | F19: Pro Vice-Chancellor - Research, Knowledge Exchange | G19: UK | H19: t.keeble@arts.ac.uk | M19: Research | N19: Keep | O19: PVC/DVC Research | P19: masterlist-141uni, masterlist-ukuni, GN-Untouched - UK, ARMA-Prospect-Verified Contacts, Masterlist-UK, masterlist-all, Worktribe | Q19: valid | R19: Senior | T19: the arts london university
A20: https://www.linkedin.com/in/tracey-edward-34804487 | B20: Tracey | C20: Edward | D20: University of Edinburgh | E20: Yes | F20: Head Of Finance | G20: UK | H20: tracey.edward@ed.ac.uk | M20: Finance | N20: Keep | O20: Head of Finance | P20: masterlist-141uni, Masterlist-UK, GN-Already Approached, Worktribe | Q20: valid | T20: edinburgh university
A21: https://www.linkedin.com/in/tom-king-hpc | B21: Tom | C21: King | D21: Queen Mary University of London | E21: Yes | F21: Assistant Director For Research | G21: UK | H21: T.King@qmul.ac.uk | M21: Research | N21: Review | O21: Research signal - academic research leadership (reclassified; verify) | P21: Worktribe | Q21: valid | R21: Senior | T21: queen mary university of london
A22: https://www.linkedin.com/in/tmoscati | B22: Tricia | C22: Moscati | D22: Heriot-Watt University | E22: Yes | F22: Head of Digital Trans | G22: UK | H22: t.moscati@hw.ac.uk | I22: +44 131 451 8017 | M22: IT/Systems | N22: Keep | O22: IT / Information Services leadership | P22: Masterlist-UAE, masterlist-all, Worktribe | Q22: valid | T22: heriot watt university
A23: https://www.linkedin.com/in/timothy-o-shea-780a7693 | B23: Timothy | C23: O'shea | D23: University of Edinburgh | E23: Yes | F23: Principal & Vice-Chancellor | G23: UK | H23: timothy.oshea@ed.ac.uk | M23: Research | N23: Keep | O23: Vice Chancellor | P23: Worktribe | Q23: valid | R23: Senior | T23: edinburgh university
A24: https://www.linkedin.com/in/timothygiles1/ | B24: Tim | C24: Giles | D24: University of Birmingham | E24: Yes | F24: Researcher Development Manager | G24: UK | H24: t.giles@bham.ac.uk | M24: Research | N24: Review | O24: Research signal (reclassified batch 2; verify) | P24: Worktribe | Q24: valid | R24: Academic | T24: birmingham university
A25: https://www.linkedin.com/in/tim-brooks-242a6345/ | B25: Tim | C25: Brooks | D25: Anglia Ruskin University | E25: Yes | F25: Assistant Director Research & Innovation Dev | G25: UK | H25: Tim.Brooks@aru.ac.uk | M25: Research | N25: Keep | O25: Director of Research | P25: masterlist-141uni, GN-Already Approached, ARMA-Prospect-Verified Contacts, Masterlist-UK, masterlist-all, masterlist-ukuni, Worktribe | Q25: valid | R25: Senior | T25: anglia ruskin university | U25: tim.brooks@anglia.ac.uk
A26: https://www.linkedin.com/in/thomas-skeen-98254079 | B26: Thomas | C26: Skeen | D26: Queen Mary University of London | E26: Yes | F26: Director Of Finance | G26: UK | H26: t.skeen@qmul.ac.uk | I26: +44 7976 851662 | M26: Finance | N26: Keep | O26: Director of Finance | P26: masterlist-141uni, GN-Untouched - UK, Masterlist-UK, Worktribe | Q26: valid | T26: queen mary university of london
A27: https://www.linkedin.com/in/thomas-madden-15316894 | B27: Thomas | C27: Madden | D27: University of the Arts London | E27: Yes | F27: Research Team Manager | G27: UK | H27: t.madden@fashion.arts.ac.uk | M27: Research | N27: Keep | O27: Research Office Manager / Officer | P27: Worktribe, masterlist-141uni, masterlist-ukuni, ARMA-Prospect-Verified Contacts, Masterlist-UK, masterlist-all, GN-Already Approached | Q27: valid | R27: Operational | T27: the arts london university
A28: https://www.linkedin.com/in/theodoralolaluz | B28: Theodora | C28: Lola | D28: University of Edinburgh | E28: Yes | F28: Head Of Research Development | G28: UK | H28: theodora.lola-luz@ed.ac.uk | M28: Research | N28: Keep | O28: Head of Research / Research Office | P28: masterlist-141uni, GN-Untouched - UK, ARMA-Prospect-Verified Contacts, Worktribe | Q28: valid | R28: Senior | T28: edinburgh university
A29: https://www.linkedin.com/in/tarlprow | B29: Tarl | C29: Prow | D29: University of York | E29: Yes | F29: Assoc Pro-VC Research | G29: UK | H29: tarl.prow@york.ac.uk | I29: +44 7415 240478 | M29: Research | N29: Keep | O29: Pro-VC Research | P29: Worktribe | Q29: valid | R29: Senior | T29: york university
A30: https://www.linkedin.com/in/taneisha-messaoud-2a106359 | B30: Taneisha | C30: Messaoud | D30: The Manchester Metropolitan University | E30: Yes | F30: Senior Contracts Manager | G30: UK | H30: t.messaoud@mmu.ac.uk | I30: +44 7772 265580 | M30: Research | N30: Review | O30: Contracts (research context assumed) | P30: Worktribe | Q30: valid | R30: Operational | T30: manchester metropolitan university
A31: https://www.linkedin.com/in/tana-licsandru | B31: Tana | C31: Licsandru | D31: Queen Mary University of London | E31: Yes | F31: Co-Director Of MINDS Research Group | G31: UK | H31: t.licsandru@qmul.ac.uk | I31: +44 7514 255635 | M31: Research | N31: Review | O31: Research signal - academic research leadership (reclassified; verify) | P31: Worktribe | Q31: valid | R31: Senior | T31: queen mary university of london
A32: https://www.linkedin.com/in/tajalli-keshavarz-b7a2a520 | B32: Tajalli | C32: Keshavarz | D32: University of Westminster | E32: Yes | F32: Research Director | G32: UK | H32: keshavt@westminster.ac.uk | M32: Research | N32: Keep | O32: Director of Research | P32: masterlist-141uni, masterlist-ukuni, ARMA-Prospect-Verified Contacts, Masterlist-UK, masterlist-all, GN-Already Approached | Q32: valid | R32: Senior | T32: westminster university
A33: https://www.linkedin.com/in/tahya-chowdhury-89062369/ | B33: Tahya | C33: Chowdhury | D33: Queen Mary University of London | E33: Yes | F33: International Research Support | G33: UK | H33: tahya.chowdhury@qmul.ac.uk | M33: Research | N33: Keep | O33: Research support office | P33: Worktribe | Q33: valid | R33: Operational | T33: queen mary university of london
A34: https://www.linkedin.com/in/suzywhoriskey | B34: Suzy | C34: Whoriskey | D34: University of Strathclyde | E34: Yes | F34: Associate Director Of Knowledge Exchange | G34: UK | H34: suzy.whoriskey@strath.ac.uk | M34: Research | N34: Keep | O34: Knowledge Exchange | P34: masterlist-141uni, masterlist-ukuni, ARMA-Prospect-Verified Contacts, Masterlist-UK, masterlist-all, GN-Already Approached | Q34: valid | R34: Senior | T34: strathclyde university
A35: https://www.linkedin.com/in/suzannahturner/ | B35: Suzannah | C35: Turner | D35: University of Glasgow | E35: Yes | F35: Research Development Manager (Interdisciplinarity) | G35: UK | H35: Suzannah.Turner@glasgow.ac.uk | M35: Research | N35: Keep | O35: Research office role | P35: GN-Untouched - UK, ARMA-Prospect-Verified Contacts, masterlist-141uni, Masterlist-UK, masterlist-all | Q35: valid | R35: Operational | T35: glasgow university
A36: https://www.linkedin.com/in/susan-mulhearn-2b5ba7a9 | B36: Susan | C36: Mulhearn | D36: Queen Margaret University | E36: Yes | F36: Head Of Research Grants And Contracts Unit | G36: UK | H36: smulhearn@qmu.ac.uk | I36: +44 7944 965280 | M36: Research | N36: Keep | O36: Head of Research / Research Office | P36: masterlist-141uni, GN-Already Approached, ARMA-Client-Verified Contacts, Masterlist-UK | Q36: valid | R36: Senior | T36: queen margaret university
A37: https://www.linkedin.com/in/susan-mcpheat-3a0969240 | B37: Susan | C37: McPheat | D37: City St George's, University of London | E37: Yes | F37: Director of Finance | G37: UK | H37: smcpheat@citystgeorges.ac.uk | M37: Finance | N37: Keep | O37: Director of Finance | P37: Worktribe | Q37: valid | T37: city st george s university of london
A38: https://www.linkedin.com/in/susan-coupar-ba25ab3b/ | B38: Susan | C38: Coupar | D38: Abertay University | E38: Yes | F38: Head of IT Service Delivery | G38: UK | H38: s.coupar@abertay.ac.uk | M38: IT/Systems | N38: Keep | O38: IT / Information Services leadership | P38: masterlist-141uni, GN-Untouched - UK, masterlist-all, Masterlist-UAE | Q38: valid | T38: abertay university
A39: https://www.linkedin.com/in/susana-mourato-60b07513 | B39: Susana | C39: Mourato | D39: The London School of Economics and Political Science | E39: Yes | F39: Vice President And Pro-Vice Chancellor (Research) | G39: UK | H39: s.mourato@lse.ac.uk | I39: +44 7729 743790 | L39: +44 20 7405 7686 | M39: Research | N39: Keep | O39: VP for Research | P39: masterlist-141uni, ARMA-Prospect-Verified Contacts, GN-Already Approached, Masterlist-UK, masterlist-ukuni, masterlist-all | Q39: valid | R39: Senior | T39: london school of economics and political science
A40: https://www.linkedin.com/in/sufian-yousef-94907840 | B40: Sufian | C40: Yousef | D40: Anglia Ruskin University | E40: Yes | F40: Director Telecoms Res | G40: UK | H40: sufian.yousef@anglia.ac.uk | M40: Research | N40: Review | O40: Research signal - academic research leadership (reclassified; verify) | P40: GN-Untouched - UK, ARMA-Prospect-Removed - Out of Persona, Masterlist-UK, masterlist-all, masterlist-ukuni, Worktribe | Q40: valid | R40: Senior | T40: anglia ruskin university
A41: https://www.linkedin.com/in/stuart-wdowikowski-9ab839141 | B41: Stuart | C41: Wdowikowski | D41: University of Lincoln | E41: Yes | F41: Senior Finance Manager | G41: UK | H41: swdowikowski@lincoln.ac.uk | M41: Finance | N41: Review | O41: Bare Finance Manager (review band) | P41: Worktribe | Q41: valid | T41: lincoln university
A42: https://www.linkedin.com/in/stuart-piertney-1242aa276/ | B42: Stuart | C42: Piertney | D42: University of Aberdeen | E42: Yes | F42: Dean for Postgraduate Research | G42: UK | H42: s.piertney@abdn.ac.uk | M42: Research | N42: Review | O42: Research signal - academic research leadership (reclassified; verify) | P42: Worktribe | Q42: valid | R42: Senior | T42: aberdeen university
A43: https://www.linkedin.com/in/stuart-humphries-65a122151/ | B43: Stuart | C43: Humphries | D43: University of Lincoln | E43: Yes | F43: Interim PVC (Research and Commercialisation) | G43: UK | H43: shumphries@lincoln.ac.uk | M43: Research | N43: Keep | O43: PVC/DVC Research | P43: Worktribe | Q43: valid | R43: Senior | T43: lincoln university
A44: https://www.linkedin.com/in/stevewatt1 | B44: Steve | C44: Watt | D44: University of St Andrews | E44: Yes | F44: Chief Information Officer (CIO) | G44: UK | H44: steve.watt@st-andrews.ac.uk | J44: +441334467244 | M44: IT/Systems | N44: Keep | O44: CIO | P44: masterlist-ukuni, masterlist-all, masterlist-141uni, Masterlist-UK, GN-Already Approached, Worktribe | Q44: valid | T44: st andrews university
A45: https://www.linkedin.com/in/steve-rimell-0662835/ | B45: Steve | C45: Rimell | D45: Staffordshire University | E45: Yes | F45: Chief Financial Officer | G45: UK | H45: steve.rimell@staffs.ac.uk | M45: Finance | N45: Keep | O45: CFO | P45: GN-Untouched - UK, Masterlist-UK, masterlist-ukuni, masterlist-all | Q45: valid | T45: staffordshire university
A46: https://www.linkedin.com/in/steve-olivier-6a956396 | B46: Steve | C46: Olivier | D46: Robert Gordon University | E46: Yes | F46: Principal And Vice-Chancellor | G46: UK | H46: steve.olivier@rgu.ac.uk | I46: +44 1224 262000 | M46: Research | N46: Keep | O46: Vice Chancellor | P46: Worktribe | Q46: valid | R46: Senior | T46: robert gordon university
A47: https://www.linkedin.com/in/stevensutterby | B47: Steven | C47: Sutterby | D47: Queen Mary University of London | E47: Yes | F47: Post Award Assistant Manager | G47: UK | H47: s.sutterby@qmul.ac.uk | I47: +44 7702 700581 | M47: Research | N47: Keep | O47: Pre/Post-Award | P47: Worktribe | Q47: valid | R47: Operational | T47: queen mary university of london
A48: https://www.linkedin.com/in/steven-spoel | B48: Steven | C48: Spoel | D48: University of Edinburgh | E48: Yes | F48: Director Of Research | G48: UK | H48: steven.spoel@ed.ac.uk | M48: Research | N48: Keep | O48: Director of Research | P48: masterlist-141uni, ARMA-Prospect-Verified Contacts, Masterlist-UK, GN-Already Approached, Worktribe | Q48: valid | R48: Senior | T48: edinburgh university
A49: https://www.linkedin.com/in/stevenrichardpatterson | B49: Steven | C49: Patterson | D49: University of Huddersfield | E49: Yes | F49: Deputy Director And Head Of IT | G49: UK | H49: s.r.patterson@hud.ac.uk | M49: IT/Systems | N49: Keep | O49: IT / Information Services leadership | P49: masterlist-ukuni, GN-Untouched - UK, masterlist-all | Q49: valid | T49: huddersfield university
A50: https://www.linkedin.com/in/steve-goode-46b77252/ | B50: Steve | C50: Goode | D50: Health Sciences University | E50: Yes | F50: Head Of Information Technology | G50: UK | H50: sgoode@aecc.ac.uk | M50: IT/Systems | N50: Keep | O50: IT Director / Head of IT | P50: GN-Untouched - UK, masterlist-all, Masterlist-UK, masterlist-ukuni | Q50: valid | T50: health sciences university
A51: https://www.linkedin.com/in/steve-austin-8080a730 | B51: Steve | C51: Austin | D51: University of York | E51: Yes | F51: Business Systems Manager | G51: UK | H51: steve.austin@york.ac.uk | I51: +44 7761 921592 | M51: IT/Systems | N51: Keep | O51: Business / Research Systems | P51: Worktribe | Q51: valid | T51: york university
A52: https://www.linkedin.com/in/stephen-head-2018/ | B52: Stephen | C52: Head | D52: University of East London | E52: Yes | F52: Deputy Director of IT | G52: UK | H52: shead@uel.ac.uk | I52: +44 7539 216828 | M52: IT/Systems | N52: Keep | O52: IT / Information Services leadership | P52: masterlist-141uni, masterlist-ukuni, GN-Untouched - UK, Masterlist-UK, masterlist-all, Worktribe | Q52: valid | T52: east london university | U52: s.head@uel.ac.uk
A53: https://www.linkedin.com/in/stephen-ford-72548227 | B53: Stephen | C53: Ford | D53: Queen Mary University of London | E53: Yes | F53: Assistant Director For Research Operations | G53: UK | H53: stephen.ford@qmul.ac.uk | I53: +44 7511 664176 | M53: Research | N53: Keep | O53: Assistant Director, Research Operations | P53: masterlist-141uni, GN-Already Approached, ARMA-Prospect-Verified Contacts, Masterlist-UK, Worktribe | Q53: valid | R53: Senior | T53: queen mary university of london
A54: https://www.linkedin.com/in/stephen-cummings-0542952b | B54: Stephen | C54: Cummings | D54: Teeside University | E54: Yes | F54: Pro Vice-Chancellor Research And Knowledge Exchang | G54: UK | H54: s.cummings@tees.ac.uk | M54: Research | N54: Keep | O54: PVC/DVC Research | P54: masterlist-141uni, masterlist-ukuni, GN-Untouched - UK, ARMA-Prospect-Verified Contacts, Masterlist-UK, masterlist-all | Q54: valid | R54: Senior | T54: teeside university
